Workbook

Sheet INFO AÇÕES
A1: Ações | B1: Abreviatura do câmbio | C1: Preço | D1: Bolsa | E1: Símbolo do ticker | F1: Hora da última transação | G1: Variação | H1: Variação (%) | I1: Moeda | J1: Conversão MOEDA | K1: Preço Dolar | L1: Da moeda | M1: Moeda2
A2: #VALUE! | B2: {=_FV(A2,"Abreviatura do câmbio",TRUE)} -> BVMF | C2: {=_FV(A2,"Preço")} -> 17.81 | D2: {=_FV(A2,"Bolsa")} -> B3 - Brazil Stock Exchange | E2: {=_FV(A2,"Símbolo do ticker",TRUE)} -> BBAS3 | F2: {=_FV(A2,"Hora da última transação",TRUE)} -> 46322.66 | G2: {=_FV(A2,"Variação")} -> 0.34 | H2: {=_FV(A2,"Variação (%)",TRUE)} -> 0.019462 | I2: {=_FV(tb_acoes[[#This Row],[Ações]],"Moeda")} -> BRL | K2: {=IFERROR(_FV(J2,"Preço"),"")} | L2: {=IFERROR(_FV(J2,"Da moeda",TRUE),"")} | M2: {=IFERROR(_FV(J2,"Moeda"),"")}
A3: #VALUE! | B3: {=_FV(A3,"Abreviatura do câmbio",TRUE)} -> BVMF | C3: {=_FV(A3,"Preço")} -> 35.67 | D3: {=_FV(A3,"Bolsa")} -> B3 - Brazil Stock Exchange | E3: {=_FV(A3,"Símbolo do ticker",TRUE)} -> EQTL3 | F3: {=_FV(A3,"Hora da última transação",TRUE)} -> 46322.66 | G3: {=_FV(A3,"Variação")} -> 0.83 | H3: {=_FV(A3,"Variação (%)",TRUE)} -> 0.023823 | I3: {=_FV(tb_acoes[[#This Row],[Ações]],"Moeda")} -> BRL | K3: {=IFERROR(_FV(J3,"Preço"),"")} | L3: {=IFERROR(_FV(J3,"Da moeda",TRUE),"")} | M3: {=IFERROR(_FV(J3,"Moeda"),"")}
A4: #VALUE! | B4: {=_FV(A4,"Abreviatura do câmbio",TRUE)} -> BVMF | C4: {=_FV(A4,"Preço")} -> 25.43 | D4: {=_FV(A4,"Bolsa")} -> B3 - Brazil Stock Exchange | E4: {=_FV(A4,"Símbolo do ticker",TRUE)} -> SBSP3 | F4: {=_FV(A4,"Hora da última transação",TRUE)} -> 46322.66 | G4: {=_FV(A4,"Variação")} -> 0.16 | H4: {=_FV(A4,"Variação (%)",TRUE)} -> 0.006332 | I4: {=_FV(tb_acoes[[#This Row],[Ações]],"Moeda")} -> BRL | K4: {=IFERROR(_FV(J4,"Preço"),"")} | L4: {=IFERROR(_FV(J4,"Da moeda",TRUE),"")} | M4: {=IFERROR(_FV(J4,"Moeda"),"")}
A5: #VALUE! | B5: {=_FV(A5,"Abreviatura do câmbio",TRUE)} -> BVMF | C5: {=_FV(A5,"Preço")} -> 6.86 | D5: {=_FV(A5,"Bolsa")} -> B3 - Brazil Stock Exchange | E5: {=_FV(A5,"Símbolo do ticker",TRUE)} -> SAPR4 | F5: {=_FV(A5,"Hora da última transação",TRUE)} -> 46322.66 | G5: {=_FV(A5,"Variação")} -> 0.06 | H5: {=_FV(A5,"Variação (%)",TRUE)} -> 0.008824 | I5: {=_FV(tb_acoes[[#This Row],[Ações]],"Moeda")} -> BRL | K5: {=IFERROR(_FV(J5,"Preço"),"")} | L5: {=IFERROR(_FV(J5,"Da moeda",TRUE),"")} | M5: {=IFERROR(_FV(J5,"Moeda"),"")}
A6: #VALUE! | B6: {=_FV(A6,"Abreviatura do câmbio",TRUE)} -> BVMF | C6: {=_FV(A6,"Preço")} -> 13.97 | D6: {=_FV(A6,"Bolsa")} -> B3 - Brazil Stock Exchange | E6: {=_FV(A6,"Símbolo do ticker",TRUE)} -> ITSA3 | F6: {=_FV(A6,"Hora da última transação",TRUE)} -> 46322.66 | G6: {=_FV(A6,"Variação")} -> -0.13 | H6: {=_FV(A6,"Variação (%)",TRUE)} -> -0.00922 | I6: {=_FV(tb_acoes[[#This Row],[Ações]],"Moeda")} -> BRL | K6: {=IFERROR(_FV(J6,"Preço"),"")} | L6: {=IFERROR(_FV(J6,"Da moeda",TRUE),"")} | M6: {=IFERROR(_FV(J6,"Moeda"),"")}
A7: #VALUE! | B7: {=_FV(A7,"Abreviatura do câmbio",TRUE)} -> BVMF | C7: {=_FV(A7,"Preço")} -> 91.8 | D7: {=_FV(A7,"Bolsa")} -> B3 - Brazil Stock Exchange | E7: {=_FV(A7,"Símbolo do ticker",TRUE)} -> XPLG11 | F7: {=_FV(A7,"Hora da última transação",TRUE)} -> 46322.66 | G7: {=_FV(A7,"Variação")} -> -1.32 | H7: {=_FV(A7,"Variação (%)",TRUE)} -> -0.014175 | I7: {=_FV(tb_acoes[[#This Row],[Ações]],"Moeda")} -> BRL | K7: {=IFERROR(_FV(J7,"Preço"),"")} | L7: {=IFERROR(_FV(J7,"Da moeda",TRUE),"")} | M7: {=IFERROR(_FV(J7,"Moeda"),"")}
A8: #VALUE! | B8: {=_FV(A8,"Abreviatura do câmbio",TRUE)} -> BVMF | C8: {=_FV(A8,"Preço")} -> 149 | D8: {=_FV(A8,"Bolsa")} -> B3 - Brazil Stock Exchange | E8: {=_FV(A8,"Símbolo do ticker",TRUE)} -> HGLG11 | F8: {=_FV(A8,"Hora da última transação",TRUE)} -> 46322.66 | G8: {=_FV(A8,"Variação")} -> -2.7 | H8: {=_FV(A8,"Variação (%)",TRUE)} -> -0.017798 | I8: {=_FV(tb_acoes[[#This Row],[Ações]],"Moeda")} -> BRL | K8: {=IFERROR(_FV(J8,"Preço"),"")} | L8: {=IFERROR(_FV(J8,"Da moeda",TRUE),"")} | M8: {=IFERROR(_FV(J8,"Moeda"),"")}
A9: #VALUE! | B9: {=_FV(A9,"Abreviatura do câmbio",TRUE)} -> BVMF | C9: {=_FV(A9,"Preço")} -> 151.45 | D9: {=_FV(A9,"Bolsa")} -> B3 - Brazil Stock Exchange | E9: {=_FV(A9,"Símbolo do ticker",TRUE)} -> KNRI11 | F9: {=_FV(A9,"Hora da última transação",TRUE)} -> 46322.66 | G9: {=_FV(A9,"Variação")} -> -2 | H9: {=_FV(A9,"Variação (%)",TRUE)} -> -0.013034 | I9: {=_FV(tb_acoes[[#This Row],[Ações]],"Moeda")} -> BRL | K9: {=IFERROR(_FV(J9,"Preço"),"")} | L9: {=IFERROR(_FV(J9,"Da moeda",TRUE),"")} | M9: {=IFERROR(_FV(J9,"Moeda"),"")}
A10: #VALUE! | B10: {=_FV(A10,"Abreviatura do câmbio",TRUE)} -> BVMF | C10: {=_FV(A10,"Preço")} -> 98.61 | D10: {=_FV(A10,"Bolsa")} -> B3 - Brazil Stock Exchange | E10: {=_FV(A10,"Símbolo do ticker",TRUE)} -> BTLG11 | F10: {=_FV(A10,"Hora da última transação",TRUE)} -> 46322.66 | G10: {=_FV(A10,"Variação")} -> -1.54 | H10: {=_FV(A10,"Variação (%)",TRUE)} -> -0.015377 | I10: {=_FV(tb_acoes[[#This Row],[Ações]],"Moeda")} -> BRL | K10: {=IFERROR(_FV(J10,"Preço"),"")} | L10: {=IFERROR(_FV(J10,"Da moeda",TRUE),"")} | M10: {=IFERROR(_FV(J10,"Moeda"),"")}
A11: #VALUE! | B11: {=_FV(A11,"Abreviatura do câmbio",TRUE)} -> BVMF | C11: {=_FV(A11,"Preço")} -> 99.33 | D11: {=_FV(A11,"Bolsa")} -> B3 - Brazil Stock Exchange | E11: {=_FV(A11,"Símbolo do ticker",TRUE)} -> XPML11 | F11: {=_FV(A11,"Hora da última transação",TRUE)} -> 46322.66 | G11: {=_FV(A11,"Variação")} -> -0.87 | H11: {=_FV(A11,"Variação (%)",TRUE)} -> -0.008683 | I11: {=_FV(tb_acoes[[#This Row],[Ações]],"Moeda")} -> BRL | K11: {=IFERROR(_FV(J11,"Preço"),"")} | L11: {=IFERROR(_FV(J11,"Da moeda",TRUE),"")} | M11: {=IFERROR(_FV(J11,"Moeda"),"")}
A12: #VALUE! | B12: {=_FV(A12,"Abreviatura do câmbio",TRUE)} -> BVMF | C12: {=_FV(A12,"Preço")} -> 86.67 | D12: {=_FV(A12,"Bolsa")} -> B3 - Brazil Stock Exchange | E12: {=_FV(A12,"Símbolo do ticker",TRUE)} -> KNCA11 | F12: {=_FV(A12,"Hora da última transação",TRUE)} -> 46322.66 | G12: {=_FV(A12,"Variação")} -> -1.33 | H12: {=_FV(A12,"Variação (%)",TRUE)} -> -0.015114 | I12: {=_FV(tb_acoes[[#This Row],[Ações]],"Moeda")} -> BRL | K12: {=IFERROR(_FV(J12,"Preço"),"")} | L12: {=IFERROR(_FV(J12,"Da moeda",TRUE),"")} | M12: {=IFERROR(_FV(J12,"Moeda"),"")}
A13: #VALUE! | B13: {=_FV(A13,"Abreviatura do câmbio",TRUE)} -> BVMF | C13: {=_FV(A13,"Preço")} -> 9.02 | D13: {=_FV(A13,"Bolsa")} -> B3 - Brazil Stock Exchange | E13: {=_FV(A13,"Símbolo do ticker",TRUE)} -> MXRF11 | F13: {=_FV(A13,"Hora da última transação",TRUE)} -> 46322.66 | G13: {=_FV(A13,"Variação")} -> -0.09 | H13: {=_FV(A13,"Variação (%)",TRUE)} -> -0.009879 | I13: {=_FV(tb_acoes[[#This Row],[Ações]],"Moeda")} -> BRL | K13: {=IFERROR(_FV(J13,"Preço"),"")} | L13: {=IFERROR(_FV(J13,"Da moeda",TRUE),"")} | M13: {=IFERROR(_FV(J13,"Moeda"),"")}
... A16: #VALUE! | B16: {=_FV(A16,"Abreviatura do câmbio",TRUE)} -> BVMF | C16: {=_FV(A16,"Preço")} -> 105.28 | D16: {=_FV(A16,"Bolsa")} -> B3 - Brazil Stock Exchange | E16: {=_FV(A16,"Símbolo do ticker",TRUE)} -> KNCR11 | F16: {=_FV(A16,"Hora da última transação",TRUE)} -> 46322.66 | G16: {=_FV(A16,"Variação")} -> 0.98 | H16: {=_FV(A16,"Variação (%)",TRUE)} -> 0.009396 | I16: {=_FV(tb_acoes[[#This Row],[Ações]],"Moeda")} -> BRL | K16: {=IFERROR(_FV(J16,"Preço"),"")} | L16: {=IFERROR(_FV(J16,"Da moeda",TRUE),"")} | M16: {=IFERROR(_FV(J16,"Moeda"),"")}
A17: #VALUE! | B17: {=_FV(A17,"Abreviatura do câmbio",TRUE)} -> ARCX | C17: {=_FV(A17,"Preço")} -> 50.6625 | D17: {=_FV(A17,"Bolsa")} -> NYSE Arca | E17: {=_FV(A17,"Símbolo do ticker",TRUE)} -> TFLO | F17: {=_FV(A17,"Hora da última transação",TRUE)} -> 46322.671 | G17: {=_FV(A17,"Variação")} -> 0.0025 | H17: {=_FV(A17,"Variação (%)",TRUE)} -> 4.935e-05 | I17: {=_FV(tb_acoes[[#This Row],[Ações]],"Moeda")} -> USD | J17: #VALUE! | K17: {=IFERROR(_FV(J17,"Preço"),"")} -> 5.3414 | L17: {=IFERROR(_FV(J17,"Da moeda",TRUE),"")} -> USD | M17: {=IFERROR(_FV(J17,"Moeda"),"")} -> BRL
A18: #VALUE! | B18: {=_FV(A18,"Abreviatura do câmbio",TRUE)} -> BVMF | C18: {=_FV(A18,"Preço")} -> 8.35 | D18: {=_FV(A18,"Bolsa")} -> B3 - Brazil Stock Exchange | E18: {=_FV(A18,"Símbolo do ticker",TRUE)} -> GARE11 | F18: {=_FV(A18,"Hora da última transação",TRUE)} -> 46321.875 | G18: {=_FV(A18,"Variação")} -> -0.39 | H18: {=_FV(A18,"Variação (%)",TRUE)} -> -0.044622 | I18: {=_FV(tb_acoes[[#This Row],[Ações]],"Moeda")} -> BRL | K18: {=IFERROR(_FV(J18,"Preço"),"")} | L18: {=IFERROR(_FV(J18,"Da moeda",TRUE),"")} | M18: {=IFERROR(_FV(J18,"Moeda"),"")}
A19: #VALUE! | B19: {=_FV(A19,"Abreviatura do câmbio",TRUE)} -> ARCX | C19: {=_FV(A19,"Preço")} -> 774.07 | D19: {=_FV(A19,"Bolsa")} -> NYSE Arca | E19: {=_FV(A19,"Símbolo do ticker",TRUE)} -> IVV | F19: {=_FV(A19,"Hora da última transação",TRUE)} -> 46322.671 | G19: {=_FV(A19,"Variação")} -> 5.38 | H19: {=_FV(A19,"Variação (%)",TRUE)} -> 0.006999 | I19: {=_FV(tb_acoes[[#This Row],[Ações]],"Moeda")} -> USD | J19: #VALUE! | K19: {=IFERROR(_FV(J19,"Preço"),"")} -> 5.3414 | L19: {=IFERROR(_FV(J19,"Da moeda",TRUE),"")} -> USD | M19: {=IFERROR(_FV(J19,"Moeda"),"")} -> BRL

Sheet Planilha1
A1: Campo calculado
A2: Ordem de resolução | B2: Campo | C2: Fórmula
A3: 1 | B3: Campo1 | C3: = ('VALOR TOTAL MERCADO'-'VALOR TOTAL')/'VALOR TOTAL'
A4: 2 | B4: Campo2 | C4: ='VALOR TOTAL MERCADO' -'VALOR TOTAL'
A6: Item calculado
A7: Ordem de resolução | B7: Item | C7: Fórmula
A10: Observação: | B10: Quando uma célula é atualizada por mais de uma fórmula,
B11: o valor é definido pela fórmula com a última ordem de resolução.
B13: Para alterar a ordem de resolução de vários itens ou campos calculados,
B14: na guia Opções, no grupo Cálculos, clique em Campos, Itens e Conjuntos e clique em Ordem de Resolução.

Sheet RESUMO
B2: TIPO MOVIMENTAÇÃO | C2: Aporte
B3: FEITO? | C3: SIM
D4: R$ | E4: R$ | F4: R$ | G4: R$ | H4: R$ | I4: % | J4: %
B5: # | C5: COTAS | D5: PREÇO NEGOCIADO | E5: PREÇO MERCADO | F5: TOTAL NEGOCIADO | G5: TOTAL MERCADO | H5: GANHO/ PERDA | I5: VALORIZAÇÂO | J5: VARIAÇÃO REAL
B6: Ações | C6: 24 | D6: 22.476433 | E6: 20.622667 | F6: 427.79 | G6: 395.22 | H6: -32.57 | I6: -0.076135487 | J6: 0.0047438
B7: BBAS3 | C7: 4 | D7: 19.0425 | E7: 17.76 | F7: 76.17 | G7: 71.04 | H7: -5.13 | I7: -0.06734935 | J7: 0.0166
B8: BBSE3 | C8: 1 | D8: 41.77 | E8: 43.52 | F8: 41.77 | G8: 43.52 | H8: 1.75 | I8: 0.041896098 | J8: 0.008809
B9: EQTL3 | C9: 3 | D9: 40.853333 | E9: 35.54 | F9: 122.56 | G9: 106.62 | H9: -15.94 | I9: -0.13005875 | J9: 0.020092
B10: ITSA3 | C10: 4 | D10: 13.9275 | E10: 13.9 | F10: 55.71 | G10: 55.6 | H10: -0.11 | I10: -0.0019745109 | J10: -0.014184
B11: SAPR4 | C11: 10 | D11: 7.291 | E11: 6.72 | F11: 72.91 | G11: 67.2 | H11: -5.71 | I11: -0.078315732 | J11: -0.011765
B12: SBSP3 | C12: 2 | D12: 29.335 | E12: 25.62 | F12: 58.67 | G12: 51.24 | H12: -7.43 | I12: -0.12664053 | J12: 0.01385
B13: FIIs | C13: 33 | D13: #DIV/0! | E13: 43.252381 | F13: #DIV/0! | G13: 367.67 | H13: -4.34 | I13: -0.011666353 | J13: -0.015502333
B14: GARE11 | C14: 10 | D14: 8.473 | E14: 8.35 | F14: 84.73 | G14: 83.5 | H14: -1.23 | I14: -0.0145167 | J14: -0.044622
B15: KNSC11 | C15: 8 | D15: 8.98 | E15: 8.91 | F15: 71.84 | G15: 71.28 | H15: -0.56 | I15: -0.0077951002 | J15: -0.007795
B16: MXRF11 | C16: 14 | D16: 9.1778571 | E16: 9.01 | F16: 128.49 | G16: 126.14 | H16: -2.35 | I16: -0.018289361 | J16: -0.010977
B17: XPLG11 | D17: #DIV/0! | E17: 92.32 | F17: #DIV/0! | G17: 0 | H17: 0 | I17: #DIV/0! | J17: -0.008591
B18: HGLG11 | D18: #DIV/0! | E18: 149.68 | F18: #DIV/0! | G18: 0 | H18: 0 | I18: #DIV/0! | J18: -0.013316
B19: KNRI11 | D19: #DIV/0! | E19: 152.64 | F19: #DIV/0! | G19: 0 | H19: 0 | I19: #DIV/0! | J19: -0.005279
B20: BTLG11 | D20: #DIV/0! | E20: 98.99 | F20: #DIV/0! | G20: 0 | H20: 0 | I20: #DIV/0! | J20: -0.011583
B21: XPML11 | D21: #DIV/0! | E21: 99.91 | F21: #DIV/0! | G21: 0 | H21: 0 | I21: #DIV/0! | J21: -0.002894
B22: KNCA11 | C22: 1 | D22: 86.95 | E22: 86.75 | F22: 86.95 | G22: 86.75 | H22: -0.2 | I22: -0.0023001725 | J22: -0.014205
B23: KNCR11 | D23: #DIV/0! | E23: 104.91 | F23: #DIV/0! | G23: 0 | H23: 0 | I23: #DIV/0! | J23: 0.005849
B24: Total Geral | C24: 57 | D24: #DIV/0! | E24: 33.823333 | F24: #DIV/0! | G24: 762.89 | H24: -36.91 | I24: -0.046149037 | J24: -0.0070664444

Sheet planejamento financeiro
A3: Soma de VALOR TOTAL | B3: Rótulos de Coluna
A4: Rótulos de Linha | B4: Entradas | C4: Saídas | D4: Aporte | E4: Resultado | F4: %
A5: 2026 | B5: 32230 | C5: 12672.393 | D5: 4799.8 | E5: =B5-C5 -> 19557.607 | F5: =(1-(C5/B5)) -> 0.60681375
A6: out | D6: 799.8
A7: nov | B7: 18820 | C7: 6834.2084 | D7: 2000 | E7: =B7-C7 -> 11985.792 | F7: =(1-(C7/B7)) -> 0.63686459
A8: dez | B8: 13410 | C8: 5838.1844 | D8: 2000 | E8: =B8-C8 -> 7571.8156 | F8: =(1-(C8/B8)) -> 0.5646395
A9: 2027 | B9: 106310 | C9: 46468.516 | D9: 34000 | E9: =B9-C9 -> 59841.484 | F9: =(1-(C9/B9)) -> 0.56289609
A10: jan | B10: 13410 | C10: 4678.6835 | D10: 2500 | E10: =B10-C10 -> 8731.3165 | F10: =(1-(C10/B10)) -> 0.65110488
A11: fev | B11: 8700 | C11: 3457.6941 | D11: 2500 | E11: =B11-C11 -> 5242.3059 | F11: =(1-(C11/B11)) -> 0.6025639
A12: mar | B12: 8700 | C12: 3523.2151 | D12: 2500 | E12: =B12-C12 -> 5176.7849 | F12: =(1-(C12/B12)) -> 0.59503275
A13: abr | B13: 8700 | C13: 3586.2248 | D13: 2500 | E13: =B13-C13 -> 5113.7752 | F13: =(1-(C13/B13)) -> 0.58779025
A14: mai | B14: 8700 | C14: 3649.2241 | D14: 2500 | E14: =B14-C14 -> 5050.7759 | F14: =(1-(C14/B14)) -> 0.58054895
A15: jun | B15: 8700 | C15: 3703.8249 | D15: 2500 | E15: =B15-C15 -> 4996.1751 | F15: =(1-(C15/B15)) -> 0.574273
A16: jul | B16: 8700 | C16: 3758.4361 | D16: 2500 | E16: =B16-C16 -> 4941.5639 | F16: =(1-(C16/B16)) -> 0.56799585
A17: ago | B17: 8700 | C17: 3313.0369 | D17: 2500 | E17: =B17-C17 -> 5386.9631 | F17: =(1-(C17/B17)) -> 0.61919116
A18: set | B18: 8000 | C18: 4367.6377 | D18: 3500 | E18: =B18-C18 -> 3632.3623 | F18: =(1-(C18/B18)) -> 0.45404528
A19: out | B19: 8000 | C19: 3422.2385 | D19: 3500 | E19: =B19-C19 -> 4577.7615 | F19: =(1-(C19/B19)) -> 0.57222018
A20: nov | B20: 8000 | C20: 4476.8498 | D20: 3500 | E20: =B20-C20 -> 3523.1502 | F20: =(1-(C20/B20)) -> 0.44039378
A21: dez | B21: 8000 | C21: 4531.4506 | D21: 3500 | E21: =B21-C21 -> 3468.5494 | F21: =(1-(C21/B21)) -> 0.43356868
A22: 2028 | B22: 96000 | C22: 25846.937 | D22: 46000 | E22: =B22-C22 -> 70153.063 | F22: =(1-(C22/B22)) -> 0.73076107
A23: jan | B23: 8000 | C23: 1869.9521 | D23: 4000 | E23: =B23-C23 -> 6130.0479 | F23: =(1-(C23/B23)) -> 0.76625599
A24: fev | B24: 8000 | C24: 1920.3536 | D24: 4000 | E24: =B24-C24 -> 6079.6464 | F24: =(1-(C24/B24)) -> 0.75995579
A25: mar | B25: 8000 | C25: 1968.244 | D25: 4000 | E25: =B25-C25 -> 6031.756 | F25: =(1-(C25/B25)) -> 0.7539695
A26: abr | B26: 8000 | C26: 2015.2798 | D26: 4000 | E26: =B26-C26 -> 5984.7202 | F26: =(1-(C26/B26)) -> 0.74809002
A27: mai | B27: 8000 | C27: 2040.4858 | D27: 4000 | E27: =B27-C27 -> 5959.5142 | F27: =(1-(C27/B27)) -> 0.74493927
A28: jun | B28: 8000 | C28: 2065.6814 | D28: 4000 | E28: =B28-C28 -> 5934.3186 | F28: =(1-(C28/B28)) -> 0.74178983
A29: jul | B29: 8000 | C29: 2090.8874 | D29: 4000 | E29: =B29-C29 -> 5909.1126 | F29: =(1-(C29/B29)) -> 0.73863908
A30: ago | B30: 8000 | C30: 2110.8874 | D30: 4000 | E30: =B30-C30 -> 5889.1126 | F30: =(1-(C30/B30)) -> 0.73613908
A31: set | B31: 8000 | C31: 2116.0933 | D31: 4000 | E31: =B31-C31 -> 5883.9067 | F31: =(1-(C31/B31)) -> 0.73548833
A32: out | B32: 8000 | C32: 2532.8904 | D32: 4000 | E32: =B32-C32 -> 5467.1096 | F32: =(1-(C32/B32)) -> 0.6833887
A33: nov | B33: 8000 | C33: 2549.6874 | D33: 3000 | E33: =B33-C33 -> 5450.3126 | F33: =(1-(C33/B33)) -> 0.68128907
A34: dez | B34: 8000 | C34: 2566.4949 | D34: 3000 | E34: =B34-C34 -> 5433.5051 | F34: =(1-(C34/B34)) -> 0.67918814
A35: 2029 | B35: 96000 | C35: 33192.965 | D35: 36000 | E35: =B35-C35 -> 62807.035 | F35: =(1-(C35/B35)) -> 0.65423995
A36: jan | B36: 8000 | C36: 2583.2919 | D36: 3000 | E36: =B36-C36 -> 5416.7081 | F36: =(1-(C36/B36)) -> 0.67708851
A37: fev | B37: 8000 | C37: 2600.089 | D37: 3000 | E37: =B37-C37 -> 5399.911 | F37: =(1-(C37/B37)) -> 0.67498888
A38: mar | B38: 8000 | C38: 2616.8964 | D38: 3000 | E38: =B38-C38 -> 5383.1036 | F38: =(1-(C38/B38)) -> 0.67288795
A39: abr | B39: 8000 | C39: 2617.0631 | D39: 3000 | E39: =B39-C39 -> 5382.9369 | F39: =(1-(C39/B39)) -> 0.67286711
A40: mai | B40: 8000 | C40: 2847.0013 | D40: 3000 | E40: =B40-C40 -> 5152.9987 | F40: =(1-(C40/B40)) -> 0.64412484
A41: jun | B41: 8000 | C41: 2846.9909 | D41: 3000 | E41: =B41-C41 -> 5153.0091 | F41: =(1-(C41/B41)) -> 0.64412614
A42: jul | B42: 8000 | C42: 2846.9804 | D42: 3000 | E42: =B42-C42 -> 5153.0196 | F42: =(1-(C42/B42)) -> 0.64412744
A43: ago | B43: 8000 | C43: 2846.9596 | D43: 3000 | E43: =B43-C43 -> 5153.0404 | F43: =(1-(C43/B43)) -> 0.64413005
A44: set | B44: 8000 | C44: 2846.9492 | D44: 3000 | E44: =B44-C44 -> 5153.0508 | F44: =(1-(C44/B44)) -> 0.64413135
A45: out | B45: 8000 | C45: 2846.9283 | D45: 3000 | E45: =B45-C45 -> 5153.0717 | F45: =(1-(C45/B45)) -> 0.64413396
A46: nov | B46: 8000 | C46: 2846.9179 | D46: 3000 | E46: =B46-C46 -> 5153.0821 | F46: =(1-(C46/B46)) -> 0.64413526
A47: dez | B47: 8000 | C47: 2846.8971 | D47: 3000 | E47: =B47-C47 -> 5153.1029 | F47: =(1-(C47/B47)) -> 0.64413787
A48: Total Geral | B48: 330540 | C48: 118180.81 | D48: 120799.8 | E48: =B48-C48 -> 212359.19 | F48: =(1-(C48/B48)) -> 0.64246139

Sheet Base de dados
G2: SUM | H2: AVERAGE | J2: SUM
G3: =SUBTOTAL(109,G5:G1048576) -> 1 | H3: =SUBTOTAL(1,H5:H1048576) -> 86.95 | J3: =SUBTOTAL(109,J5:J1048576) -> 86.95 | Q3: =SUBTOTAL(1,Q5:Q1048576) -> 86.67 | R3: =SUBTOTAL(109,R5:R1048576) -> 86.67 | S3: =SUBTOTAL(109,S5:S1048576) -> -0.28 | T3: =SUBTOTAL(1,T5:T1048576) -> -0.015114 | U3: =SUBTOTAL(1,U5:U1048576) -> -0.0032202415
B4: TIPO MOVIMENTAÇÃO | C4: DATA | D4: DESCRIÇÃO | E4: MOEDA | F4: ATIVO | G4: QUANTIDADE | H4: PREÇO | I4: CORRETORA/BANCO | J4: VALOR TOTAL | K4: FEITO? | L4: Mês | M4: Ano | N4: Dia | O4: PREÇO MÉDIO PONDERADO | P4: VALOR TOTAL PONDERADO | Q4: PREÇO MERCADO | R4: VALOR TOTAL MERCADO | S4: GANHO/PERDA | T4: VARIAÇÃO (%) | U4: VALORIZAÇÃO (%)
B5: Aporte | C5: 46302 | D5: GARE11 | E5: =IF(tb_investimentos[[#This Row],[TIPO MOVIMENTAÇÃO]]="Aporte",_xlfn.XLOOKUP(tb_investimentos[[#This Row],[DESCRIÇÃO]],'INFO AÇÕES'!E:E,'INFO AÇÕES'!I:I),"BRL") -> BRL | F5: FIIs | G5: 1 | H5: 8.74 | I5: Investimentos BB | J5: =H5*G5 -> 8.74 | K5: SIM | L5: =MONTH(tb_investimentos[[#This Row],[DATA]]) -> 10 | M5: =YEAR(tb_investimentos[[#This Row],[DATA]]) -> 2026 | N5: =DAY(tb_investimentos[[#This Row],[DATA]]) -> 7 | O5: =SUMIF($D$5:$D$10000, D5, $J$5:$J$10000) / SUMIF($D$5:$D$10000, D5, $G$5:$G$10000) -> 8.473 | P5: =tb_investimentos[[#This Row],[PREÇO MÉDIO PONDERADO]]*tb_investimentos[[#This Row],[QUANTIDADE]] -> 8.473 | Q5: =IFERROR(_xlfn.XLOOKUP(tb_investimentos[[#This Row],[DESCRIÇÃO]],tb_acoes[Símbolo do ticker],tb_acoes[Preço]),"") -> 8.35 | R5: =IFERROR(tb_investimentos[[#This Row],[QUANTIDADE]]*tb_investimentos[[#This Row],[PREÇO MERCADO]],"") -> 8.35 | S5: =IFERROR(tb_investimentos[[#This Row],[VALOR TOTAL MERCADO]]-tb_investimentos[[#This Row],[VALOR TOTAL PONDERADO]],"") -> -0.123 | T5: =IFERROR(_xlfn.XLOOKUP(tb_investimentos[[#This Row],[DESCRIÇÃO]],'INFO AÇÕES'!E:E,'INFO AÇÕES'!H:H),"") -> -0.044622 | U5: =IFERROR((tb_investimentos[[#This Row],[VALOR TOTAL MERCADO]]-tb_investimentos[[#This Row],[VALOR TOTAL PONDERADO]])/tb_investimentos[[#This Row],[VALOR TOTAL PONDERADO]],"") -> -0.0145167
B6: Aporte | C6: 46302 | D6: MXRF11 | E6: =IF(tb_investimentos[[#This Row],[TIPO MOVIMENTAÇÃO]]="Aporte",_xlfn.XLOOKUP(tb_investimentos[[#This Row],[DESCRIÇÃO]],'INFO AÇÕES'!E:E,'INFO AÇÕES'!I:I),"BRL") -> BRL | F6: FIIs | G6: 1 | H6: 9.38 | I6: Investimentos BB | J6: =H6*G6 -> 9.38 | K6: SIM | L6: =MONTH(tb_investimentos[[#This Row],[DATA]]) -> 10 | M6: =YEAR(tb_investimentos[[#This Row],[DATA]]) -> 2026 | N6: =DAY(tb_investimentos[[#This Row],[DATA]]) -> 7 | O6: =SUMIF($D$5:$D$10000, D6, $J$5:$J$10000) / SUMIF($D$5:$D$10000, D6, $G$5:$G$10000) -> 9.1778571 | P6: =tb_investimentos[[#This Row],[PREÇO MÉDIO PONDERADO]]*tb_investimentos[[#This Row],[QUANTIDADE]] -> 9.1778571 | Q6: =IFERROR(_xlfn.XLOOKUP(tb_investimentos[[#This Row],[DESCRIÇÃO]],tb_acoes[Símbolo do ticker],tb_acoes[Preço]),"") -> 9.02 | R6: =IFERROR(tb_investimentos[[#This Row],[QUANTIDADE]]*tb_investimentos[[#This Row],[PREÇO MERCADO]],"") -> 9.02 | S6: =IFERROR(tb_investimentos[[#This Row],[VALOR TOTAL MERCADO]]-tb_investimentos[[#This Row],[VALOR TOTAL PONDERADO]],"") -> -0.15785714 | T6: =IFERROR(_xlfn.XLOOKUP(tb_investimentos[[#This Row],[DESCRIÇÃO]],'INFO AÇÕES'!E:E,'INFO AÇÕES'!H:H),"") -> -0.009879 | U6: =IFERROR((tb_investimentos[[#This Row],[VALOR TOTAL MERCADO]]-tb_investimentos[[#This Row],[VALOR TOTAL PONDERADO]])/tb_investimentos[[#This Row],[VALOR TOTAL PONDERADO]],"") -> -0.017199782
B7: Aporte | C7: 46302 | D7: MXRF11 | E7: =IF(tb_investimentos[[#This Row],[TIPO MOVIMENTAÇÃO]]="Aporte",_xlfn.XLOOKUP(tb_investimentos[[#This Row],[DESCRIÇÃO]],'INFO AÇÕES'!E:E,'INFO AÇÕES'!I:I),"BRL") -> BRL | F7: FIIs | G7: 1 | H7: 9.44 | I7: Investimentos BB | J7: =H7*G7 -> 9.44 | K7: SIM | L7: =MONTH(tb_investimentos[[#This Row],[DATA]]) -> 10 | M7: =YEAR(tb_investimentos[[#This Row],[DATA]]) -> 2026 | N7: =DAY(tb_investimentos[[#This Row],[DATA]]) -> 7 | O7: =SUMIF($D$5:$D$10000, D7, $J$5:$J$10000) / SUMIF($D$5:$D$10000, D7, $G$5:$G$10000) -> 9.1778571 | P7: =tb_investimentos[[#This Row],[PREÇO MÉDIO PONDERADO]]*tb_investimentos[[#This Row],[QUANTIDADE]] -> 9.1778571 | Q7: =IFERROR(_xlfn.XLOOKUP(tb_investimentos[[#This Row],[DESCRIÇÃO]],tb_acoes[Símbolo do ticker],tb_acoes[Preço]),"") -> 9.02 | R7: =IFERROR(tb_investimentos[[#This Row],[QUANTIDADE]]*tb_investimentos[[#This Row],[PREÇO MERCADO]],"") -> 9.02 | S7: =IFERROR(tb_investimentos[[#This Row],[VALOR TOTAL MERCADO]]-tb_investimentos[[#This Row],[VALOR TOTAL PONDERADO]],"") -> -0.15785714 | T7: =IFERROR(_xlfn.XLOOKUP(tb_investimentos[[#This Row],[DESCRIÇÃO]],'INFO AÇÕES'!E:E,'INFO AÇÕES'!H:H),"") -> -0.009879 | U7: =IFERROR((tb_investimentos[[#This Row],[VALOR TOTAL MERCADO]]-tb_investimentos[[#This Row],[VALOR TOTAL PONDERADO]])/tb_investimentos[[#This Row],[VALOR TOTAL PONDERADO]],"") -> -0.017199782
B8: Aporte | C8: 46309 | D8: KNSC11 | E8: =IF(tb_investimentos[[#This Row],[TIPO MOVIMENTAÇÃO]]="Aporte",_xlfn.XLOOKUP(tb_investimentos[[#This Row],[DESCRIÇÃO]],'INFO AÇÕES'!E:E,'INFO AÇÕES'!I:I),"BRL") -> BRL | F8: FIIs | G8: 3 | H8: 9.07 | I8: Investimentos BB | J8: =H8*G8 -> 27.21 | K8: SIM | L8: =MONTH(tb_investimentos[[#This Row],[DATA]]) -> 10 | M8: =YEAR(tb_investimentos[[#This Row],[DATA]]) -> 2026 | N8: =DAY(tb_investimentos[[#This Row],[DATA]]) -> 14 | O8: =SUMIF($D$5:$D$10000, D8, $J$5:$J$10000) / SUMIF($D$5:$D$10000, D8, $G$5:$G$10000) -> 8.98 | P8: =tb_investimentos[[#This Row],[PREÇO MÉDIO PONDERADO]]*tb_investimentos[[#This Row],[QUANTIDADE]] -> 26.94 | Q8: =IFERROR(_xlfn.XLOOKUP(tb_investimentos[[#This Row],[DESCRIÇÃO]],tb_acoes[Símbolo do ticker],tb_acoes[Preço]),"") -> 8.85 | R8: =IFERROR(tb_investimentos[[#This Row],[QUANTIDADE]]*tb_investimentos[[#This Row],[PREÇO MERCADO]],"") -> 26.55 | S8: =IFERROR(tb_investimentos[[#This Row],[VALOR TOTAL MERCADO]]-tb_investimentos[[#This Row],[VALOR TOTAL PONDERADO]],"") -> -0.39 | T8: =IFERROR(_xlfn.XLOOKUP(tb_investimentos[[#This Row],[DESCRIÇÃO]],'INFO AÇÕES'!E:E,'INFO AÇÕES'!H:H),"") -> -0.014477 | U8: =IFERROR((tb_investimentos[[#This Row],[VALOR TOTAL MERCADO]]-tb_investimentos[[#This Row],[VALOR TOTAL PONDERADO]])/tb_investimentos[[#This Row],[VALOR TOTAL PONDERADO]],"") -> -0.014476615
B9: Aporte | C9: 46309 | D9: MXRF11 | E9: =IF(tb_investimentos[[#This Row],[TIPO MOVIMENTAÇÃO]]="Aporte",_xlfn.XLOOKUP(tb_investimentos[[#This Row],[DESCRIÇÃO]],'INFO AÇÕES'!E:E,'INFO AÇÕES'!I:I),"BRL") -> BRL | F9: FIIs | G9: 3 | H9: 9.32 | I9: Investimentos BB | J9: =H9*G9 -> 27.96 | K9: SIM | L9: =MONTH(tb_investimentos[[#This Row],[DATA]]) -> 10 | M9: =YEAR(tb_investimentos[[#This Row],[DATA]]) -> 2026 | N9: =DAY(tb_investimentos[[#This Row],[DATA]]) -> 14 | O9: =SUMIF($D$5:$D$10000, D9, $J$5:$J$10000) / SUMIF($D$5:$D$10000, D9, $G$5:$G$10000) -> 9.1778571 | P9: =tb_investimentos[[#This Row],[PREÇO MÉDIO PONDERADO]]*tb_investimentos[[#This Row],[QUANTIDADE]] -> 27.533571 | Q9: =IFERROR(_xlfn.XLOOKUP(tb_investimentos[[#This Row],[DESCRIÇÃO]],tb_acoes[Símbolo do ticker],tb_acoes[Preço]),"") -> 9.02 | R9: =IFERROR(tb_investimentos[[#This Row],[QUANTIDADE]]*tb_investimentos[[#This Row],[PREÇO MERCADO]],"") -> 27.06 | S9: =IFERROR(tb_investimentos[[#This Row],[VALOR TOTAL MERCADO]]-tb_investimentos[[#This Row],[VALOR TOTAL PONDERADO]],"") -> -0.47357143 | T9: =IFERROR(_xlfn.XLOOKUP(tb_investimentos[[#This Row],[DESCRIÇÃO]],'INFO AÇÕES'!E:E,'INFO AÇÕES'!H:H),"") -> -0.009879 | U9: =IFERROR((tb_investimentos[[#This Row],[VALOR TOTAL MERCADO]]-tb_investimentos[[#This Row],[VALOR TOTAL PONDERADO]])/tb_investimentos[[#This Row],[VALOR TOTAL PONDERADO]],"") -> -0.017199782
B10: Aporte | C10: 46309 | D10: GARE11 | E10: =IF(tb_investimentos[[#This Row],[TIPO MOVIMENTAÇÃO]]="Aporte",_xlfn.XLOOKUP(tb_investimentos[[#This Row],[DESCRIÇÃO]],'INFO AÇÕES'!E:E,'INFO AÇÕES'!I:I),"BRL") -> BRL | F10: FIIs | G10: 2 | H10: 8.59 | I10: Investimentos BB | J10: =H10*G10 -> 17.18 | K10: SIM | L10: =MONTH(tb_investimentos[[#This Row],[DATA]]) -> 10 | M10: =YEAR(tb_investimentos[[#This Row],[DATA]]) -> 2026 | N10: =DAY(tb_investimentos[[#This Row],[DATA]]) -> 14 | O10: =SUMIF($D$5:$D$10000, D10, $J$5:$J$10000) / SUMIF($D$5:$D$10000, D10, $G$5:$G$10000) -> 8.473 | P10: =tb_investimentos[[#This Row],[PREÇO MÉDIO PONDERADO]]*tb_investimentos[[#This Row],[QUANTIDADE]] -> 16.946 | Q10: =IFERROR(_xlfn.XLOOKUP(tb_investimentos[[#This Row],[DESCRIÇÃO]],tb_acoes[Símbolo do ticker],tb_acoes[Preço]),"") -> 8.35 | R10: =IFERROR(tb_investimentos[[#This Row],[QUANTIDADE]]*tb_investimentos[[#This Row],[PREÇO MERCADO]],"") -> 16.7 | S10: =IFERROR(tb_investimentos[[#This Row],[VALOR TOTAL MERCADO]]-tb_investimentos[[#This Row],[VALOR TOTAL PONDERADO]],"") -> -0.246 | T10: =IFERROR(_xlfn.XLOOKUP(tb_investimentos[[#This Row],[DESCRIÇÃO]],'INFO AÇÕES'!E:E,'INFO AÇÕES'!H:H),"") -> -0.044622 | U10: =IFERROR((tb_investimentos[[#This Row],[VALOR TOTAL MERCADO]]-tb_investimentos[[#This Row],[VALOR TOTAL PONDERADO]])/tb_investimentos[[#This Row],[VALOR TOTAL PONDERADO]],"") -> -0.0145167
B11: Aporte | C11: 46309 | D11: SAPR4 | E11: =IF(tb_investimentos[[#This Row],[TIPO MOVIMENTAÇÃO]]="Aporte",_xlfn.XLOOKUP(tb_investimentos[[#This Row],[DESCRIÇÃO]],'INFO AÇÕES'!E:E,'INFO AÇÕES'!I:I),"BRL") -> BRL | F11: Ações | G11: 2 | H11: 7.84 | I11: Investimentos BB | J11: =H11*G11 -> 15.68 | K11: SIM | L11: =MONTH(tb_investimentos[[#This Row],[DATA]]) -> 10 | M11: =YEAR(tb_investimentos[[#This Row],[DATA]]) -> 2026 | N11: =DAY(tb_investimentos[[#This Row],[DATA]]) -> 14 | O11: =SUMIF($D$5:$D$10000, D11, $J$5:$J$10000) / SUMIF($D$5:$D$10000, D11, $G$5:$G$10000) -> 7.291 | P11: =tb_investimentos[[#This Row],[PREÇO MÉDIO PONDERADO]]*tb_investimentos[[#This Row],[QUANTIDADE]] -> 14.582 | Q11: =IFERROR(_xlfn.XLOOKUP(tb_investimentos[[#This Row],[DESCRIÇÃO]],tb_acoes[Símbolo do ticker],tb_acoes[Preço]),"") -> 6.86 | R11: =IFERROR(tb_investimentos[[#This Row],[QUANTIDADE]]*tb_investimentos[[#This Row],[PREÇO MERCADO]],"") -> 13.72 | S11: =IFERROR(tb_investimentos[[#This Row],[VALOR TOTAL MERCADO]]-tb_investimentos[[#This Row],[VALOR TOTAL PONDERADO]],"") -> -0.862 | T11: =IFERROR(_xlfn.XLOOKUP(tb_investimentos[[#This Row],[DESCRIÇÃO]],'INFO AÇÕES'!E:E,'INFO AÇÕES'!H:H),"") -> 0.008824 | U11: =IFERROR((tb_investimentos[[#This Row],[VALOR TOTAL MERCADO]]-tb_investimentos[[#This Row],[VALOR TOTAL PONDERADO]])/tb_investimentos[[#This Row],[VALOR TOTAL PONDERADO]],"") -> -0.059113976
B12: Aporte | C12: 46314 | D12: GARE11 | E12: =IF(tb_investimentos[[#This Row],[TIPO MOVIMENTAÇÃO]]="Aporte",_xlfn.XLOOKUP(tb_investimentos[[#This Row],[DESCRIÇÃO]],'INFO AÇÕES'!E:E,'INFO AÇÕES'!I:I),"BRL") -> BRL | F12: FIIs | G12: 2 | H12: 8.68 | I12: Investimentos BB | J12: =H12*G12 -> 17.36 | K12: SIM | L12: =MONTH(tb_investimentos[[#This Row],[DATA]]) -> 10 | M12: =YEAR(tb_investimentos[[#This Row],[DATA]]) -> 2026 | N12: =DAY(tb_investimentos[[#This Row],[DATA]]) -> 19 | O12: =SUMIF($D$5:$D$10000, D12, $J$5:$J$10000) / SUMIF($D$5:$D$10000, D12, $G$5:$G$10000) -> 8.473 | P12: =tb_investimentos[[#This Row],[PREÇO MÉDIO PONDERADO]]*tb_investimentos[[#This Row],[QUANTIDADE]] -> 16.946 | Q12: =IFERROR(_xlfn.XLOOKUP(tb_investimentos[[#This Row],[DESCRIÇÃO]],tb_acoes[Símbolo do ticker],tb_acoes[Preço]),"") -> 8.35 | R12: =IFERROR(tb_investimentos[[#This Row],[QUANTIDADE]]*tb_investimentos[[#This Row],[PREÇO MERCADO]],"") -> 16.7 | S12: =IFERROR(tb_investimentos[[#This Row],[VALOR TOTAL MERCADO]]-tb_investimentos[[#This Row],[VALOR TOTAL PONDERADO]],"") -> -0.246 | T12: =IFERROR(_xlfn.XLOOKUP(tb_investimentos[[#This Row],[DESCRIÇÃO]],'INFO AÇÕES'!E:E,'INFO AÇÕES'!H:H),"") -> -0.044622 | U12: =IFERROR((tb_investimentos[[#This Row],[VALOR TOTAL MERCADO]]-tb_investimentos[[#This Row],[VALOR TOTAL PONDERADO]])/tb_investimentos[[#This Row],[VALOR TOTAL PONDERADO]],"") -> -0.0145167
B13: Aporte | C13: 46314 | D13: KNSC11 | E13: =IF(tb_investimentos[[#This Row],[TIPO MOVIMENTAÇÃO]]="Aporte",_xlfn.XLOOKUP(tb_investimentos[[#This Row],[DESCRIÇÃO]],'INFO AÇÕES'!E:E,'INFO AÇÕES'!I:I),"BRL") -> BRL | F13: FIIs | G13: 2 | H13: 9.16 | I13: Investimentos BB | J13: =H13*G13 -> 18.32 | K13: SIM | L13: =MONTH(tb_investimentos[[#This Row],[DATA]]) -> 10 | M13: =YEAR(tb_investimentos[[#This Row],[DATA]]) -> 2026 | N13: =DAY(tb_investimentos[[#This Row],[DATA]]) -> 19 | O13: =SUMIF($D$5:$D$10000, D13, $J$5:$J$10000) / SUMIF($D$5:$D$10000, D13, $G$5:$G$10000) -> 8.98 | P13: =tb_investimentos[[#This Row],[PREÇO MÉDIO PONDERADO]]*tb_investimentos[[#This Row],[QUANTIDADE]] -> 17.96 | Q13: =IFERROR(_xlfn.XLOOKUP(tb_investimentos[[#This Row],[DESCRIÇÃO]],tb_acoes[Símbolo do ticker],tb_acoes[Preço]),"") -> 8.85 | R13: =IFERROR(tb_investimentos[[#This Row],[QUANTIDADE]]*tb_investimentos[[#This Row],[PREÇO MERCADO]],"") -> 17.7 | S13: =IFERROR(tb_investimentos[[#This Row],[VALOR TOTAL MERCADO]]-tb_investimentos[[#This Row],[VALOR TOTAL PONDERADO]],"") -> -0.26 | T13: =IFERROR(_xlfn.XLOOKUP(tb_investimentos[[#This Row],[DESCRIÇÃO]],'INFO AÇÕES'!E:E,'INFO AÇÕES'!H:H),"") -> -0.014477 | U13: =IFERROR((tb_investimentos[[#This Row],[VALOR TOTAL MERCADO]]-tb_investimentos[[#This Row],[VALOR TOTAL PONDERADO]])/tb_investimentos[[#This Row],[VALOR TOTAL PONDERADO]],"") -> -0.014476615
B14: Aporte | C14: 46314 | D14: MXRF11 | E14: =IF(tb_investimentos[[#This Row],[TIPO MOVIMENTAÇÃO]]="Aporte",_xlfn.XLOOKUP(tb_investimentos[[#This Row],[DESCRIÇÃO]],'INFO AÇÕES'!E:E,'INFO AÇÕES'!I:I),"BRL") -> BRL | F14: FIIs | G14: 2 | H14: 9.39 | I14: Investimentos BB | J14: =H14*G14 -> 18.78 | K14: SIM | L14: =MONTH(tb_investimentos[[#This Row],[DATA]]) -> 10 | M14: =YEAR(tb_investimentos[[#This Row],[DATA]]) -> 2026 | N14: =DAY(tb_investimentos[[#This Row],[DATA]]) -> 19 | O14: =SUMIF($D$5:$D$10000, D14, $J$5:$J$10000) / SUMIF($D$5:$D$10000, D14, $G$5:$G$10000) -> 9.1778571 | P14: =tb_investimentos[[#This Row],[PREÇO MÉDIO PONDERADO]]*tb_investimentos[[#This Row],[QUANTIDADE]] -> 18.355714 | Q14: =IFERROR(_xlfn.XLOOKUP(tb_investimentos[[#This Row],[DESCRIÇÃO]],tb_acoes[Símbolo do ticker],tb_acoes[Preço]),"") -> 9.02 | R14: =IFERROR(tb_investimentos[[#This Row],[QUANTIDADE]]*tb_investimentos[[#This Row],[PREÇO MERCADO]],"") -> 18.04 | S14: =IFERROR(tb_investimentos[[#This Row],[VALOR TOTAL MERCADO]]-tb_investimentos[[#This Row],[VALOR TOTAL PONDERADO]],"") -> -0.31571429 | T14: =IFERROR(_xlfn.XLOOKUP(tb_investimentos[[#This Row],[DESCRIÇÃO]],'INFO AÇÕES'!E:E,'INFO AÇÕES'!H:H),"") -> -0.009879 | U14: =IFERROR((tb_investimentos[[#This Row],[VALOR TOTAL MERCADO]]-tb_investimentos[[#This Row],[VALOR TOTAL PONDERADO]])/tb_investimentos[[#This Row],[VALOR TOTAL PONDERADO]],"") -> -0.017199782
B15: Aporte | C15: 46314 | D15: SAPR4 | E15: =IF(tb_investimentos[[#This Row],[TIPO MOVIMENTAÇÃO]]="Aporte",_xlfn.XLOOKUP(tb_investimentos[[#This Row],[DESCRIÇÃO]],'INFO AÇÕES'!E:E,'INFO AÇÕES'!I:I),"BRL") -> BRL | F15: Ações | G15: 3 | H15: 7.75 | I15: Investimentos BB | J15: =H15*G15 -> 23.25 | K15: SIM | L15: =MONTH(tb_investimentos[[#This Row],[DATA]]) -> 10 | M15: =YEAR(tb_investimentos[[#This Row],[DATA]]) -> 2026 | N15: =DAY(tb_investimentos[[#This Row],[DATA]]) -> 19 | O15: =SUMIF($D$5:$D$10000, D15, $J$5:$J$10000) / SUMIF($D$5:$D$10000, D15, $G$5:$G$10000) -> 7.291 | P15: =tb_investimentos[[#This Row],[PREÇO MÉDIO PONDERADO]]*tb_investimentos[[#This Row],[QUANTIDADE]] -> 21.873 | Q15: =IFERROR(_xlfn.XLOOKUP(tb_investimentos[[#This Row],[DESCRIÇÃO]],tb_acoes[Símbolo do ticker],tb_acoes[Preço]),"") -> 6.86 | R15: =IFERROR(tb_investimentos[[#This Row],[QUANTIDADE]]*tb_investimentos[[#This Row],[PREÇO MERCADO]],"") -> 20.58 | S15: =IFERROR(tb_investimentos[[#This Row],[VALOR TOTAL MERCADO]]-tb_investimentos[[#This Row],[VALOR TOTAL PONDERADO]],"") -> -1.293 | T15: =IFERROR(_xlfn.XLOOKUP(tb_investimentos[[#This Row],[DESCRIÇÃO]],'INFO AÇÕES'!E:E,'INFO AÇÕES'!H:H),"") -> 0.008824 | U15: =IFERROR((tb_investimentos[[#This Row],[VALOR TOTAL MERCADO]]-tb_investimentos[[#This Row],[VALOR TOTAL PONDERADO]])/tb_investimentos[[#This Row],[VALOR TOTAL PONDERADO]],"") -> -0.059113976
B16: Aporte | C16: 46314 | D16: ITSA3 | E16: =IF(tb_investimentos[[#This Row],[TIPO MOVIMENTAÇÃO]]="Aporte",_xlfn.XLOOKUP(tb_investimentos[[#This Row],[DESCRIÇÃO]],'INFO AÇÕES'!E:E,'INFO AÇÕES'!I:I),"BRL") -> BRL | F16: Ações | G16: 1 | H16: 15.42 | I16: Investimentos BB | J16: =H16*G16 -> 15.42 | K16: SIM | L16: =MONTH(tb_investimentos[[#This Row],[DATA]]) -> 10 | M16: =YEAR(tb_investimentos[[#This Row],[DATA]]) -> 2026 | N16: =DAY(tb_investimentos[[#This Row],[DATA]]) -> 19 | O16: =SUMIF($D$5:$D$10000, D16, $J$5:$J$10000) / SUMIF($D$5:$D$10000, D16, $G$5:$G$10000) -> 13.9275 | P16: =tb_investimentos[[#This Row],[PREÇO MÉDIO PONDERADO]]*tb_investimentos[[#This Row],[QUANTIDADE]] -> 13.9275 | Q16: =IFERROR(_xlfn.XLOOKUP(tb_investimentos[[#This Row],[DESCRIÇÃO]],tb_acoes[Símbolo do ticker],tb_acoes[Preço]),"") -> 13.97 | R16: =IFERROR(tb_investimentos[[#This Row],[QUANTIDADE]]*tb_investimentos[[#This Row],[PREÇO MERCADO]],"") -> 13.97 | S16: =IFERROR(tb_investimentos[[#This Row],[VALOR TOTAL MERCADO]]-tb_investimentos[[#This Row],[VALOR TOTAL PONDERADO]],"") -> 0.0425 | T16: =IFERROR(_xlfn.XLOOKUP(tb_investimentos[[#This Row],[DESCRIÇÃO]],'INFO AÇÕES'!E:E,'INFO AÇÕES'!H:H),"") -> -0.00922 | U16: =IFERROR((tb_investimentos[[#This Row],[VALOR TOTAL MERCADO]]-tb_investimentos[[#This Row],[VALOR TOTAL PONDERADO]])/tb_investimentos[[#This Row],[VALOR TOTAL PONDERADO]],"") -> 0.0030515168
... B26: Saídas | C26: 46331 | D26: Banco do Brasil | E26: =IF(tb_investimentos[[#This Row],[TIPO MOVIMENTAÇÃO]]="Aporte",_xlfn.XLOOKUP(tb_investimentos[[#This Row],[DESCRIÇÃO]],'INFO AÇÕES'!E:E,'INFO AÇÕES'!I:I),"BRL") -> BRL | F26: Cartão de Crédito | G26: 1 | H26: 1150 | I26: Banco do Brasil | J26: =H26*G26 -> 1150 | K26: NÃO | L26: =MONTH(tb_investimentos[[#This Row],[DATA]]) -> 11 | M26: =YEAR(tb_investimentos[[#This Row],[DATA]]) -> 2026 | N26: =DAY(tb_investimentos[[#This Row],[DATA]]) -> 5 | O26: =SUMIF($D$5:$D$10000, D26, $J$5:$J$10000) / SUMIF($D$5:$D$10000, D26, $G$5:$G$10000) -> 515.93333 | P26: =tb_investimentos[[#This Row],[PREÇO MÉDIO PONDERADO]]*tb_investimentos[[#This Row],[QUANTIDADE]] -> 515.93333 | Q26: =IFERROR(_xlfn.XLOOKUP(tb_investimentos[[#This Row],[DESCRIÇÃO]],tb_acoes[Símbolo do ticker],tb_acoes[Preço]),"") | R26: =IFERROR(tb_investimentos[[#This Row],[QUANTIDADE]]*tb_investimentos[[#This Row],[PREÇO MERCADO]],"") | S26: =IFERROR(tb_investimentos[[#This Row],[VALOR TOTAL MERCADO]]-tb_investimentos[[#This Row],[VALOR TOTAL PONDERADO]],"") | T26: =IFERROR(_xlfn.XLOOKUP(tb_investimentos[[#This Row],[DESCRIÇÃO]],'INFO AÇÕES'!E:E,'INFO AÇÕES'!H:H),"") | U26: =IFERROR((tb_investimentos[[#This Row],[VALOR TOTAL MERCADO]]-tb_investimentos[[#This Row],[VALOR TOTAL PONDERADO]])/tb_investimentos[[#This Row],[VALOR TOTAL PONDERADO]],"")
B27: Aporte | C27: 46331 | E27: =IF(tb_investimentos[[#This Row],[TIPO MOVIMENTAÇÃO]]="Aporte",_xlfn.XLOOKUP(tb_investimentos[[#This Row],[DESCRIÇÃO]],'INFO AÇÕES'!E:E,'INFO AÇÕES'!I:I),"BRL") -> 0 | F27: Ações | G27: 1 | H27: 2000 | I27: Investimentos BB | J27: =H27*G27 -> 2000 | K27: NÃO | L27: =MONTH(tb_investimentos[[#This Row],[DATA]]) -> 11 | M27: =YEAR(tb_investimentos[[#This Row],[DATA]]) -> 2026 | N27: =DAY(tb_investimentos[[#This Row],[DATA]]) -> 5 | O27: =SUMIF($D$5:$D$10000, D27, $J$5:$J$10000) / SUMIF($D$5:$D$10000, D27, $G$5:$G$10000) -> #DIV/0! | P27: =tb_investimentos[[#This Row],[PREÇO MÉDIO PONDERADO]]*tb_investimentos[[#This Row],[QUANTIDADE]] -> #DIV/0! | Q27: =IFERROR(_xlfn.XLOOKUP(tb_investimentos[[#This Row],[DESCRIÇÃO]],tb_acoes[Símbolo do ticker],tb_acoes[Preço]),"") | R27: =IFERROR(tb_investimentos[[#This Row],[QUANTIDADE]]*tb_investimentos[[#This Row],[PREÇO MERCADO]],"") | S27: =IFERROR(tb_investimentos[[#This Row],[VALOR TOTAL MERCADO]]-tb_investimentos[[#This Row],[VALOR TOTAL PONDERADO]],"") | T27: =IFERROR(_xlfn.XLOOKUP(tb_investimentos[[#This Row],[DESCRIÇÃO]],'INFO AÇÕES'!E:E,'INFO AÇÕES'!H:H),"") | U27: =IFERROR((tb_investimentos[[#This Row],[VALOR TOTAL MERCADO]]-tb_investimentos[[#This Row],[VALOR TOTAL PONDERADO]])/tb_investimentos[[#This Row],[VALOR TOTAL PONDERADO]],"")
B28: Saídas | C28: 46332 | D28: Mercado Livre | E28: =IF(tb_investimentos[[#This Row],[TIPO MOVIMENTAÇÃO]]="Aporte",_xlfn.XLOOKUP(tb_investimentos[[#This Row],[DESCRIÇÃO]],'INFO AÇÕES'!E:E,'INFO AÇÕES'!I:I),"BRL") -> BRL | F28: Emprestimo 1/3 | G28: 1 | H28: 650 | I28: Banco do Brasil | J28: =H28*G28 -> 650 | K28: NÃO | L28: =MONTH(tb_investimentos[[#This Row],[DATA]]) -> 11 | M28: =YEAR(tb_investimentos[[#This Row],[DATA]]) -> 2026 | N28: =DAY(tb_investimentos[[#This Row],[DATA]]) -> 6 | O28: =SUMIF($D$5:$D$10000, D28, $J$5:$J$10000) / SUMIF($D$5:$D$10000, D28, $G$5:$G$10000) -> 650 | P28: =tb_investimentos[[#This Row],[PREÇO MÉDIO PONDERADO]]*tb_investimentos[[#This Row],[QUANTIDADE]] -> 650 | Q28: =IFERROR(_xlfn.XLOOKUP(tb_investimentos[[#This Row],[DESCRIÇÃO]],tb_acoes[Símbolo do ticker],tb_acoes[Preço]),"") | R28: =IFERROR(tb_investimentos[[#This Row],[QUANTIDADE]]*tb_investimentos[[#This Row],[PREÇO MERCADO]],"") | S28: =IFERROR(tb_investimentos[[#This Row],[VALOR TOTAL MERCADO]]-tb_investimentos[[#This Row],[VALOR TOTAL PONDERADO]],"") | T28: =IFERROR(_xlfn.XLOOKUP(tb_investimentos[[#This Row],[DESCRIÇÃO]],'INFO AÇÕES'!E:E,'INFO AÇÕES'!H:H),"") | U28: =IFERROR((tb_investimentos[[#This Row],[VALOR TOTAL MERCADO]]-tb_investimentos[[#This Row],[VALOR TOTAL PONDERADO]])/tb_investimentos[[#This Row],[VALOR TOTAL PONDERADO]],"")
B29: Entradas | C29: 46332 | D29: Capital de Giro | E29: =IF(tb_investimentos[[#This Row],[TIPO MOVIMENTAÇÃO]]="Aporte",_xlfn.XLOOKUP(tb_investimentos[[#This Row],[DESCRIÇÃO]],'INFO AÇÕES'!E:E,'INFO AÇÕES'!I:I),"BRL") -> BRL | F29: Pascoal | G29: 1 | H29: 4710 | I29: Banco do Brasil | J29: =H29*G29 -> 4710 | K29: NÃO | L29: =MONTH(tb_investimentos[[#This Row],[DATA]]) -> 11 | M29: =YEAR(tb_investimentos[[#This Row],[DATA]]) -> 2026 | N29: =DAY(tb_investimentos[[#This Row],[DATA]]) -> 6 | O29: =SUMIF($D$5:$D$10000, D29, $J$5:$J$10000) / SUMIF($D$5:$D$10000, D29, $G$5:$G$10000) -> 4710 | P29: =tb_investimentos[[#This Row],[PREÇO MÉDIO PONDERADO]]*tb_investimentos[[#This Row],[QUANTIDADE]] -> 4710 | Q29: =IFERROR(_xlfn.XLOOKUP(tb_investimentos[[#This Row],[DESCRIÇÃO]],tb_acoes[Símbolo do ticker],tb_acoes[Preço]),"") | R29: =IFERROR(tb_investimentos[[#This Row],[QUANTIDADE]]*tb_investimentos[[#This Row],[PREÇO MERCADO]],"") | S29: =IFERROR(tb_investimentos[[#This Row],[VALOR TOTAL MERCADO]]-tb_investimentos[[#This Row],[VALOR TOTAL PONDERADO]],"") | T29: =IFERROR(_xlfn.XLOOKUP(tb_investimentos[[#This Row],[DESCRIÇÃO]],'INFO AÇÕES'!E:E,'INFO AÇÕES'!H:H),"") | U29: =IFERROR((tb_investimentos[[#This Row],[VALOR TOTAL MERCADO]]-tb_investimentos[[#This Row],[VALOR TOTAL PONDERADO]])/tb_investimentos[[#This Row],[VALOR TOTAL PONDERADO]],"")
B30: Entradas | C30: 46332 | D30: Capital de Giro | E30: =IF(tb_investimentos[[#This Row],[TIPO MOVIMENTAÇÃO]]="Aporte",_xlfn.XLOOKUP(tb_investimentos[[#This Row],[DESCRIÇÃO]],'INFO AÇÕES'!E:E,'INFO AÇÕES'!I:I),"BRL") -> BRL | F30: Pascoal | G30: 1 | H30: 4710 | I30: Banco do Brasil | J30: =H30*G30 -> 4710 | K30: NÃO | L30: =MONTH(tb_investimentos[[#This Row],[DATA]]) -> 11 | M30: =YEAR(tb_investimentos[[#This Row],[DATA]]) -> 2026 | N30: =DAY(tb_investimentos[[#This Row],[DATA]]) -> 6 | O30: =SUMIF($D$5:$D$10000, D30, $J$5:$J$10000) / SUMIF($D$5:$D$10000, D30, $G$5:$G$10000) -> 4710 | P30: =tb_investimentos[[#This Row],[PREÇO MÉDIO PONDERADO]]*tb_investimentos[[#This Row],[QUANTIDADE]] -> 4710 | Q30: =IFERROR(_xlfn.XLOOKUP(tb_investimentos[[#This Row],[DESCRIÇÃO]],tb_acoes[Símbolo do ticker],tb_acoes[Preço]),"") | R30: =IFERROR(tb_investimentos[[#This Row],[QUANTIDADE]]*tb_investimentos[[#This Row],[PREÇO MERCADO]],"") | S30: =IFERROR(tb_investimentos[[#This Row],[VALOR TOTAL MERCADO]]-tb_investimentos[[#This Row],[VALOR TOTAL PONDERADO]],"") | T30: =IFERROR(_xlfn.XLOOKUP(tb_investimentos[[#This Row],[DESCRIÇÃO]],'INFO AÇÕES'!E:E,'INFO AÇÕES'!H:H),"") | U30: =IFERROR((tb_investimentos[[#This Row],[VALOR TOTAL MERCADO]]-tb_investimentos[[#This Row],[VALOR TOTAL PONDERADO]])/tb_investimentos[[#This Row],[VALOR TOTAL PONDERADO]],"")
B31: Saídas | C31: 46334 | D31: Sabesp | E31: =IF(tb_investimentos[[#This Row],[TIPO MOVIMENTAÇÃO]]="Aporte",_xlfn.XLOOKUP(tb_investimentos[[#This Row],[DESCRIÇÃO]],'INFO AÇÕES'!E:E,'INFO AÇÕES'!I:I),"BRL") -> BRL | F31: Agua | G31: 1 | H31: 25 | I31: Banco do Brasil | J31: =H31*G31 -> 25 | K31: NÃO | L31: =MONTH(tb_investimentos[[#This Row],[DATA]]) -> 11 | M31: =YEAR(tb_investimentos[[#This Row],[DATA]]) -> 2026 | N31: =DAY(tb_investimentos[[#This Row],[DATA]]) -> 8 | O31: =SUMIF($D$5:$D$10000, D31, $J$5:$J$10000) / SUMIF($D$5:$D$10000, D31, $G$5:$G$10000) -> 25 | P31: =tb_investimentos[[#This Row],[PREÇO MÉDIO PONDERADO]]*tb_investimentos[[#This Row],[QUANTIDADE]] -> 25 | Q31: =IFERROR(_xlfn.XLOOKUP(tb_investimentos[[#This Row],[DESCRIÇÃO]],tb_acoes[Símbolo do ticker],tb_acoes[Preço]),"") | R31: =IFERROR(tb_investimentos[[#This Row],[QUANTIDADE]]*tb_investimentos[[#This Row],[PREÇO MERCADO]],"") | S31: =IFERROR(tb_investimentos[[#This Row],[VALOR TOTAL MERCADO]]-tb_investimentos[[#This Row],[VALOR TOTAL PONDERADO]],"") | T31: =IFERROR(_xlfn.XLOOKUP(tb_investimentos[[#This Row],[DESCRIÇÃO]],'INFO AÇÕES'!E:E,'INFO AÇÕES'!H:H),"") | U31: =IFERROR((tb_investimentos[[#This Row],[VALOR TOTAL MERCADO]]-tb_investimentos[[#This Row],[VALOR TOTAL PONDERADO]])/tb_investimentos[[#This Row],[VALOR TOTAL PONDERADO]],"")
B32: Saídas | C32: 46336 | D32: Cia Manah | E32: =IF(tb_investimentos[[#This Row],[TIPO MOVIMENTAÇÃO]]="Aporte",_xlfn.XLOOKUP(tb_investimentos[[#This Row],[DESCRIÇÃO]],'INFO AÇÕES'!E:E,'INFO AÇÕES'!I:I),"BRL") -> BRL | F32: Ballet e Ginastica | G32: 1 | H32: 95 | I32: Banco do Brasil | J32: =H32*G32 -> 95 | K32: NÃO | L32: =MONTH(tb_investimentos[[#This Row],[DATA]]) -> 11 | M32: =YEAR(tb_investimentos[[#This Row],[DATA]]) -> 2026 | N32: =DAY(tb_investimentos[[#This Row],[DATA]]) -> 10 | O32: =SUMIF($D$5:$D$10000, D32, $J$5:$J$10000) / SUMIF($D$5:$D$10000, D32, $G$5:$G$10000) -> 95 | P32: =tb_investimentos[[#This Row],[PREÇO MÉDIO PONDERADO]]*tb_investimentos[[#This Row],[QUANTIDADE]] -> 95 | Q32: =IFERROR(_xlfn.XLOOKUP(tb_investimentos[[#This Row],[DESCRIÇÃO]],tb_acoes[Símbolo do ticker],tb_acoes[Preço]),"") | R32: =IFERROR(tb_investimentos[[#This Row],[QUANTIDADE]]*tb_investimentos[[#This Row],[PREÇO MERCADO]],"") | S32: =IFERROR(tb_investimentos[[#This Row],[VALOR TOTAL MERCADO]]-tb_investimentos[[#This Row],[VALOR TOTAL PONDERADO]],"") | T32: =IFERROR(_xlfn.XLOOKUP(tb_investimentos[[#This Row],[DESCRIÇÃO]],'INFO AÇÕES'!E:E,'INFO AÇÕES'!H:H),"") | U32: =IFERROR((tb_investimentos[[#This Row],[VALOR TOTAL MERCADO]]-tb_investimentos[[#This Row],[VALOR TOTAL PONDERADO]])/tb_investimentos[[#This Row],[VALOR TOTAL PONDERADO]],"")
B33: Saídas | C33: 46338 | D33: Youtube | E33: =IF(tb_investimentos[[#This Row],[TIPO MOVIMENTAÇÃO]]="Aporte",_xlfn.XLOOKUP(tb_investimentos[[#This Row],[DESCRIÇÃO]],'INFO AÇÕES'!E:E,'INFO AÇÕES'!I:I),"BRL") -> BRL | F33: Youtube Music | G33: 1 | H33: 16.9 | I33: Banco do Brasil | J33: =H33*G33 -> 16.9 | K33: NÃO | L33: =MONTH(tb_investimentos[[#This Row],[DATA]]) -> 11 | M33: =YEAR(tb_investimentos[[#This Row],[DATA]]) -> 2026 | N33: =DAY(tb_investimentos[[#This Row],[DATA]]) -> 12 | O33: =SUMIF($D$5:$D$10000, D33, $J$5:$J$10000) / SUMIF($D$5:$D$10000, D33, $G$5:$G$10000) -> 137.33454 | P33: =tb_investimentos[[#This Row],[PREÇO MÉDIO PONDERADO]]*tb_investimentos[[#This Row],[QUANTIDADE]] -> 137.33454 | Q33: =IFERROR(_xlfn.XLOOKUP(tb_investimentos[[#This Row],[DESCRIÇÃO]],tb_acoes[Símbolo do ticker],tb_acoes[Preço]),"") | R33: =IFERROR(tb_investimentos[[#This Row],[QUANTIDADE]]*tb_investimentos[[#This Row],[PREÇO MERCADO]],"") | S33: =IFERROR(tb_investimentos[[#This Row],[VALOR TOTAL MERCADO]]-tb_investimentos[[#This Row],[VALOR TOTAL PONDERADO]],"") | T33: =IFERROR(_xlfn.XLOOKUP(tb_investimentos[[#This Row],[DESCRIÇÃO]],'INFO AÇÕES'!E:E,'INFO AÇÕES'!H:H),"") | U33: =IFERROR((tb_investimentos[[#This Row],[VALOR TOTAL MERCADO]]-tb_investimentos[[#This Row],[VALOR TOTAL PONDERADO]])/tb_investimentos[[#This Row],[VALOR TOTAL PONDERADO]],"")
B34: Saídas | C34: 46341 | D34: Vivo | E34: =IF(tb_investimentos[[#This Row],[TIPO MOVIMENTAÇÃO]]="Aporte",_xlfn.XLOOKUP(tb_investimentos[[#This Row],[DESCRIÇÃO]],'INFO AÇÕES'!E:E,'INFO AÇÕES'!I:I),"BRL") -> BRL | F34: Movel | G34: 1 | H34: 39.9 | I34: Banco do Brasil | J34: =H34*G34 -> 39.9 | K34: NÃO | L34: =MONTH(tb_investimentos[[#This Row],[DATA]]) -> 11 | M34: =YEAR(tb_investimentos[[#This Row],[DATA]]) -> 2026 | N34: =DAY(tb_investimentos[[#This Row],[DATA]]) -> 15 | O34: =SUMIF($D$5:$D$10000, D34, $J$5:$J$10000) / SUMIF($D$5:$D$10000, D34, $G$5:$G$10000) -> 59.9 | P34: =tb_investimentos[[#This Row],[PREÇO MÉDIO PONDERADO]]*tb_investimentos[[#This Row],[QUANTIDADE]] -> 59.9 | Q34: =IFERROR(_xlfn.XLOOKUP(tb_investimentos[[#This Row],[DESCRIÇÃO]],tb_acoes[Símbolo do ticker],tb_acoes[Preço]),"") | R34: =IFERROR(tb_investimentos[[#This Row],[QUANTIDADE]]*tb_investimentos[[#This Row],[PREÇO MERCADO]],"") | S34: =IFERROR(tb_investimentos[[#This Row],[VALOR TOTAL MERCADO]]-tb_investimentos[[#This Row],[VALOR TOTAL PONDERADO]],"") | T34: =IFERROR(_xlfn.XLOOKUP(tb_investimentos[[#This Row],[DESCRIÇÃO]],'INFO AÇÕES'!E:E,'INFO AÇÕES'!H:H),"") | U34: =IFERROR((tb_investimentos[[#This Row],[VALOR TOTAL MERCADO]]-tb_investimentos[[#This Row],[VALOR TOTAL PONDERADO]])/tb_investimentos[[#This Row],[VALOR TOTAL PONDERADO]],"")
B35: Saídas | C35: 46341 | D35: Vivo | E35: =IF(tb_investimentos[[#This Row],[TIPO MOVIMENTAÇÃO]]="Aporte",_xlfn.XLOOKUP(tb_investimentos[[#This Row],[DESCRIÇÃO]],'INFO AÇÕES'!E:E,'INFO AÇÕES'!I:I),"BRL") -> BRL | F35: Fibra | G35: 1 | H35: 79.9 | I35: Banco do Brasil | J35: =H35*G35 -> 79.9 | K35: NÃO | L35: =MONTH(tb_investimentos[[#This Row],[DATA]]) -> 11 | M35: =YEAR(tb_investimentos[[#This Row],[DATA]]) -> 2026 | N35: =DAY(tb_investimentos[[#This Row],[DATA]]) -> 15 | O35: =SUMIF($D$5:$D$10000, D35, $J$5:$J$10000) / SUMIF($D$5:$D$10000, D35, $G$5:$G$10000) -> 59.9 | P35: =tb_investimentos[[#This Row],[PREÇO MÉDIO PONDERADO]]*tb_investimentos[[#This Row],[QUANTIDADE]] -> 59.9 | Q35: =IFERROR(_xlfn.XLOOKUP(tb_investimentos[[#This Row],[DESCRIÇÃO]],tb_acoes[Símbolo do ticker],tb_acoes[Preço]),"") | R35: =IFERROR(tb_investimentos[[#This Row],[QUANTIDADE]]*tb_investimentos[[#This Row],[PREÇO MERCADO]],"") | S35: =IFERROR(tb_investimentos[[#This Row],[VALOR TOTAL MERCADO]]-tb_investimentos[[#This Row],[VALOR TOTAL PONDERADO]],"") | T35: =IFERROR(_xlfn.XLOOKUP(tb_investimentos[[#This Row],[DESCRIÇÃO]],'INFO AÇÕES'!E:E,'INFO AÇÕES'!H:H),"") | U35: =IFERROR((tb_investimentos[[#This Row],[VALOR TOTAL MERCADO]]-tb_investimentos[[#This Row],[VALOR TOTAL PONDERADO]])/tb_investimentos[[#This Row],[VALOR TOTAL PONDERADO]],"")
B36: Saídas | C36: 46341 | D36: Enel | E36: =IF(tb_investimentos[[#This Row],[TIPO MOVIMENTAÇÃO]]="Aporte",_xlfn.XLOOKUP(tb_investimentos[[#This Row],[DESCRIÇÃO]],'INFO AÇÕES'!E:E,'INFO AÇÕES'!I:I),"BRL") -> BRL | F36: Energia | G36: 1 | H36: 110 | I36: Banco do Brasil | J36: =H36*G36 -> 110 | K36: NÃO | L36: =MONTH(tb_investimentos[[#This Row],[DATA]]) -> 11 | M36: =YEAR(tb_investimentos[[#This Row],[DATA]]) -> 2026 | N36: =DAY(tb_investimentos[[#This Row],[DATA]]) -> 15 | O36: =SUMIF($D$5:$D$10000, D36, $J$5:$J$10000) / SUMIF($D$5:$D$10000, D36, $G$5:$G$10000) -> 110 | P36: =tb_investimentos[[#This Row],[PREÇO MÉDIO PONDERADO]]*tb_investimentos[[#This Row],[QUANTIDADE]] -> 110 | Q36: =IFERROR(_xlfn.XLOOKUP(tb_investimentos[[#This Row],[DESCRIÇÃO]],tb_acoes[Símbolo do ticker],tb_acoes[Preço]),"") | R36: =IFERROR(tb_investimentos[[#This Row],[QUANTIDADE]]*tb_investimentos[[#This Row],[PREÇO MERCADO]],"") | S36: =IFERROR(tb_investimentos[[#This Row],[VALOR TOTAL MERCADO]]-tb_investimentos[[#This Row],[VALOR TOTAL PONDERADO]],"") | T36: =IFERROR(_xlfn.XLOOKUP(tb_investimentos[[#This Row],[DESCRIÇÃO]],'INFO AÇÕES'!E:E,'INFO AÇÕES'!H:H),"") | U36: =IFERROR((tb_investimentos[[#This Row],[VALOR TOTAL MERCADO]]-tb_investimentos[[#This Row],[VALOR TOTAL PONDERADO]])/tb_investimentos[[#This Row],[VALOR TOTAL PONDERADO]],"")
B37: Saídas | C37: 46341 | D37: Contabilizei | E37: =IF(tb_investimentos[[#This Row],[TIPO MOVIMENTAÇÃO]]="Aporte",_xlfn.XLOOKUP(tb_investimentos[[#This Row],[DESCRIÇÃO]],'INFO AÇÕES'!E:E,'INFO AÇÕES'!I:I),"BRL") -> BRL | F37: Impostos | G37: 1 | H37: 500 | I37: Banco do Brasil | J37: =H37*G37 -> 500 | K37: NÃO | L37: =MONTH(tb_investimentos[[#This Row],[DATA]]) -> 11 | M37: =YEAR(tb_investimentos[[#This Row],[DATA]]) -> 2026 | N37: =DAY(tb_investimentos[[#This Row],[DATA]]) -> 15 | O37: =SUMIF($D$5:$D$10000, D37, $J$5:$J$10000) / SUMIF($D$5:$D$10000, D37, $G$5:$G$10000) -> 500 | P37: =tb_investimentos[[#This Row],[PREÇO MÉDIO PONDERADO]]*tb_investimentos[[#This Row],[QUANTIDADE]] -> 500 | Q37: =IFERROR(_xlfn.XLOOKUP(tb_investimentos[[#This Row],[DESCRIÇÃO]],tb_acoes[Símbolo do ticker],tb_acoes[Preço]),"") | R37: =IFERROR(tb_investimentos[[#This Row],[QUANTIDADE]]*tb_investimentos[[#This Row],[PREÇO MERCADO]],"") | S37: =IFERROR(tb_investimentos[[#This Row],[VALOR TOTAL MERCADO]]-tb_investimentos[[#This Row],[VALOR TOTAL PONDERADO]],"") | T37: =IFERROR(_xlfn.XLOOKUP(tb_investimentos[[#This Row],[DESCRIÇÃO]],'INFO AÇÕES'!E:E,'INFO AÇÕES'!H:H),"") | U37: =IFERROR((tb_investimentos[[#This Row],[VALOR TOTAL MERCADO]]-tb_investimentos[[#This Row],[VALOR TOTAL PONDERADO]])/tb_investimentos[[#This Row],[VALOR TOTAL PONDERADO]],"")
B38: Saídas | C38: 46341 | D38: Caixa Econômica Federal | E38: =IF(tb_investimentos[[#This Row],[TIPO MOVIMENTAÇÃO]]="Aporte",_xlfn.XLOOKUP(tb_investimentos[[#This Row],[DESCRIÇÃO]],'INFO AÇÕES'!E:E,'INFO AÇÕES'!I:I),"BRL") -> BRL | F38: Evolução de obras | G38: 1 | H38: 742.50836 | I38: Banco do Brasil | J38: =H38*G38 -> 742.50836 | K38: NÃO | L38: =MONTH(tb_investimentos[[#This Row],[DATA]]) -> 11 | M38: =YEAR(tb_investimentos[[#This Row],[DATA]]) -> 2026 | N38: =DAY(tb_investimentos[[#This Row],[DATA]]) -> 15 | O38: =SUMIF($D$5:$D$10000, D38, $J$5:$J$10000) / SUMIF($D$5:$D$10000, D38, $G$5:$G$10000) -> 1629.993 | P38: =tb_investimentos[[#This Row],[PREÇO MÉDIO PONDERADO]]*tb_investimentos[[#This Row],[QUANTIDADE]] -> 1629.993 | Q38: =IFERROR(_xlfn.XLOOKUP(tb_investimentos[[#This Row],[DESCRIÇÃO]],tb_acoes[Símbolo do ticker],tb_acoes[Preço]),"") | R38: =IFERROR(tb_investimentos[[#This Row],[QUANTIDADE]]*tb_investimentos[[#This Row],[PREÇO MERCADO]],"") | S38: =IFERROR(tb_investimentos[[#This Row],[VALOR TOTAL MERCADO]]-tb_investimentos[[#This Row],[VALOR TOTAL PONDERADO]],"") | T38: =IFERROR(_xlfn.XLOOKUP(tb_investimentos[[#This Row],[DESCRIÇÃO]],'INFO AÇÕES'!E:E,'INFO AÇÕES'!H:H),"") | U38: =IFERROR((tb_investimentos[[#This Row],[VALOR TOTAL MERCADO]]-tb_investimentos[[#This Row],[VALOR TOTAL PONDERADO]])/tb_investimentos[[#This Row],[VALOR TOTAL PONDERADO]],"")
B39: Saídas | C39: 46346 | D39: DAS/DARF | E39: =IF(tb_investimentos[[#This Row],[TIPO MOVIMENTAÇÃO]]="Aporte",_xlfn.XLOOKUP(tb_investimentos[[#This Row],[DESCRIÇÃO]],'INFO AÇÕES'!E:E,'INFO AÇÕES'!I:I),"BRL") -> BRL | F39: Impostos | G39: 1 | H39: 87 | I39: Banco do Brasil | J39: =H39*G39 -> 87 | K39: NÃO | L39: =MONTH(tb_investimentos[[#This Row],[DATA]]) -> 11 | M39: =YEAR(tb_investimentos[[#This Row],[DATA]]) -> 2026 | N39: =DAY(tb_investimentos[[#This Row],[DATA]]) -> 20 | O39: =SUMIF($D$5:$D$10000, D39, $J$5:$J$10000) / SUMIF($D$5:$D$10000, D39, $G$5:$G$10000) -> 93.857143 | P39: =tb_investimentos[[#This Row],[PREÇO MÉDIO PONDERADO]]*tb_investimentos[[#This Row],[QUANTIDADE]] -> 93.857143 | Q39: =IFERROR(_xlfn.XLOOKUP(tb_investimentos[[#This Row],[DESCRIÇÃO]],tb_acoes[Símbolo do ticker],tb_acoes[Preço]),"") | R39: =IFERROR(tb_investimentos[[#This Row],[QUANTIDADE]]*tb_investimentos[[#This Row],[PREÇO MERCADO]],"") | S39: =IFERROR(tb_investimentos[[#This Row],[VALOR TOTAL MERCADO]]-tb_investimentos[[#This Row],[VALOR TOTAL PONDERADO]],"") | T39: =IFERROR(_xlfn.XLOOKUP(tb_investimentos[[#This Row],[DESCRIÇÃO]],'INFO AÇÕES'!E:E,'INFO AÇÕES'!H:H),"") | U39: =IFERROR((tb_investimentos[[#This Row],[VALOR TOTAL MERCADO]]-tb_investimentos[[#This Row],[VALOR TOTAL PONDERADO]])/tb_investimentos[[#This Row],[VALOR TOTAL PONDERADO]],"")
... B47: Saídas | C47: 46361 | D47: Banco do Brasil | E47: =IF(tb_investimentos[[#This Row],[TIPO MOVIMENTAÇÃO]]="Aporte",_xlfn.XLOOKUP(tb_investimentos[[#This Row],[DESCRIÇÃO]],'INFO AÇÕES'!E:E,'INFO AÇÕES'!I:I),"BRL") -> BRL | F47: Cartão de Crédito | G47: 1 | H47: 500 | I47: Banco do Brasil | J47: =H47*G47 -> 500 | K47: NÃO | L47: =MONTH(tb_investimentos[[#This Row],[DATA]]) -> 12 | M47: =YEAR(tb_investimentos[[#This Row],[DATA]]) -> 2026 | N47: =DAY(tb_investimentos[[#This Row],[DATA]]) -> 5 | O47: =SUMIF($D$5:$D$10000, D47, $J$5:$J$10000) / SUMIF($D$5:$D$10000, D47, $G$5:$G$10000) -> 515.93333 | P47: =tb_investimentos[[#This Row],[PREÇO MÉDIO PONDERADO]]*tb_investimentos[[#This Row],[QUANTIDADE]] -> 515.93333 | Q47: =IFERROR(_xlfn.XLOOKUP(tb_investimentos[[#This Row],[DESCRIÇÃO]],tb_acoes[Símbolo do ticker],tb_acoes[Preço]),"") | R47: =IFERROR(tb_investimentos[[#This Row],[QUANTIDADE]]*tb_investimentos[[#This Row],[PREÇO MERCADO]],"") | S47: =IFERROR(tb_investimentos[[#This Row],[VALOR TOTAL MERCADO]]-tb_investimentos[[#This Row],[VALOR TOTAL PONDERADO]],"") | T47: =IFERROR(_xlfn.XLOOKUP(tb_investimentos[[#This Row],[DESCRIÇÃO]],'INFO AÇÕES'!E:E,'INFO AÇÕES'!H:H),"") | U47: =IFERROR((tb_investimentos[[#This Row],[VALOR TOTAL MERCADO]]-tb_investimentos[[#This Row],[VALOR TOTAL PONDERADO]])/tb_investimentos[[#This Row],[VALOR TOTAL PONDERADO]],"")
B48: Aporte | C48: 46361 | E48: =IF(tb_investimentos[[#This Row],[TIPO MOVIMENTAÇÃO]]="Aporte",_xlfn.XLOOKUP(tb_investimentos[[#This Row],[DESCRIÇÃO]],'INFO AÇÕES'!E:E,'INFO AÇÕES'!I:I),"BRL") -> 0 | F48: Ações | G48: 1 | H48: 2000 | I48: Investimentos BB | J48: =H48*G48 -> 2000 | K48: NÃO | L48: =MONTH(tb_investimentos[[#This Row],[DATA]]) -> 12 | M48: =YEAR(tb_investimentos[[#This Row],[DATA]]) -> 2026 | N48: =DAY(tb_investimentos[[#This Row],[DATA]]) -> 5 | O48: =SUMIF($D$5:$D$10000, D48, $J$5:$J$10000) / SUMIF($D$5:$D$10000, D48, $G$5:$G$10000) -> #DIV/0! | P48: =tb_investimentos[[#This Row],[PREÇO MÉDIO PONDERADO]]*tb_investimentos[[#This Row],[QUANTIDADE]] -> #DIV/0! | Q48: =IFERROR(_xlfn.XLOOKUP(tb_investimentos[[#This Row],[DESCRIÇÃO]],tb_acoes[Símbolo do ticker],tb_acoes[Preço]),"") | R48: =IFERROR(tb_investimentos[[#This Row],[QUANTIDADE]]*tb_investimentos[[#This Row],[PREÇO MERCADO]],"") | S48: =IFERROR(tb_investimentos[[#This Row],[VALOR TOTAL MERCADO]]-tb_investimentos[[#This Row],[VALOR TOTAL PONDERADO]],"") | T48: =IFERROR(_xlfn.XLOOKUP(tb_investimentos[[#This Row],[DESCRIÇÃO]],'INFO AÇÕES'!E:E,'INFO AÇÕES'!H:H),"") | U48: =IFERROR((tb_investimentos[[#This Row],[VALOR TOTAL MERCADO]]-tb_investimentos[[#This Row],[VALOR TOTAL PONDERADO]])/tb_investimentos[[#This Row],[VALOR TOTAL PONDERADO]],"")
B49: Saídas | C49: 46362 | D49: Mercado Livre | E49: =IF(tb_investimentos[[#This Row],[TIPO MOVIMENTAÇÃO]]="Aporte",_xlfn.XLOOKUP(tb_investimentos[[#This Row],[DESCRIÇÃO]],'INFO AÇÕES'!E:E,'INFO AÇÕES'!I:I),"BRL") -> BRL | F49: Emprestimo 2/3 | G49: 1 | H49: 650 | I49: Banco do Brasil | J49: =H49*G49 -> 650 | K49: NÃO | L49: =MONTH(tb_investimentos[[#This Row],[DATA]]) -> 12 | M49: =YEAR(tb_investimentos[[#This Row],[DATA]]) -> 2026 | N49: =DAY(tb_investimentos[[#This Row],[DATA]]) -> 6 | O49: =SUMIF($D$5:$D$10000, D49, $J$5:$J$10000) / SUMIF($D$5:$D$10000, D49, $G$5:$G$10000) -> 650 | P49: =tb_investimentos[[#This Row],[PREÇO MÉDIO PONDERADO]]*tb_investimentos[[#This Row],[QUANTIDADE]] -> 650 | Q49: =IFERROR(_xlfn.XLOOKUP(tb_investimentos[[#This Row],[DESCRIÇÃO]],tb_acoes[Símbolo do ticker],tb_acoes[Preço]),"") | R49: =IFERROR(tb_investimentos[[#This Row],[QUANTIDADE]]*tb_investimentos[[#This Row],[PREÇO MERCADO]],"") | S49: =IFERROR(tb_investimentos[[#This Row],[VALOR TOTAL MERCADO]]-tb_investimentos[[#This Row],[VALOR TOTAL PONDERADO]],"") | T49: =IFERROR(_xlfn.XLOOKUP(tb_investimentos[[#This Row],[DESCRIÇÃO]],'INFO AÇÕES'!E:E,'INFO AÇÕES'!H:H),"") | U49: =IFERROR((tb_investimentos[[#This Row],[VALOR TOTAL MERCADO]]-tb_investimentos[[#This Row],[VALOR TOTAL PONDERADO]])/tb_investimentos[[#This Row],[VALOR TOTAL PONDERADO]],"")
B50: Entradas | C50: 46362 | D50: Capital de Giro | E50: =IF(tb_investimentos[[#This Row],[TIPO MOVIMENTAÇÃO]]="Aporte",_xlfn.XLOOKUP(tb_investimentos[[#This Row],[DESCRIÇÃO]],'INFO AÇÕES'!E:E,'INFO AÇÕES'!I:I),"BRL") -> BRL | F50: Pascoal | G50: 1 | H50: 4710 | I50: Banco do Brasil | J50: =H50*G50 -> 4710 | K50: NÃO | L50: =MONTH(tb_investimentos[[#This Row],[DATA]]) -> 12 | M50: =YEAR(tb_investimentos[[#This Row],[DATA]]) -> 2026 | N50: =DAY(tb_investimentos[[#This Row],[DATA]]) -> 6 | O50: =SUMIF($D$5:$D$10000, D50, $J$5:$J$10000) / SUMIF($D$5:$D$10000, D50, $G$5:$G$10000) -> 4710 | P50: =tb_investimentos[[#This Row],[PREÇO MÉDIO PONDERADO]]*tb_investimentos[[#This Row],[QUANTIDADE]] -> 4710 | Q50: =IFERROR(_xlfn.XLOOKUP(tb_investimentos[[#This Row],[DESCRIÇÃO]],tb_acoes[Símbolo do ticker],tb_acoes[Preço]),"") | R50: =IFERROR(tb_investimentos[[#This Row],[QUANTIDADE]]*tb_investimentos[[#This Row],[PREÇO MERCADO]],"") | S50: =IFERROR(tb_investimentos[[#This Row],[VALOR TOTAL MERCADO]]-tb_investimentos[[#This Row],[VALOR TOTAL PONDERADO]],"") | T50: =IFERROR(_xlfn.XLOOKUP(tb_investimentos[[#This Row],[DESCRIÇÃO]],'INFO AÇÕES'!E:E,'INFO AÇÕES'!H:H),"") | U50: =IFERROR((tb_investimentos[[#This Row],[VALOR TOTAL MERCADO]]-tb_investimentos[[#This Row],[VALOR TOTAL PONDERADO]])/tb_investimentos[[#This Row],[VALOR TOTAL PONDERADO]],"")
B51: Saídas | C51: 46364 | D51: Sabesp | E51: =IF(tb_investimentos[[#This Row],[TIPO MOVIMENTAÇÃO]]="Aporte",_xlfn.XLOOKUP(tb_investimentos[[#This Row],[DESCRIÇÃO]],'INFO AÇÕES'!E:E,'INFO AÇÕES'!I:I),"BRL") -> BRL | F51: Agua | G51: 1 | H51: 25 | I51: Banco do Brasil | J51: =H51*G51 -> 25 | K51: NÃO | L51: =MONTH(tb_investimentos[[#This Row],[DATA]]) -> 12 | M51: =YEAR(tb_investimentos[[#This Row],[DATA]]) -> 2026 | N51: =DAY(tb_investimentos[[#This Row],[DATA]]) -> 8 | O51: =SUMIF($D$5:$D$10000, D51, $J$5:$J$10000) / SUMIF($D$5:$D$10000, D51, $G$5:$G$10000) -> 25 | P51: =tb_investimentos[[#This Row],[PREÇO MÉDIO PONDERADO]]*tb_investimentos[[#This Row],[QUANTIDADE]] -> 25 | Q51: =IFERROR(_xlfn.XLOOKUP(tb_investimentos[[#This Row],[DESCRIÇÃO]],tb_acoes[Símbolo do ticker],tb_acoes[Preço]),"") | R51: =IFERROR(tb_investimentos[[#This Row],[QUANTIDADE]]*tb_investimentos[[#This Row],[PREÇO MERCADO]],"") | S51: =IFERROR(tb_investimentos[[#This Row],[VALOR TOTAL MERCADO]]-tb_investimentos[[#This Row],[VALOR TOTAL PONDERADO]],"") | T51: =IFERROR(_xlfn.XLOOKUP(tb_investimentos[[#This Row],[DESCRIÇÃO]],'INFO AÇÕES'!E:E,'INFO AÇÕES'!H:H),"") | U51: =IFERROR((tb_investimentos[[#This Row],[VALOR TOTAL MERCADO]]-tb_investimentos[[#This Row],[VALOR TOTAL PONDERADO]])/tb_investimentos[[#This Row],[VALOR TOTAL PONDERADO]],"")
B52: Saídas | C52: 46366 | D52: Cia Manah | E52: =IF(tb_investimentos[[#This Row],[TIPO MOVIMENTAÇÃO]]="Aporte",_xlfn.XLOOKUP(tb_investimentos[[#This Row],[DESCRIÇÃO]],'INFO AÇÕES'!E:E,'INFO AÇÕES'!I:I),"BRL") -> BRL | F52: Ballet e Ginastica | G52: 1 | H52: 95 | I52: Banco do Brasil | J52: =H52*G52 -> 95 | K52: NÃO | L52: =MONTH(tb_investimentos[[#This Row],[DATA]]) -> 12 | M52: =YEAR(tb_investimentos[[#This Row],[DATA]]) -> 2026 | N52: =DAY(tb_investimentos[[#This Row],[DATA]]) -> 10 | O52: =SUMIF($D$5:$D$10000, D52, $J$5:$J$10000) / SUMIF($D$5:$D$10000, D52, $G$5:$G$10000) -> 95 | P52: =tb_investimentos[[#This Row],[PREÇO MÉDIO PONDERADO]]*tb_investimentos[[#This Row],[QUANTIDADE]] -> 95 | Q52: =IFERROR(_xlfn.XLOOKUP(tb_investimentos[[#This Row],[DESCRIÇÃO]],tb_acoes[Símbolo do ticker],tb_acoes[Preço]),"") | R52: =IFERROR(tb_investimentos[[#This Row],[QUANTIDADE]]*tb_investimentos[[#This Row],[PREÇO MERCADO]],"") | S52: =IFERROR(tb_investimentos[[#This Row],[VALOR TOTAL MERCADO]]-tb_investimentos[[#This Row],[VALOR TOTAL PONDERADO]],"") | T52: =IFERROR(_xlfn.XLOOKUP(tb_investimentos[[#This Row],[DESCRIÇÃO]],'INFO AÇÕES'!E:E,'INFO AÇÕES'!H:H),"") | U52: =IFERROR((tb_investimentos[[#This Row],[VALOR TOTAL MERCADO]]-tb_investimentos[[#This Row],[VALOR TOTAL PONDERADO]])/tb_investimentos[[#This Row],[VALOR TOTAL PONDERADO]],"")
B53: Saídas | C53: 46368 | D53: Youtube | E53: =IF(tb_investimentos[[#This Row],[TIPO MOVIMENTAÇÃO]]="Aporte",_xlfn.XLOOKUP(tb_investimentos[[#This Row],[DESCRIÇÃO]],'INFO AÇÕES'!E:E,'INFO AÇÕES'!I:I),"BRL") -> BRL | F53: Youtube Music | G53: 1 | H53: 859.94176 | I53: Banco do Brasil | J53: =H53*G53 -> 859.94176 | K53: NÃO | L53: =MONTH(tb_investimentos[[#This Row],[DATA]]) -> 12 | M53: =YEAR(tb_investimentos[[#This Row],[DATA]]) -> 2026 | N53: =DAY(tb_investimentos[[#This Row],[DATA]]) -> 12 | O53: =SUMIF($D$5:$D$10000, D53, $J$5:$J$10000) / SUMIF($D$5:$D$10000, D53, $G$5:$G$10000) -> 137.33454 | P53: =tb_investimentos[[#This Row],[PREÇO MÉDIO PONDERADO]]*tb_investimentos[[#This Row],[QUANTIDADE]] -> 137.33454 | Q53: =IFERROR(_xlfn.XLOOKUP(tb_investimentos[[#This Row],[DESCRIÇÃO]],tb_acoes[Símbolo do ticker],tb_acoes[Preço]),"") | R53: =IFERROR(tb_investimentos[[#This Row],[QUANTIDADE]]*tb_investimentos[[#This Row],[PREÇO MERCADO]],"") | S53: =IFERROR(tb_investimentos[[#This Row],[VALOR TOTAL MERCADO]]-tb_investimentos[[#This Row],[VALOR TOTAL PONDERADO]],"") | T53: =IFERROR(_xlfn.XLOOKUP(tb_investimentos[[#This Row],[DESCRIÇÃO]],'INFO AÇÕES'!E:E,'INFO AÇÕES'!H:H),"") | U53: =IFERROR((tb_investimentos[[#This Row],[VALOR TOTAL MERCADO]]-tb_investimentos[[#This Row],[VALOR TOTAL PONDERADO]])/tb_investimentos[[#This Row],[VALOR TOTAL PONDERADO]],"")
B54: Saídas | C54: 46371 | D54: Vivo | E54: =IF(tb_investimentos[[#This Row],[TIPO MOVIMENTAÇÃO]]="Aporte",_xlfn.XLOOKUP(tb_investimentos[[#This Row],[DESCRIÇÃO]],'INFO AÇÕES'!E:E,'INFO AÇÕES'!I:I),"BRL") -> BRL | F54: Movel | G54: 1 | H54: 39.9 | I54: Banco do Brasil | J54: =H54*G54 -> 39.9 | K54: NÃO | L54: =MONTH(tb_investimentos[[#This Row],[DATA]]) -> 12 | M54: =YEAR(tb_investimentos[[#This Row],[DATA]]) -> 2026 | N54: =DAY(tb_investimentos[[#This Row],[DATA]]) -> 15 | O54: =SUMIF($D$5:$D$10000, D54, $J$5:$J$10000) / SUMIF($D$5:$D$10000, D54, $G$5:$G$10000) -> 59.9 | P54: =tb_investimentos[[#This Row],[PREÇO MÉDIO PONDERADO]]*tb_investimentos[[#This Row],[QUANTIDADE]] -> 59.9 | Q54: =IFERROR(_xlfn.XLOOKUP(tb_investimentos[[#This Row],[DESCRIÇÃO]],tb_acoes[Símbolo do ticker],tb_acoes[Preço]),"") | R54: =IFERROR(tb_investimentos[[#This Row],[QUANTIDADE]]*tb_investimentos[[#This Row],[PREÇO MERCADO]],"") | S54: =IFERROR(tb_investimentos[[#This Row],[VALOR TOTAL MERCADO]]-tb_investimentos[[#This Row],[VALOR TOTAL PONDERADO]],"") | T54: =IFERROR(_xlfn.XLOOKUP(tb_investimentos[[#This Row],[DESCRIÇÃO]],'INFO AÇÕES'!E:E,'INFO AÇÕES'!H:H),"") | U54: =IFERROR((tb_investimentos[[#This Row],[VALOR TOTAL MERCADO]]-tb_investimentos[[#This Row],[VALOR TOTAL PONDERADO]])/tb_investimentos[[#This Row],[VALOR TOTAL PONDERADO]],"")
B55: Saídas | C55: 46371 | D55: Vivo | E55: =IF(tb_investimentos[[#This Row],[TIPO MOVIMENTAÇÃO]]="Aporte",_xlfn.XLOOKUP(tb_investimentos[[#This Row],[DESCRIÇÃO]],'INFO AÇÕES'!E:E,'INFO AÇÕES'!I:I),"BRL") -> BRL | F55: Fibra | G55: 1 | H55: 79.9 | I55: Banco do Brasil | J55: =H55*G55 -> 79.9 | K55: NÃO | L55: =MONTH(tb_investimentos[[#This Row],[DATA]]) -> 12 | M55: =YEAR(tb_investimentos[[#This Row],[DATA]]) -> 2026 | N55: =DAY(tb_investimentos[[#This Row],[DATA]]) -> 15 | O55: =SUMIF($D$5:$D$10000, D55, $J$5:$J$10000) / SUMIF($D$5:$D$10000, D55, $G$5:$G$10000) -> 59.9 | P55: =tb_investimentos[[#This Row],[PREÇO MÉDIO PONDERADO]]*tb_investimentos[[#This Row],[QUANTIDADE]] -> 59.9 | Q55: =IFERROR(_xlfn.XLOOKUP(tb_investimentos[[#This Row],[DESCRIÇÃO]],tb_acoes[Símbolo do ticker],tb_acoes[Preço]),"") | R55: =IFERROR(tb_investimentos[[#This Row],[QUANTIDADE]]*tb_investimentos[[#This Row],[PREÇO MERCADO]],"") | S55: =IFERROR(tb_investimentos[[#This Row],[VALOR TOTAL MERCADO]]-tb_investimentos[[#This Row],[VALOR TOTAL PONDERADO]],"") | T55: =IFERROR(_xlfn.XLOOKUP(tb_investimentos[[#This Row],[DESCRIÇÃO]],'INFO AÇÕES'!E:E,'INFO AÇÕES'!H:H),"") | U55: =IFERROR((tb_investimentos[[#This Row],[VALOR TOTAL MERCADO]]-tb_investimentos[[#This Row],[VALOR TOTAL PONDERADO]])/tb_investimentos[[#This Row],[VALOR TOTAL PONDERADO]],"")
B56: Saídas | C56: 46371 | D56: Enel | E56: =IF(tb_investimentos[[#This Row],[TIPO MOVIMENTAÇÃO]]="Aporte",_xlfn.XLOOKUP(tb_investimentos[[#This Row],[DESCRIÇÃO]],'INFO AÇÕES'!E:E,'INFO AÇÕES'!I:I),"BRL") -> BRL | F56: Energia | G56: 1 | H56: 110 | I56: Banco do Brasil | J56: =H56*G56 -> 110 | K56: NÃO | L56: =MONTH(tb_investimentos[[#This Row],[DATA]]) -> 12 | M56: =YEAR(tb_investimentos[[#This Row],[DATA]]) -> 2026 | N56: =DAY(tb_investimentos[[#This Row],[DATA]]) -> 15 | O56: =SUMIF($D$5:$D$10000, D56, $J$5:$J$10000) / SUMIF($D$5:$D$10000, D56, $G$5:$G$10000) -> 110 | P56: =tb_investimentos[[#This Row],[PREÇO MÉDIO PONDERADO]]*tb_investimentos[[#This Row],[QUANTIDADE]] -> 110 | Q56: =IFERROR(_xlfn.XLOOKUP(tb_investimentos[[#This Row],[DESCRIÇÃO]],tb_acoes[Símbolo do ticker],tb_acoes[Preço]),"") | R56: =IFERROR(tb_investimentos[[#This Row],[QUANTIDADE]]*tb_investimentos[[#This Row],[PREÇO MERCADO]],"") | S56: =IFERROR(tb_investimentos[[#This Row],[VALOR TOTAL MERCADO]]-tb_investimentos[[#This Row],[VALOR TOTAL PONDERADO]],"") | T56: =IFERROR(_xlfn.XLOOKUP(tb_investimentos[[#This Row],[DESCRIÇÃO]],'INFO AÇÕES'!E:E,'INFO AÇÕES'!H:H),"") | U56: =IFERROR((tb_investimentos[[#This Row],[VALOR TOTAL MERCADO]]-tb_investimentos[[#This Row],[VALOR TOTAL PONDERADO]])/tb_investimentos[[#This Row],[VALOR TOTAL PONDERADO]],"")
B57: Saídas | C57: 46371 | D57: Caixa Econômica Federal | E57: =IF(tb_investimentos[[#This Row],[TIPO MOVIMENTAÇÃO]]="Aporte",_xlfn.XLOOKUP(tb_investimentos[[#This Row],[DESCRIÇÃO]],'INFO AÇÕES'!E:E,'INFO AÇÕES'!I:I),"BRL") -> BRL | F57: Evolução de obras | G57: 1 | H57: 797.4426 | I57: Banco do Brasil | J57: =H57*G57 -> 797.4426 | K57: NÃO | L57: =MONTH(tb_investimentos[[#This Row],[DATA]]) -> 12 | M57: =YEAR(tb_investimentos[[#This Row],[DATA]]) -> 2026 | N57: =DAY(tb_investimentos[[#This Row],[DATA]]) -> 15 | O57: =SUMIF($D$5:$D$10000, D57, $J$5:$J$10000) / SUMIF($D$5:$D$10000, D57, $G$5:$G$10000) -> 1629.993 | P57: =tb_investimentos[[#This Row],[PREÇO MÉDIO PONDERADO]]*tb_investimentos[[#This Row],[QUANTIDADE]] -> 1629.993 | Q57: =IFERROR(_xlfn.XLOOKUP(tb_investimentos[[#This Row],[DESCRIÇÃO]],tb_acoes[Símbolo do ticker],tb_acoes[Preço]),"") | R57: =IFERROR(tb_investimentos[[#This Row],[QUANTIDADE]]*tb_investimentos[[#This Row],[PREÇO MERCADO]],"") | S57: =IFERROR(tb_investimentos[[#This Row],[VALOR TOTAL MERCADO]]-tb_investimentos[[#This Row],[VALOR TOTAL PONDERADO]],"") | T57: =IFERROR(_xlfn.XLOOKUP(tb_investimentos[[#This Row],[DESCRIÇÃO]],'INFO AÇÕES'!E:E,'INFO AÇÕES'!H:H),"") | U57: =IFERROR((tb_investimentos[[#This Row],[VALOR TOTAL MERCADO]]-tb_investimentos[[#This Row],[VALOR TOTAL PONDERADO]])/tb_investimentos[[#This Row],[VALOR TOTAL PONDERADO]],"")
B58: Saídas | C58: 46376 | D58: DAS/DARF | E58: =IF(tb_investimentos[[#This Row],[TIPO MOVIMENTAÇÃO]]="Aporte",_xlfn.XLOOKUP(tb_investimentos[[#This Row],[DESCRIÇÃO]],'INFO AÇÕES'!E:E,'INFO AÇÕES'!I:I),"BRL") -> BRL | F58: Impostos | G58: 1 | H58: 87 | I58: Banco do Brasil | J58: =H58*G58 -> 87 | K58: NÃO | L58: =MONTH(tb_investimentos[[#This Row],[DATA]]) -> 12 | M58: =YEAR(tb_investimentos[[#This Row],[DATA]]) -> 2026 | N58: =DAY(tb_investimentos[[#This Row],[DATA]]) -> 20 | O58: =SUMIF($D$5:$D$10000, D58, $J$5:$J$10000) / SUMIF($D$5:$D$10000, D58, $G$5:$G$10000) -> 93.857143 | P58: =tb_investimentos[[#This Row],[PREÇO MÉDIO PONDERADO]]*tb_investimentos[[#This Row],[QUANTIDADE]] -> 93.857143 | Q58: =IFERROR(_xlfn.XLOOKUP(tb_investimentos[[#This Row],[DESCRIÇÃO]],tb_acoes[Símbolo do ticker],tb_acoes[Preço]),"") | R58: =IFERROR(tb_investimentos[[#This Row],[QUANTIDADE]]*tb_investimentos[[#This Row],[PREÇO MERCADO]],"") | S58: =IFERROR(tb_investimentos[[#This Row],[VALOR TOTAL MERCADO]]-tb_investimentos[[#This Row],[VALOR TOTAL PONDERADO]],"") | T58: =IFERROR(_xlfn.XLOOKUP(tb_investimentos[[#This Row],[DESCRIÇÃO]],'INFO AÇÕES'!E:E,'INFO AÇÕES'!H:H),"") | U58: =IFERROR((tb_investimentos[[#This Row],[VALOR TOTAL MERCADO]]-tb_investimentos[[#This Row],[VALOR TOTAL PONDERADO]])/tb_investimentos[[#This Row],[VALOR TOTAL PONDERADO]],"")
B59: Saídas | C59: 46380 | D59: Aluguel | E59: =IF(tb_investimentos[[#This Row],[TIPO MOVIMENTAÇÃO]]="Aporte",_xlfn.XLOOKUP(tb_investimentos[[#This Row],[DESCRIÇÃO]],'INFO AÇÕES'!E:E,'INFO AÇÕES'!I:I),"BRL") -> BRL | F59: Moradia | G59: 1 | H59: 650 | I59: Banco do Brasil | J59: =H59*G59 -> 650 | K59: NÃO | L59: =MONTH(tb_investimentos[[#This Row],[DATA]]) -> 12 | M59: =YEAR(tb_investimentos[[#This Row],[DATA]]) -> 2026 | N59: =DAY(tb_investimentos[[#This Row],[DATA]]) -> 24 | O59: =SUMIF($D$5:$D$10000, D59, $J$5:$J$10000) / SUMIF($D$5:$D$10000, D59, $G$5:$G$10000) -> 650 | P59: =tb_investimentos[[#This Row],[PREÇO MÉDIO PONDERADO]]*tb_investimentos[[#This Row],[QUANTIDADE]] -> 650 | Q59: =IFERROR(_xlfn.XLOOKUP(tb_investimentos[[#This Row],[DESCRIÇÃO]],tb_acoes[Símbolo do ticker],tb_acoes[Preço]),"") | R59: =IFERROR(tb_investimentos[[#This Row],[QUANTIDADE]]*tb_investimentos[[#This Row],[PREÇO MERCADO]],"") | S59: =IFERROR(tb_investimentos[[#This Row],[VALOR TOTAL MERCADO]]-tb_investimentos[[#This Row],[VALOR TOTAL PONDERADO]],"") | T59: =IFERROR(_xlfn.XLOOKUP(tb_investimentos[[#This Row],[DESCRIÇÃO]],'INFO AÇÕES'!E:E,'INFO AÇÕES'!H:H),"") | U59: =IFERROR((tb_investimentos[[#This Row],[VALOR TOTAL MERCADO]]-tb_investimentos[[#This Row],[VALOR TOTAL PONDERADO]])/tb_investimentos[[#This Row],[VALOR TOTAL PONDERADO]],"")
B60: Saídas | C60: 46386 | D60: Tia Mônica | E60: =IF(tb_investimentos[[#This Row],[TIPO MOVIMENTAÇÃO]]="Aporte",_xlfn.XLOOKUP(tb_investimentos[[#This Row],[DESCRIÇÃO]],'INFO AÇÕES'!E:E,'INFO AÇÕES'!I:I),"BRL") -> BRL | F60: Cuidadora | G60: 1 | H60: 650 | I60: Banco do Brasil | J60: =H60*G60 -> 650 | K60: NÃO | L60: =MONTH(tb_investimentos[[#This Row],[DATA]]) -> 12 | M60: =YEAR(tb_investimentos[[#This Row],[DATA]]) -> 2026 | N60: =DAY(tb_investimentos[[#This Row],[DATA]]) -> 30 | O60: =SUMIF($D$5:$D$10000, D60, $J$5:$J$10000) / SUMIF($D$5:$D$10000, D60, $G$5:$G$10000) -> 650 | P60: =tb_investimentos[[#This Row],[PREÇO MÉDIO PONDERADO]]*tb_investimentos[[#This Row],[QUANTIDADE]] -> 650 | Q60: =IFERROR(_xlfn.XLOOKUP(tb_investimentos[[#This Row],[DESCRIÇÃO]],tb_acoes[Símbolo do ticker],tb_acoes[Preço]),"") | R60: =IFERROR(tb_investimentos[[#This Row],[QUANTIDADE]]*tb_investimentos[[#This Row],[PREÇO MERCADO]],"") | S60: =IFERROR(tb_investimentos[[#This Row],[VALOR TOTAL MERCADO]]-tb_investimentos[[#This Row],[VALOR TOTAL PONDERADO]],"") | T60: =IFERROR(_xlfn.XLOOKUP(tb_investimentos[[#This Row],[DESCRIÇÃO]],'INFO AÇÕES'!E:E,'INFO AÇÕES'!H:H),"") | U60: =IFERROR((tb_investimentos[[#This Row],[VALOR TOTAL MERCADO]]-tb_investimentos[[#This Row],[VALOR TOTAL PONDERADO]])/tb_investimentos[[#This Row],[VALOR TOTAL PONDERADO]],"")
... B65: Saídas | C65: 46392 | D65: LoyaltyCom | E65: =IF(tb_investimentos[[#This Row],[TIPO MOVIMENTAÇÃO]]="Aporte",_xlfn.XLOOKUP(tb_investimentos[[#This Row],[DESCRIÇÃO]],'INFO AÇÕES'!E:E,'INFO AÇÕES'!I:I),"BRL") -> BRL | F65: Compra de produtos | G65: 1 | H65: 270 | I65: Banco do Brasil | J65: =H65*G65 -> 270 | K65: NÃO | L65: =MONTH(tb_investimentos[[#This Row],[DATA]]) -> 1 | M65: =YEAR(tb_investimentos[[#This Row],[DATA]]) -> 2027 | N65: =DAY(tb_investimentos[[#This Row],[DATA]]) -> 5 | O65: =SUMIF($D$5:$D$10000, D65, $J$5:$J$10000) / SUMIF($D$5:$D$10000, D65, $G$5:$G$10000) -> 7801.7949 | P65: =tb_investimentos[[#This Row],[PREÇO MÉDIO PONDERADO]]*tb_investimentos[[#This Row],[QUANTIDADE]] -> 7801.7949 | Q65: =IFERROR(_xlfn.XLOOKUP(tb_investimentos[[#This Row],[DESCRIÇÃO]],tb_acoes[Símbolo do ticker],tb_acoes[Preço]),"") | R65: =IFERROR(tb_investimentos[[#This Row],[QUANTIDADE]]*tb_investimentos[[#This Row],[PREÇO MERCADO]],"") | S65: =IFERROR(tb_investimentos[[#This Row],[VALOR TOTAL MERCADO]]-tb_investimentos[[#This Row],[VALOR TOTAL PONDERADO]],"") | T65: =IFERROR(_xlfn.XLOOKUP(tb_investimentos[[#This Row],[DESCRIÇÃO]],'INFO AÇÕES'!E:E,'INFO AÇÕES'!H:H),"") | U65: =IFERROR((tb_investimentos[[#This Row],[VALOR TOTAL MERCADO]]-tb_investimentos[[#This Row],[VALOR TOTAL PONDERADO]])/tb_investimentos[[#This Row],[VALOR TOTAL PONDERADO]],"")
B66: Aporte | C66: 46392 | E66: =IF(tb_investimentos[[#This Row],[TIPO MOVIMENTAÇÃO]]="Aporte",_xlfn.XLOOKUP(tb_investimentos[[#This Row],[DESCRIÇÃO]],'INFO AÇÕES'!E:E,'INFO AÇÕES'!I:I),"BRL") -> 0 | F66: Ações | G66: 1 | H66: 2500 | I66: Investimentos BB | J66: =H66*G66 -> 2500 | K66: NÃO | L66: =MONTH(tb_investimentos[[#This Row],[DATA]]) -> 1 | M66: =YEAR(tb_investimentos[[#This Row],[DATA]]) -> 2027 | N66: =DAY(tb_investimentos[[#This Row],[DATA]]) -> 5 | O66: =SUMIF($D$5:$D$10000, D66, $J$5:$J$10000) / SUMIF($D$5:$D$10000, D66, $G$5:$G$10000) -> #DIV/0! | P66: =tb_investimentos[[#This Row],[PREÇO MÉDIO PONDERADO]]*tb_investimentos[[#This Row],[QUANTIDADE]] -> #DIV/0! | Q66: =IFERROR(_xlfn.XLOOKUP(tb_investimentos[[#This Row],[DESCRIÇÃO]],tb_acoes[Símbolo do ticker],tb_acoes[Preço]),"") | R66: =IFERROR(tb_investimentos[[#This Row],[QUANTIDADE]]*tb_investimentos[[#This Row],[PREÇO MERCADO]],"") | S66: =IFERROR(tb_investimentos[[#This Row],[VALOR TOTAL MERCADO]]-tb_investimentos[[#This Row],[VALOR TOTAL PONDERADO]],"") | T66: =IFERROR(_xlfn.XLOOKUP(tb_investimentos[[#This Row],[DESCRIÇÃO]],'INFO AÇÕES'!E:E,'INFO AÇÕES'!H:H),"") | U66: =IFERROR((tb_investimentos[[#This Row],[VALOR TOTAL MERCADO]]-tb_investimentos[[#This Row],[VALOR TOTAL PONDERADO]])/tb_investimentos[[#This Row],[VALOR TOTAL PONDERADO]],"")
B67: Saídas | C67: 46393 | D67: Mercado Livre | E67: =IF(tb_investimentos[[#This Row],[TIPO MOVIMENTAÇÃO]]="Aporte",_xlfn.XLOOKUP(tb_investimentos[[#This Row],[DESCRIÇÃO]],'INFO AÇÕES'!E:E,'INFO AÇÕES'!I:I),"BRL") -> BRL | F67: Emprestimo 3/3 | G67: 1 | H67: 650 | I67: Banco do Brasil | J67: =H67*G67 -> 650 | K67: NÃO | L67: =MONTH(tb_investimentos[[#This Row],[DATA]]) -> 1 | M67: =YEAR(tb_investimentos[[#This Row],[DATA]]) -> 2027 | N67: =DAY(tb_investimentos[[#This Row],[DATA]]) -> 6 | O67: =SUMIF($D$5:$D$10000, D67, $J$5:$J$10000) / SUMIF($D$5:$D$10000, D67, $G$5:$G$10000) -> 650 | P67: =tb_investimentos[[#This Row],[PREÇO MÉDIO PONDERADO]]*tb_investimentos[[#This Row],[QUANTIDADE]] -> 650 | Q67: =IFERROR(_xlfn.XLOOKUP(tb_investimentos[[#This Row],[DESCRIÇÃO]],tb_acoes[Símbolo do ticker],tb_acoes[Preço]),"") | R67: =IFERROR(tb_investimentos[[#This Row],[QUANTIDADE]]*tb_investimentos[[#This Row],[PREÇO MERCADO]],"") | S67: =IFERROR(tb_investimentos[[#This Row],[VALOR TOTAL MERCADO]]-tb_investimentos[[#This Row],[VALOR TOTAL PONDERADO]],"") | T67: =IFERROR(_xlfn.XLOOKUP(tb_investimentos[[#This Row],[DESCRIÇÃO]],'INFO AÇÕES'!E:E,'INFO AÇÕES'!H:H),"") | U67: =IFERROR((tb_investimentos[[#This Row],[VALOR TOTAL MERCADO]]-tb_investimentos[[#This Row],[VALOR TOTAL PONDERADO]])/tb_investimentos[[#This Row],[VALOR TOTAL PONDERADO]],"")
B68: Entradas | C68: 46393 | D68: Capital de Giro | E68: =IF(tb_investimentos[[#This Row],[TIPO MOVIMENTAÇÃO]]="Aporte",_xlfn.XLOOKUP(tb_investimentos[[#This Row],[DESCRIÇÃO]],'INFO AÇÕES'!E:E,'INFO AÇÕES'!I:I),"BRL") -> BRL | F68: Pascoal | G68: 1 | H68: 4710 | I68: Banco do Brasil | J68: =H68*G68 -> 4710 | K68: NÃO | L68: =MONTH(tb_investimentos[[#This Row],[DATA]]) -> 1 | M68: =YEAR(tb_investimentos[[#This Row],[DATA]]) -> 2027 | N68: =DAY(tb_investimentos[[#This Row],[DATA]]) -> 6 | O68: =SUMIF($D$5:$D$10000, D68, $J$5:$J$10000) / SUMIF($D$5:$D$10000, D68, $G$5:$G$10000) -> 4710 | P68: =tb_investimentos[[#This Row],[PREÇO MÉDIO PONDERADO]]*tb_investimentos[[#This Row],[QUANTIDADE]] -> 4710 | Q68: =IFERROR(_xlfn.XLOOKUP(tb_investimentos[[#This Row],[DESCRIÇÃO]],tb_acoes[Símbolo do ticker],tb_acoes[Preço]),"") | R68: =IFERROR(tb_investimentos[[#This Row],[QUANTIDADE]]*tb_investimentos[[#This Row],[PREÇO MERCADO]],"") | S68: =IFERROR(tb_investimentos[[#This Row],[VALOR TOTAL MERCADO]]-tb_investimentos[[#This Row],[VALOR TOTAL PONDERADO]],"") | T68: =IFERROR(_xlfn.XLOOKUP(tb_investimentos[[#This Row],[DESCRIÇÃO]],'INFO AÇÕES'!E:E,'INFO AÇÕES'!H:H),"") | U68: =IFERROR((tb_investimentos[[#This Row],[VALOR TOTAL MERCADO]]-tb_investimentos[[#This Row],[VALOR TOTAL PONDERADO]])/tb_investimentos[[#This Row],[VALOR TOTAL PONDERADO]],"")
B69: Saídas | C69: 46395 | D69: Sabesp | E69: =IF(tb_investimentos[[#This Row],[TIPO MOVIMENTAÇÃO]]="Aporte",_xlfn.XLOOKUP(tb_investimentos[[#This Row],[DESCRIÇÃO]],'INFO AÇÕES'!E:E,'INFO AÇÕES'!I:I),"BRL") -> BRL | F69: Agua | G69: 1 | H69: 25 | I69: Banco do Brasil | J69: =H69*G69 -> 25 | K69: NÃO | L69: =MONTH(tb_investimentos[[#This Row],[DATA]]) -> 1 | M69: =YEAR(tb_investimentos[[#This Row],[DATA]]) -> 2027 | N69: =DAY(tb_investimentos[[#This Row],[DATA]]) -> 8 | O69: =SUMIF($D$5:$D$10000, D69, $J$5:$J$10000) / SUMIF($D$5:$D$10000, D69, $G$5:$G$10000) -> 25 | P69: =tb_investimentos[[#This Row],[PREÇO MÉDIO PONDERADO]]*tb_investimentos[[#This Row],[QUANTIDADE]] -> 25 | Q69: =IFERROR(_xlfn.XLOOKUP(tb_investimentos[[#This Row],[DESCRIÇÃO]],tb_acoes[Símbolo do ticker],tb_acoes[Preço]),"") | R69: =IFERROR(tb_investimentos[[#This Row],[QUANTIDADE]]*tb_investimentos[[#This Row],[PREÇO MERCADO]],"") | S69: =IFERROR(tb_investimentos[[#This Row],[VALOR TOTAL MERCADO]]-tb_investimentos[[#This Row],[VALOR TOTAL PONDERADO]],"") | T69: =IFERROR(_xlfn.XLOOKUP(tb_investimentos[[#This Row],[DESCRIÇÃO]],'INFO AÇÕES'!E:E,'INFO AÇÕES'!H:H),"") | U69: =IFERROR((tb_investimentos[[#This Row],[VALOR TOTAL MERCADO]]-tb_investimentos[[#This Row],[VALOR TOTAL PONDERADO]])/tb_investimentos[[#This Row],[VALOR TOTAL PONDERADO]],"")
B70: Saídas | C70: 46397 | D70: Cia Manah | E70: =IF(tb_investimentos[[#This Row],[TIPO MOVIMENTAÇÃO]]="Aporte",_xlfn.XLOOKUP(tb_investimentos[[#This Row],[DESCRIÇÃO]],'INFO AÇÕES'!E:E,'INFO AÇÕES'!I:I),"BRL") -> BRL | F70: Ballet e Ginastica | G70: 1 | H70: 95 | I70: Banco do Brasil | J70: =H70*G70 -> 95 | K70: NÃO | L70: =MONTH(tb_investimentos[[#This Row],[DATA]]) -> 1 | M70: =YEAR(tb_investimentos[[#This Row],[DATA]]) -> 2027 | N70: =DAY(tb_investimentos[[#This Row],[DATA]]) -> 10 | O70: =SUMIF($D$5:$D$10000, D70, $J$5:$J$10000) / SUMIF($D$5:$D$10000, D70, $G$5:$G$10000) -> 95 | P70: =tb_investimentos[[#This Row],[PREÇO MÉDIO PONDERADO]]*tb_investimentos[[#This Row],[QUANTIDADE]] -> 95 | Q70: =IFERROR(_xlfn.XLOOKUP(tb_investimentos[[#This Row],[DESCRIÇÃO]],tb_acoes[Símbolo do ticker],tb_acoes[Preço]),"") | R70: =IFERROR(tb_investimentos[[#This Row],[QUANTIDADE]]*tb_investimentos[[#This Row],[PREÇO MERCADO]],"") | S70: =IFERROR(tb_investimentos[[#This Row],[VALOR TOTAL MERCADO]]-tb_investimentos[[#This Row],[VALOR TOTAL PONDERADO]],"") | T70: =IFERROR(_xlfn.XLOOKUP(tb_investimentos[[#This Row],[DESCRIÇÃO]],'INFO AÇÕES'!E:E,'INFO AÇÕES'!H:H),"") | U70: =IFERROR((tb_investimentos[[#This Row],[VALOR TOTAL MERCADO]]-tb_investimentos[[#This Row],[VALOR TOTAL PONDERADO]])/tb_investimentos[[#This Row],[VALOR TOTAL PONDERADO]],"")
B71: Saídas | C71: 46399 | D71: Youtube | E71: =IF(tb_investimentos[[#This Row],[TIPO MOVIMENTAÇÃO]]="Aporte",_xlfn.XLOOKUP(tb_investimentos[[#This Row],[DESCRIÇÃO]],'INFO AÇÕES'!E:E,'INFO AÇÕES'!I:I),"BRL") -> BRL | F71: Youtube Music | G71: 1 | H71: 859.94176 | I71: Banco do Brasil | J71: =H71*G71 -> 859.94176 | K71: NÃO | L71: =MONTH(tb_investimentos[[#This Row],[DATA]]) -> 1 | M71: =YEAR(tb_investimentos[[#This Row],[DATA]]) -> 2027 | N71: =DAY(tb_investimentos[[#This Row],[DATA]]) -> 12 | O71: =SUMIF($D$5:$D$10000, D71, $J$5:$J$10000) / SUMIF($D$5:$D$10000, D71, $G$5:$G$10000) -> 137.33454 | P71: =tb_investimentos[[#This Row],[PREÇO MÉDIO PONDERADO]]*tb_investimentos[[#This Row],[QUANTIDADE]] -> 137.33454 | Q71: =IFERROR(_xlfn.XLOOKUP(tb_investimentos[[#This Row],[DESCRIÇÃO]],tb_acoes[Símbolo do ticker],tb_acoes[Preço]),"") | R71: =IFERROR(tb_investimentos[[#This Row],[QUANTIDADE]]*tb_investimentos[[#This Row],[PREÇO MERCADO]],"") | S71: =IFERROR(tb_investimentos[[#This Row],[VALOR TOTAL MERCADO]]-tb_investimentos[[#This Row],[VALOR TOTAL PONDERADO]],"") | T71: =IFERROR(_xlfn.XLOOKUP(tb_investimentos[[#This Row],[DESCRIÇÃO]],'INFO AÇÕES'!E:E,'INFO AÇÕES'!H:H),"") | U71: =IFERROR((tb_investimentos[[#This Row],[VALOR TOTAL MERCADO]]-tb_investimentos[[#This Row],[VALOR TOTAL PONDERADO]])/tb_investimentos[[#This Row],[VALOR TOTAL PONDERADO]],"")
B72: Saídas | C72: 46402 | D72: Vivo | E72: =IF(tb_investimentos[[#This Row],[TIPO MOVIMENTAÇÃO]]="Aporte",_xlfn.XLOOKUP(tb_investimentos[[#This Row],[DESCRIÇÃO]],'INFO AÇÕES'!E:E,'INFO AÇÕES'!I:I),"BRL") -> BRL | F72: Movel | G72: 1 | H72: 39.9 | I72: Banco do Brasil | J72: =H72*G72 -> 39.9 | K72: NÃO | L72: =MONTH(tb_investimentos[[#This Row],[DATA]]) -> 1 | M72: =YEAR(tb_investimentos[[#This Row],[DATA]]) -> 2027 | N72: =DAY(tb_investimentos[[#This Row],[DATA]]) -> 15 | O72: =SUMIF($D$5:$D$10000, D72, $J$5:$J$10000) / SUMIF($D$5:$D$10000, D72, $G$5:$G$10000) -> 59.9 | P72: =tb_investimentos[[#This Row],[PREÇO MÉDIO PONDERADO]]*tb_investimentos[[#This Row],[QUANTIDADE]] -> 59.9 | Q72: =IFERROR(_xlfn.XLOOKUP(tb_investimentos[[#This Row],[DESCRIÇÃO]],tb_acoes[Símbolo do ticker],tb_acoes[Preço]),"") | R72: =IFERROR(tb_investimentos[[#This Row],[QUANTIDADE]]*tb_investimentos[[#This Row],[PREÇO MERCADO]],"") | S72: =IFERROR(tb_investimentos[[#This Row],[VALOR TOTAL MERCADO]]-tb_investimentos[[#This Row],[VALOR TOTAL PONDERADO]],"") | T72: =IFERROR(_xlfn.XLOOKUP(tb_investimentos[[#This Row],[DESCRIÇÃO]],'INFO AÇÕES'!E:E,'INFO AÇÕES'!H:H),"") | U72: =IFERROR((tb_investimentos[[#This Row],[VALOR TOTAL MERCADO]]-tb_investimentos[[#This Row],[VALOR TOTAL PONDERADO]])/tb_investimentos[[#This Row],[VALOR TOTAL PONDERADO]],"")
B73: Saídas | C73: 46402 | D73: Vivo | E73: =IF(tb_investimentos[[#This Row],[TIPO MOVIMENTAÇÃO]]="Aporte",_xlfn.XLOOKUP(tb_investimentos[[#This Row],[DESCRIÇÃO]],'INFO AÇÕES'!E:E,'INFO AÇÕES'!I:I),"BRL") -> BRL | F73: Fibra | G73: 1 | H73: 79.9 | I73: Banco do Brasil | J73: =H73*G73 -> 79.9 | K73: NÃO | L73: =MONTH(tb_investimentos[[#This Row],[DATA]]) -> 1 | M73: =YEAR(tb_investimentos[[#This Row],[DATA]]) -> 2027 | N73: =DAY(tb_investimentos[[#This Row],[DATA]]) -> 15 | O73: =SUMIF($D$5:$D$10000, D73, $J$5:$J$10000) / SUMIF($D$5:$D$10000, D73, $G$5:$G$10000) -> 59.9 | P73: =tb_investimentos[[#This Row],[PREÇO MÉDIO PONDERADO]]*tb_investimentos[[#This Row],[QUANTIDADE]] -> 59.9 | Q73: =IFERROR(_xlfn.XLOOKUP(tb_investimentos[[#This Row],[DESCRIÇÃO]],tb_acoes[Símbolo do ticker],tb_acoes[Preço]),"") | R73: =IFERROR(tb_investimentos[[#This Row],[QUANTIDADE]]*tb_investimentos[[#This Row],[PREÇO MERCADO]],"") | S73: =IFERROR(tb_investimentos[[#This Row],[VALOR TOTAL MERCADO]]-tb_investimentos[[#This Row],[VALOR TOTAL PONDERADO]],"") | T73: =IFERROR(_xlfn.XLOOKUP(tb_investimentos[[#This Row],[DESCRIÇÃO]],'INFO AÇÕES'!E:E,'INFO AÇÕES'!H:H),"") | U73: =IFERROR((tb_investimentos[[#This Row],[VALOR TOTAL MERCADO]]-tb_investimentos[[#This Row],[VALOR TOTAL PONDERADO]])/tb_investimentos[[#This Row],[VALOR TOTAL PONDERADO]],"")
B74: Saídas | C74: 46402 | D74: Enel | E74: =IF(tb_investimentos[[#This Row],[TIPO MOVIMENTAÇÃO]]="Aporte",_xlfn.XLOOKUP(tb_investimentos[[#This Row],[DESCRIÇÃO]],'INFO AÇÕES'!E:E,'INFO AÇÕES'!I:I),"BRL") -> BRL | F74: Energia | G74: 1 | H74: 110 | I74: Banco do Brasil | J74: =H74*G74 -> 110 | K74: NÃO | L74: =MONTH(tb_investimentos[[#This Row],[DATA]]) -> 1 | M74: =YEAR(tb_investimentos[[#This Row],[DATA]]) -> 2027 | N74: =DAY(tb_investimentos[[#This Row],[DATA]]) -> 15 | O74: =SUMIF($D$5:$D$10000, D74, $J$5:$J$10000) / SUMIF($D$5:$D$10000, D74, $G$5:$G$10000) -> 110 | P74: =tb_investimentos[[#This Row],[PREÇO MÉDIO PONDERADO]]*tb_investimentos[[#This Row],[QUANTIDADE]] -> 110 | Q74: =IFERROR(_xlfn.XLOOKUP(tb_investimentos[[#This Row],[DESCRIÇÃO]],tb_acoes[Símbolo do ticker],tb_acoes[Preço]),"") | R74: =IFERROR(tb_investimentos[[#This Row],[QUANTIDADE]]*tb_investimentos[[#This Row],[PREÇO MERCADO]],"") | S74: =IFERROR(tb_investimentos[[#This Row],[VALOR TOTAL MERCADO]]-tb_investimentos[[#This Row],[VALOR TOTAL PONDERADO]],"") | T74: =IFERROR(_xlfn.XLOOKUP(tb_investimentos[[#This Row],[DESCRIÇÃO]],'INFO AÇÕES'!E:E,'INFO AÇÕES'!H:H),"") | U74: =IFERROR((tb_investimentos[[#This Row],[VALOR TOTAL MERCADO]]-tb_investimentos[[#This Row],[VALOR TOTAL PONDERADO]])/tb_investimentos[[#This Row],[VALOR TOTAL PONDERADO]],"")
B75: Saídas | C75: 46402 | D75: Caixa Econômica Federal | E75: =IF(tb_investimentos[[#This Row],[TIPO MOVIMENTAÇÃO]]="Aporte",_xlfn.XLOOKUP(tb_investimentos[[#This Row],[DESCRIÇÃO]],'INFO AÇÕES'!E:E,'INFO AÇÕES'!I:I),"BRL") -> BRL | F75: Evolução de obras | G75: 1 | H75: 859.94176 | I75: Banco do Brasil | J75: =H75*G75 -> 859.94176 | K75: NÃO | L75: =MONTH(tb_investimentos[[#This Row],[DATA]]) -> 1 | M75: =YEAR(tb_investimentos[[#This Row],[DATA]]) -> 2027 | N75: =DAY(tb_investimentos[[#This Row],[DATA]]) -> 15 | O75: =SUMIF($D$5:$D$10000, D75, $J$5:$J$10000) / SUMIF($D$5:$D$10000, D75, $G$5:$G$10000) -> 1629.993 | P75: =tb_investimentos[[#This Row],[PREÇO MÉDIO PONDERADO]]*tb_investimentos[[#This Row],[QUANTIDADE]] -> 1629.993 | Q75: =IFERROR(_xlfn.XLOOKUP(tb_investimentos[[#This Row],[DESCRIÇÃO]],tb_acoes[Símbolo do ticker],tb_acoes[Preço]),"") | R75: =IFERROR(tb_investimentos[[#This Row],[QUANTIDADE]]*tb_investimentos[[#This Row],[PREÇO MERCADO]],"") | S75: =IFERROR(tb_investimentos[[#This Row],[VALOR TOTAL MERCADO]]-tb_investimentos[[#This Row],[VALOR TOTAL PONDERADO]],"") | T75: =IFERROR(_xlfn.XLOOKUP(tb_investimentos[[#This Row],[DESCRIÇÃO]],'INFO AÇÕES'!E:E,'INFO AÇÕES'!H:H),"") | U75: =IFERROR((tb_investimentos[[#This Row],[VALOR TOTAL MERCADO]]-tb_investimentos[[#This Row],[VALOR TOTAL PONDERADO]])/tb_investimentos[[#This Row],[VALOR TOTAL PONDERADO]],"")
B76: Saídas | C76: 46407 | D76: DAS/DARF | E76: =IF(tb_investimentos[[#This Row],[TIPO MOVIMENTAÇÃO]]="Aporte",_xlfn.XLOOKUP(tb_investimentos[[#This Row],[DESCRIÇÃO]],'INFO AÇÕES'!E:E,'INFO AÇÕES'!I:I),"BRL") -> BRL | F76: Impostos | G76: 1 | H76: 95 | I76: Banco do Brasil | J76: =H76*G76 -> 95 | K76: NÃO | L76: =MONTH(tb_investimentos[[#This Row],[DATA]]) -> 1 | M76: =YEAR(tb_investimentos[[#This Row],[DATA]]) -> 2027 | N76: =DAY(tb_investimentos[[#This Row],[DATA]]) -> 20 | O76: =SUMIF($D$5:$D$10000, D76, $J$5:$J$10000) / SUMIF($D$5:$D$10000, D76, $G$5:$G$10000) -> 93.857143 | P76: =tb_investimentos[[#This Row],[PREÇO MÉDIO PONDERADO]]*tb_investimentos[[#This Row],[QUANTIDADE]] -> 93.857143 | Q76: =IFERROR(_xlfn.XLOOKUP(tb_investimentos[[#This Row],[DESCRIÇÃO]],tb_acoes[Símbolo do ticker],tb_acoes[Preço]),"") | R76: =IFERROR(tb_investimentos[[#This Row],[QUANTIDADE]]*tb_investimentos[[#This Row],[PREÇO MERCADO]],"") | S76: =IFERROR(tb_investimentos[[#This Row],[VALOR TOTAL MERCADO]]-tb_investimentos[[#This Row],[VALOR TOTAL PONDERADO]],"") | T76: =IFERROR(_xlfn.XLOOKUP(tb_investimentos[[#This Row],[DESCRIÇÃO]],'INFO AÇÕES'!E:E,'INFO AÇÕES'!H:H),"") | U76: =IFERROR((tb_investimentos[[#This Row],[VALOR TOTAL MERCADO]]-tb_investimentos[[#This Row],[VALOR TOTAL PONDERADO]])/tb_investimentos[[#This Row],[VALOR TOTAL PONDERADO]],"")
B77: Saídas | C77: 46411 | D77: Aluguel | E77: =IF(tb_investimentos[[#This Row],[TIPO MOVIMENTAÇÃO]]="Aporte",_xlfn.XLOOKUP(tb_investimentos[[#This Row],[DESCRIÇÃO]],'INFO AÇÕES'!E:E,'INFO AÇÕES'!I:I),"BRL") -> BRL | F77: Moradia | G77: 1 | H77: 650 | I77: Banco do Brasil | J77: =H77*G77 -> 650 | K77: NÃO | L77: =MONTH(tb_investimentos[[#This Row],[DATA]]) -> 1 | M77: =YEAR(tb_investimentos[[#This Row],[DATA]]) -> 2027 | N77: =DAY(tb_investimentos[[#This Row],[DATA]]) -> 24 | O77: =SUMIF($D$5:$D$10000, D77, $J$5:$J$10000) / SUMIF($D$5:$D$10000, D77, $G$5:$G$10000) -> 650 | P77: =tb_investimentos[[#This Row],[PREÇO MÉDIO PONDERADO]]*tb_investimentos[[#This Row],[QUANTIDADE]] -> 650 | Q77: =IFERROR(_xlfn.XLOOKUP(tb_investimentos[[#This Row],[DESCRIÇÃO]],tb_acoes[Símbolo do ticker],tb_acoes[Preço]),"") | R77: =IFERROR(tb_investimentos[[#This Row],[QUANTIDADE]]*tb_investimentos[[#This Row],[PREÇO MERCADO]],"") | S77: =IFERROR(tb_investimentos[[#This Row],[VALOR TOTAL MERCADO]]-tb_investimentos[[#This Row],[VALOR TOTAL PONDERADO]],"") | T77: =IFERROR(_xlfn.XLOOKUP(tb_investimentos[[#This Row],[DESCRIÇÃO]],'INFO AÇÕES'!E:E,'INFO AÇÕES'!H:H),"") | U77: =IFERROR((tb_investimentos[[#This Row],[VALOR TOTAL MERCADO]]-tb_investimentos[[#This Row],[VALOR TOTAL PONDERADO]])/tb_investimentos[[#This Row],[VALOR TOTAL PONDERADO]],"")
B78: Saídas | C78: 46417 | D78: Tia Mônica | E78: =IF(tb_investimentos[[#This Row],[TIPO MOVIMENTAÇÃO]]="Aporte",_xlfn.XLOOKUP(tb_investimentos[[#This Row],[DESCRIÇÃO]],'INFO AÇÕES'!E:E,'INFO AÇÕES'!I:I),"BRL") -> BRL | F78: Cuidadora | G78: 1 | H78: 650 | I78: Banco do Brasil | J78: =H78*G78 -> 650 | K78: NÃO | L78: =MONTH(tb_investimentos[[#This Row],[DATA]]) -> 1 | M78: =YEAR(tb_investimentos[[#This Row],[DATA]]) -> 2027 | N78: =DAY(tb_investimentos[[#This Row],[DATA]]) -> 30 | O78: =SUMIF($D$5:$D$10000, D78, $J$5:$J$10000) / SUMIF($D$5:$D$10000, D78, $G$5:$G$10000) -> 650 | P78: =tb_investimentos[[#This Row],[PREÇO MÉDIO PONDERADO]]*tb_investimentos[[#This Row],[QUANTIDADE]] -> 650 | Q78: =IFERROR(_xlfn.XLOOKUP(tb_investimentos[[#This Row],[DESCRIÇÃO]],tb_acoes[Símbolo do ticker],tb_acoes[Preço]),"") | R78: =IFERROR(tb_investimentos[[#This Row],[QUANTIDADE]]*tb_investimentos[[#This Row],[PREÇO MERCADO]],"") | S78: =IFERROR(tb_investimentos[[#This Row],[VALOR TOTAL MERCADO]]-tb_investimentos[[#This Row],[VALOR TOTAL PONDERADO]],"") | T78: =IFERROR(_xlfn.XLOOKUP(tb_investimentos[[#This Row],[DESCRIÇÃO]],'INFO AÇÕES'!E:E,'INFO AÇÕES'!H:H),"") | U78: =IFERROR((tb_investimentos[[#This Row],[VALOR TOTAL MERCADO]]-tb_investimentos[[#This Row],[VALOR TOTAL PONDERADO]])/tb_investimentos[[#This Row],[VALOR TOTAL PONDERADO]],"")
... B82: Saídas | C82: 46423 | D82: Banco do Brasil | E82: =IF(tb_investimentos[[#This Row],[TIPO MOVIMENTAÇÃO]]="Aporte",_xlfn.XLOOKUP(tb_investimentos[[#This Row],[DESCRIÇÃO]],'INFO AÇÕES'!E:E,'INFO AÇÕES'!I:I),"BRL") -> BRL | F82: Cartão de Crédito | G82: 1 | H82: 500 | I82: Banco do Brasil | J82: =H82*G82 -> 500 | K82: NÃO | L82: =MONTH(tb_investimentos[[#This Row],[DATA]]) -> 2 | M82: =YEAR(tb_investimentos[[#This Row],[DATA]]) -> 2027 | N82: =DAY(tb_investimentos[[#This Row],[DATA]]) -> 5 | O82: =SUMIF($D$5:$D$10000, D82, $J$5:$J$10000) / SUMIF($D$5:$D$10000, D82, $G$5:$G$10000) -> 515.93333 | P82: =tb_investimentos[[#This Row],[PREÇO MÉDIO PONDERADO]]*tb_investimentos[[#This Row],[QUANTIDADE]] -> 515.93333 | Q82: =IFERROR(_xlfn.XLOOKUP(tb_investimentos[[#This Row],[DESCRIÇÃO]],tb_acoes[Símbolo do ticker],tb_acoes[Preço]),"") | R82: =IFERROR(tb_investimentos[[#This Row],[QUANTIDADE]]*tb_investimentos[[#This Row],[PREÇO MERCADO]],"") | S82: =IFERROR(tb_investimentos[[#This Row],[VALOR TOTAL MERCADO]]-tb_investimentos[[#This Row],[VALOR TOTAL PONDERADO]],"") | T82: =IFERROR(_xlfn.XLOOKUP(tb_investimentos[[#This Row],[DESCRIÇÃO]],'INFO AÇÕES'!E:E,'INFO AÇÕES'!H:H),"") | U82: =IFERROR((tb_investimentos[[#This Row],[VALOR TOTAL MERCADO]]-tb_investimentos[[#This Row],[VALOR TOTAL PONDERADO]])/tb_investimentos[[#This Row],[VALOR TOTAL PONDERADO]],"")
B83: Aporte | C83: 46423 | E83: =IF(tb_investimentos[[#This Row],[TIPO MOVIMENTAÇÃO]]="Aporte",_xlfn.XLOOKUP(tb_investimentos[[#This Row],[DESCRIÇÃO]],'INFO AÇÕES'!E:E,'INFO AÇÕES'!I:I),"BRL") -> 0 | F83: Ações | G83: 1 | H83: 2500 | I83: Investimentos BB | J83: =H83*G83 -> 2500 | K83: NÃO | L83: =MONTH(tb_investimentos[[#This Row],[DATA]]) -> 2 | M83: =YEAR(tb_investimentos[[#This Row],[DATA]]) -> 2027 | N83: =DAY(tb_investimentos[[#This Row],[DATA]]) -> 5 | O83: =SUMIF($D$5:$D$10000, D83, $J$5:$J$10000) / SUMIF($D$5:$D$10000, D83, $G$5:$G$10000) -> #DIV/0! | P83: =tb_investimentos[[#This Row],[PREÇO MÉDIO PONDERADO]]*tb_investimentos[[#This Row],[QUANTIDADE]] -> #DIV/0! | Q83: =IFERROR(_xlfn.XLOOKUP(tb_investimentos[[#This Row],[DESCRIÇÃO]],tb_acoes[Símbolo do ticker],tb_acoes[Preço]),"") | R83: =IFERROR(tb_investimentos[[#This Row],[QUANTIDADE]]*tb_investimentos[[#This Row],[PREÇO MERCADO]],"") | S83: =IFERROR(tb_investimentos[[#This Row],[VALOR TOTAL MERCADO]]-tb_investimentos[[#This Row],[VALOR TOTAL PONDERADO]],"") | T83: =IFERROR(_xlfn.XLOOKUP(tb_investimentos[[#This Row],[DESCRIÇÃO]],'INFO AÇÕES'!E:E,'INFO AÇÕES'!H:H),"") | U83: =IFERROR((tb_investimentos[[#This Row],[VALOR TOTAL MERCADO]]-tb_investimentos[[#This Row],[VALOR TOTAL PONDERADO]])/tb_investimentos[[#This Row],[VALOR TOTAL PONDERADO]],"")
B84: Saídas | C84: 46426 | D84: Sabesp | E84: =IF(tb_investimentos[[#This Row],[TIPO MOVIMENTAÇÃO]]="Aporte",_xlfn.XLOOKUP(tb_investimentos[[#This Row],[DESCRIÇÃO]],'INFO AÇÕES'!E:E,'INFO AÇÕES'!I:I),"BRL") -> BRL | F84: Agua | G84: 1 | H84: 25 | I84: Banco do Brasil | J84: =H84*G84 -> 25 | K84: NÃO | L84: =MONTH(tb_investimentos[[#This Row],[DATA]]) -> 2 | M84: =YEAR(tb_investimentos[[#This Row],[DATA]]) -> 2027 | N84: =DAY(tb_investimentos[[#This Row],[DATA]]) -> 8 | O84: =SUMIF($D$5:$D$10000, D84, $J$5:$J$10000) / SUMIF($D$5:$D$10000, D84, $G$5:$G$10000) -> 25 | P84: =tb_investimentos[[#This Row],[PREÇO MÉDIO PONDERADO]]*tb_investimentos[[#This Row],[QUANTIDADE]] -> 25 | Q84: =IFERROR(_xlfn.XLOOKUP(tb_investimentos[[#This Row],[DESCRIÇÃO]],tb_acoes[Símbolo do ticker],tb_acoes[Preço]),"") | R84: =IFERROR(tb_investimentos[[#This Row],[QUANTIDADE]]*tb_investimentos[[#This Row],[PREÇO MERCADO]],"") | S84: =IFERROR(tb_investimentos[[#This Row],[VALOR TOTAL MERCADO]]-tb_investimentos[[#This Row],[VALOR TOTAL PONDERADO]],"") | T84: =IFERROR(_xlfn.XLOOKUP(tb_investimentos[[#This Row],[DESCRIÇÃO]],'INFO AÇÕES'!E:E,'INFO AÇÕES'!H:H),"") | U84: =IFERROR((tb_investimentos[[#This Row],[VALOR TOTAL MERCADO]]-tb_investimentos[[#This Row],[VALOR TOTAL PONDERADO]])/tb_investimentos[[#This Row],[VALOR TOTAL PONDERADO]],"")
B85: Saídas | C85: 46428 | D85: Cia Manah | E85: =IF(tb_investimentos[[#This Row],[TIPO MOVIMENTAÇÃO]]="Aporte",_xlfn.XLOOKUP(tb_investimentos[[#This Row],[DESCRIÇÃO]],'INFO AÇÕES'!E:E,'INFO AÇÕES'!I:I),"BRL") -> BRL | F85: Ballet e Ginastica | G85: 1 | H85: 95 | I85: Banco do Brasil | J85: =H85*G85 -> 95 | K85: NÃO | L85: =MONTH(tb_investimentos[[#This Row],[DATA]]) -> 2 | M85: =YEAR(tb_investimentos[[#This Row],[DATA]]) -> 2027 | N85: =DAY(tb_investimentos[[#This Row],[DATA]]) -> 10 | O85: =SUMIF($D$5:$D$10000, D85, $J$5:$J$10000) / SUMIF($D$5:$D$10000, D85, $G$5:$G$10000) -> 95 | P85: =tb_investimentos[[#This Row],[PREÇO MÉDIO PONDERADO]]*tb_investimentos[[#This Row],[QUANTIDADE]] -> 95 | Q85: =IFERROR(_xlfn.XLOOKUP(tb_investimentos[[#This Row],[DESCRIÇÃO]],tb_acoes[Símbolo do ticker],tb_acoes[Preço]),"") | R85: =IFERROR(tb_investimentos[[#This Row],[QUANTIDADE]]*tb_investimentos[[#This Row],[PREÇO MERCADO]],"") | S85: =IFERROR(tb_investimentos[[#This Row],[VALOR TOTAL MERCADO]]-tb_investimentos[[#This Row],[VALOR TOTAL PONDERADO]],"") | T85: =IFERROR(_xlfn.XLOOKUP(tb_investimentos[[#This Row],[DESCRIÇÃO]],'INFO AÇÕES'!E:E,'INFO AÇÕES'!H:H),"") | U85: =IFERROR((tb_investimentos[[#This Row],[VALOR TOTAL MERCADO]]-tb_investimentos[[#This Row],[VALOR TOTAL PONDERADO]])/tb_investimentos[[#This Row],[VALOR TOTAL PONDERADO]],"")
B86: Saídas | C86: 46430 | D86: Youtube | E86: =IF(tb_investimentos[[#This Row],[TIPO MOVIMENTAÇÃO]]="Aporte",_xlfn.XLOOKUP(tb_investimentos[[#This Row],[DESCRIÇÃO]],'INFO AÇÕES'!E:E,'INFO AÇÕES'!I:I),"BRL") -> BRL | F86: Youtube Music | G86: 1 | H86: 16.9 | I86: Banco do Brasil | J86: =H86*G86 -> 16.9 | K86: NÃO | L86: =MONTH(tb_investimentos[[#This Row],[DATA]]) -> 2 | M86: =YEAR(tb_investimentos[[#This Row],[DATA]]) -> 2027 | N86: =DAY(tb_investimentos[[#This Row],[DATA]]) -> 12 | O86: =SUMIF($D$5:$D$10000, D86, $J$5:$J$10000) / SUMIF($D$5:$D$10000, D86, $G$5:$G$10000) -> 137.33454 | P86: =tb_investimentos[[#This Row],[PREÇO MÉDIO PONDERADO]]*tb_investimentos[[#This Row],[QUANTIDADE]] -> 137.33454 | Q86: =IFERROR(_xlfn.XLOOKUP(tb_investimentos[[#This Row],[DESCRIÇÃO]],tb_acoes[Símbolo do ticker],tb_acoes[Preço]),"") | R86: =IFERROR(tb_investimentos[[#This Row],[QUANTIDADE]]*tb_investimentos[[#This Row],[PREÇO MERCADO]],"") | S86: =IFERROR(tb_investimentos[[#This Row],[VALOR TOTAL MERCADO]]-tb_investimentos[[#This Row],[VALOR TOTAL PONDERADO]],"") | T86: =IFERROR(_xlfn.XLOOKUP(tb_investimentos[[#This Row],[DESCRIÇÃO]],'INFO AÇÕES'!E:E,'INFO AÇÕES'!H:H),"") | U86: =IFERROR((tb_investimentos[[#This Row],[VALOR TOTAL MERCADO]]-tb_investimentos[[#This Row],[VALOR TOTAL PONDERADO]])/tb_investimentos[[#This Row],[VALOR TOTAL PONDERADO]],"")
B87: Saídas | C87: 46433 | D87: Vivo | E87: =IF(tb_investimentos[[#This Row],[TIPO MOVIMENTAÇÃO]]="Aporte",_xlfn.XLOOKUP(tb_investimentos[[#This Row],[DESCRIÇÃO]],'INFO AÇÕES'!E:E,'INFO AÇÕES'!I:I),"BRL") -> BRL | F87: Movel | G87: 1 | H87: 39.9 | I87: Banco do Brasil | J87: =H87*G87 -> 39.9 | K87: NÃO | L87: =MONTH(tb_investimentos[[#This Row],[DATA]]) -> 2 | M87: =YEAR(tb_investimentos[[#This Row],[DATA]]) -> 2027 | N87: =DAY(tb_investimentos[[#This Row],[DATA]]) -> 15 | O87: =SUMIF($D$5:$D$10000, D87, $J$5:$J$10000) / SUMIF($D$5:$D$10000, D87, $G$5:$G$10000) -> 59.9 | P87: =tb_investimentos[[#This Row],[PREÇO MÉDIO PONDERADO]]*tb_investimentos[[#This Row],[QUANTIDADE]] -> 59.9 | Q87: =IFERROR(_xlfn.XLOOKUP(tb_investimentos[[#This Row],[DESCRIÇÃO]],tb_acoes[Símbolo do ticker],tb_acoes[Preço]),"") | R87: =IFERROR(tb_investimentos[[#This Row],[QUANTIDADE]]*tb_investimentos[[#This Row],[PREÇO MERCADO]],"") | S87: =IFERROR(tb_investimentos[[#This Row],[VALOR TOTAL MERCADO]]-tb_investimentos[[#This Row],[VALOR TOTAL PONDERADO]],"") | T87: =IFERROR(_xlfn.XLOOKUP(tb_investimentos[[#This Row],[DESCRIÇÃO]],'INFO AÇÕES'!E:E,'INFO AÇÕES'!H:H),"") | U87: =IFERROR((tb_investimentos[[#This Row],[VALOR TOTAL MERCADO]]-tb_investimentos[[#This Row],[VALOR TOTAL PONDERADO]])/tb_investimentos[[#This Row],[VALOR TOTAL PONDERADO]],"")
B88: Saídas | C88: 46433 | D88: Vivo | E88: =IF(tb_investimentos[[#This Row],[TIPO MOVIMENTAÇÃO]]="Aporte",_xlfn.XLOOKUP(tb_investimentos[[#This Row],[DESCRIÇÃO]],'INFO AÇÕES'!E:E,'INFO AÇÕES'!I:I),"BRL") -> BRL | F88: Fibra | G88: 1 | H88: 79.9 | I88: Banco do Brasil | J88: =H88*G88 -> 79.9 | K88: NÃO | L88: =MONTH(tb_investimentos[[#This Row],[DATA]]) -> 2 | M88: =YEAR(tb_investimentos[[#This Row],[DATA]]) -> 2027 | N88: =DAY(tb_investimentos[[#This Row],[DATA]]) -> 15 | O88: =SUMIF($D$5:$D$10000, D88, $J$5:$J$10000) / SUMIF($D$5:$D$10000, D88, $G$5:$G$10000) -> 59.9 | P88: =tb_investimentos[[#This Row],[PREÇO MÉDIO PONDERADO]]*tb_investimentos[[#This Row],[QUANTIDADE]] -> 59.9 | Q88: =IFERROR(_xlfn.XLOOKUP(tb_investimentos[[#This Row],[DESCRIÇÃO]],tb_acoes[Símbolo do ticker],tb_acoes[Preço]),"") | R88: =IFERROR(tb_investimentos[[#This Row],[QUANTIDADE]]*tb_investimentos[[#This Row],[PREÇO MERCADO]],"") | S88: =IFERROR(tb_investimentos[[#This Row],[VALOR TOTAL MERCADO]]-tb_investimentos[[#This Row],[VALOR TOTAL PONDERADO]],"") | T88: =IFERROR(_xlfn.XLOOKUP(tb_investimentos[[#This Row],[DESCRIÇÃO]],'INFO AÇÕES'!E:E,'INFO AÇÕES'!H:H),"") | U88: =IFERROR((tb_investimentos[[#This Row],[VALOR TOTAL MERCADO]]-tb_investimentos[[#This Row],[VALOR TOTAL PONDERADO]])/tb_investimentos[[#This Row],[VALOR TOTAL PONDERADO]],"")
B89: Saídas | C89: 46433 | D89: Enel | E89: =IF(tb_investimentos[[#This Row],[TIPO MOVIMENTAÇÃO]]="Aporte",_xlfn.XLOOKUP(tb_investimentos[[#This Row],[DESCRIÇÃO]],'INFO AÇÕES'!E:E,'INFO AÇÕES'!I:I),"BRL") -> BRL | F89: Energia | G89: 1 | H89: 110 | I89: Banco do Brasil | J89: =H89*G89 -> 110 | K89: NÃO | L89: =MONTH(tb_investimentos[[#This Row],[DATA]]) -> 2 | M89: =YEAR(tb_investimentos[[#This Row],[DATA]]) -> 2027 | N89: =DAY(tb_investimentos[[#This Row],[DATA]]) -> 15 | O89: =SUMIF($D$5:$D$10000, D89, $J$5:$J$10000) / SUMIF($D$5:$D$10000, D89, $G$5:$G$10000) -> 110 | P89: =tb_investimentos[[#This Row],[PREÇO MÉDIO PONDERADO]]*tb_investimentos[[#This Row],[QUANTIDADE]] -> 110 | Q89: =IFERROR(_xlfn.XLOOKUP(tb_investimentos[[#This Row],[DESCRIÇÃO]],tb_acoes[Símbolo do ticker],tb_acoes[Preço]),"") | R89: =IFERROR(tb_investimentos[[#This Row],[QUANTIDADE]]*tb_investimentos[[#This Row],[PREÇO MERCADO]],"") | S89: =IFERROR(tb_investimentos[[#This Row],[VALOR TOTAL MERCADO]]-tb_investimentos[[#This Row],[VALOR TOTAL PONDERADO]],"") | T89: =IFERROR(_xlfn.XLOOKUP(tb_investimentos[[#This Row],[DESCRIÇÃO]],'INFO AÇÕES'!E:E,'INFO AÇÕES'!H:H),"") | U89: =IFERROR((tb_investimentos[[#This Row],[VALOR TOTAL MERCADO]]-tb_investimentos[[#This Row],[VALOR TOTAL PONDERADO]])/tb_investimentos[[#This Row],[VALOR TOTAL PONDERADO]],"")
B90: Saídas | C90: 46433 | D90: Caixa Econômica Federal | E90: =IF(tb_investimentos[[#This Row],[TIPO MOVIMENTAÇÃO]]="Aporte",_xlfn.XLOOKUP(tb_investimentos[[#This Row],[DESCRIÇÃO]],'INFO AÇÕES'!E:E,'INFO AÇÕES'!I:I),"BRL") -> BRL | F90: Evolução de obras | G90: 1 | H90: 990.9941 | I90: Banco do Brasil | J90: =H90*G90 -> 990.9941 | K90: NÃO | L90: =MONTH(tb_investimentos[[#This Row],[DATA]]) -> 2 | M90: =YEAR(tb_investimentos[[#This Row],[DATA]]) -> 2027 | N90: =DAY(tb_investimentos[[#This Row],[DATA]]) -> 15 | O90: =SUMIF($D$5:$D$10000, D90, $J$5:$J$10000) / SUMIF($D$5:$D$10000, D90, $G$5:$G$10000) -> 1629.993 | P90: =tb_investimentos[[#This Row],[PREÇO MÉDIO PONDERADO]]*tb_investimentos[[#This Row],[QUANTIDADE]] -> 1629.993 | Q90: =IFERROR(_xlfn.XLOOKUP(tb_investimentos[[#This Row],[DESCRIÇÃO]],tb_acoes[Símbolo do ticker],tb_acoes[Preço]),"") | R90: =IFERROR(tb_investimentos[[#This Row],[QUANTIDADE]]*tb_investimentos[[#This Row],[PREÇO MERCADO]],"") | S90: =IFERROR(tb_investimentos[[#This Row],[VALOR TOTAL MERCADO]]-tb_investimentos[[#This Row],[VALOR TOTAL PONDERADO]],"") | T90: =IFERROR(_xlfn.XLOOKUP(tb_investimentos[[#This Row],[DESCRIÇÃO]],'INFO AÇÕES'!E:E,'INFO AÇÕES'!H:H),"") | U90: =IFERROR((tb_investimentos[[#This Row],[VALOR TOTAL MERCADO]]-tb_investimentos[[#This Row],[VALOR TOTAL PONDERADO]])/tb_investimentos[[#This Row],[VALOR TOTAL PONDERADO]],"")
B91: Saídas | C91: 46438 | D91: DAS/DARF | E91: =IF(tb_investimentos[[#This Row],[TIPO MOVIMENTAÇÃO]]="Aporte",_xlfn.XLOOKUP(tb_investimentos[[#This Row],[DESCRIÇÃO]],'INFO AÇÕES'!E:E,'INFO AÇÕES'!I:I),"BRL") -> BRL | F91: Impostos | G91: 1 | H91: 95 | I91: Banco do Brasil | J91: =H91*G91 -> 95 | K91: NÃO | L91: =MONTH(tb_investimentos[[#This Row],[DATA]]) -> 2 | M91: =YEAR(tb_investimentos[[#This Row],[DATA]]) -> 2027 | N91: =DAY(tb_investimentos[[#This Row],[DATA]]) -> 20 | O91: =SUMIF($D$5:$D$10000, D91, $J$5:$J$10000) / SUMIF($D$5:$D$10000, D91, $G$5:$G$10000) -> 93.857143 | P91: =tb_investimentos[[#This Row],[PREÇO MÉDIO PONDERADO]]*tb_investimentos[[#This Row],[QUANTIDADE]] -> 93.857143 | Q91: =IFERROR(_xlfn.XLOOKUP(tb_investimentos[[#This Row],[DESCRIÇÃO]],tb_acoes[Símbolo do ticker],tb_acoes[Preço]),"") | R91: =IFERROR(tb_investimentos[[#This Row],[QUANTIDADE]]*tb_investimentos[[#This Row],[PREÇO MERCADO]],"") | S91: =IFERROR(tb_investimentos[[#This Row],[VALOR TOTAL MERCADO]]-tb_investimentos[[#This Row],[VALOR TOTAL PONDERADO]],"") | T91: =IFERROR(_xlfn.XLOOKUP(tb_investimentos[[#This Row],[DESCRIÇÃO]],'INFO AÇÕES'!E:E,'INFO AÇÕES'!H:H),"") | U91: =IFERROR((tb_investimentos[[#This Row],[VALOR TOTAL MERCADO]]-tb_investimentos[[#This Row],[VALOR TOTAL PONDERADO]])/tb_investimentos[[#This Row],[VALOR TOTAL PONDERADO]],"")
B92: Saídas | C92: 46442 | D92: Aluguel | E92: =IF(tb_investimentos[[#This Row],[TIPO MOVIMENTAÇÃO]]="Aporte",_xlfn.XLOOKUP(tb_investimentos[[#This Row],[DESCRIÇÃO]],'INFO AÇÕES'!E:E,'INFO AÇÕES'!I:I),"BRL") -> BRL | F92: Moradia | G92: 1 | H92: 650 | I92: Banco do Brasil | J92: =H92*G92 -> 650 | K92: NÃO | L92: =MONTH(tb_investimentos[[#This Row],[DATA]]) -> 2 | M92: =YEAR(tb_investimentos[[#This Row],[DATA]]) -> 2027 | N92: =DAY(tb_investimentos[[#This Row],[DATA]]) -> 24 | O92: =SUMIF($D$5:$D$10000, D92, $J$5:$J$10000) / SUMIF($D$5:$D$10000, D92, $G$5:$G$10000) -> 650 | P92: =tb_investimentos[[#This Row],[PREÇO MÉDIO PONDERADO]]*tb_investimentos[[#This Row],[QUANTIDADE]] -> 650 | Q92: =IFERROR(_xlfn.XLOOKUP(tb_investimentos[[#This Row],[DESCRIÇÃO]],tb_acoes[Símbolo do ticker],tb_acoes[Preço]),"") | R92: =IFERROR(tb_investimentos[[#This Row],[QUANTIDADE]]*tb_investimentos[[#This Row],[PREÇO MERCADO]],"") | S92: =IFERROR(tb_investimentos[[#This Row],[VALOR TOTAL MERCADO]]-tb_investimentos[[#This Row],[VALOR TOTAL PONDERADO]],"") | T92: =IFERROR(_xlfn.XLOOKUP(tb_investimentos[[#This Row],[DESCRIÇÃO]],'INFO AÇÕES'!E:E,'INFO AÇÕES'!H:H),"") | U92: =IFERROR((tb_investimentos[[#This Row],[VALOR TOTAL MERCADO]]-tb_investimentos[[#This Row],[VALOR TOTAL PONDERADO]])/tb_investimentos[[#This Row],[VALOR TOTAL PONDERADO]],"")
B93: Saídas | C93: 46446 | D93: Tia Mônica | E93: =IF(tb_investimentos[[#This Row],[TIPO MOVIMENTAÇÃO]]="Aporte",_xlfn.XLOOKUP(tb_investimentos[[#This Row],[DESCRIÇÃO]],'INFO AÇÕES'!E:E,'INFO AÇÕES'!I:I),"BRL") -> BRL | F93: Cuidadora | G93: 1 | H93: 650 | I93: Banco do Brasil | J93: =H93*G93 -> 650 | K93: NÃO | L93: =MONTH(tb_investimentos[[#This Row],[DATA]]) -> 2 | M93: =YEAR(tb_investimentos[[#This Row],[DATA]]) -> 2027 | N93: =DAY(tb_investimentos[[#This Row],[DATA]]) -> 28 | O93: =SUMIF($D$5:$D$10000, D93, $J$5:$J$10000) / SUMIF($D$5:$D$10000, D93, $G$5:$G$10000) -> 650 | P93: =tb_investimentos[[#This Row],[PREÇO MÉDIO PONDERADO]]*tb_investimentos[[#This Row],[QUANTIDADE]] -> 650 | Q93: =IFERROR(_xlfn.XLOOKUP(tb_investimentos[[#This Row],[DESCRIÇÃO]],tb_acoes[Símbolo do ticker],tb_acoes[Preço]),"") | R93: =IFERROR(tb_investimentos[[#This Row],[QUANTIDADE]]*tb_investimentos[[#This Row],[PREÇO MERCADO]],"") | S93: =IFERROR(tb_investimentos[[#This Row],[VALOR TOTAL MERCADO]]-tb_investimentos[[#This Row],[VALOR TOTAL PONDERADO]],"") | T93: =IFERROR(_xlfn.XLOOKUP(tb_investimentos[[#This Row],[DESCRIÇÃO]],'INFO AÇÕES'!E:E,'INFO AÇÕES'!H:H),"") | U93: =IFERROR((tb_investimentos[[#This Row],[VALOR TOTAL MERCADO]]-tb_investimentos[[#This Row],[VALOR TOTAL PONDERADO]])/tb_investimentos[[#This Row],[VALOR TOTAL PONDERADO]],"")
B94: Entradas | C94: 46451 | D94: LoyaltyCom | E94: =IF(tb_investimentos[[#This Row],[TIPO MOVIMENTAÇÃO]]="Aporte",_xlfn.XLOOKUP(tb_investimentos[[#This Row],[DESCRIÇÃO]],'INFO AÇÕES'!E:E,'INFO AÇÕES'!I:I),"BRL") -> BRL | F94: Salário | G94: 1 | H94: 8000 | I94: Banco do Brasil | J94: =H94*G94 -> 8000 | K94: NÃO | L94: =MONTH(tb_investimentos[[#This Row],[DATA]]) -> 3 | M94: =YEAR(tb_investimentos[[#This Row],[DATA]]) -> 2027 | N94: =DAY(tb_investimentos[[#This Row],[DATA]]) -> 5 | O94: =SUMIF($D$5:$D$10000, D94, $J$5:$J$10000) / SUMIF($D$5:$D$10000, D94, $G$5:$G$10000) -> 7801.7949 | P94: =tb_investimentos[[#This Row],[PREÇO MÉDIO PONDERADO]]*tb_investimentos[[#This Row],[QUANTIDADE]] -> 7801.7949 | Q94: =IFERROR(_xlfn.XLOOKUP(tb_investimentos[[#This Row],[DESCRIÇÃO]],tb_acoes[Símbolo do ticker],tb_acoes[Preço]),"") | R94: =IFERROR(tb_investimentos[[#This Row],[QUANTIDADE]]*tb_investimentos[[#This Row],[PREÇO MERCADO]],"") | S94: =IFERROR(tb_investimentos[[#This Row],[VALOR TOTAL MERCADO]]-tb_investimentos[[#This Row],[VALOR TOTAL PONDERADO]],"") | T94: =IFERROR(_xlfn.XLOOKUP(tb_investimentos[[#This Row],[DESCRIÇÃO]],'INFO AÇÕES'!E:E,'INFO AÇÕES'!H:H),"") | U94: =IFERROR((tb_investimentos[[#This Row],[VALOR TOTAL MERCADO]]-tb_investimentos[[#This Row],[VALOR TOTAL PONDERADO]])/tb_investimentos[[#This Row],[VALOR TOTAL PONDERADO]],"")
B95: Entradas | C95: 46451 | D95: Fatec-SP | E95: =IF(tb_investimentos[[#This Row],[TIPO MOVIMENTAÇÃO]]="Aporte",_xlfn.XLOOKUP(tb_investimentos[[#This Row],[DESCRIÇÃO]],'INFO AÇÕES'!E:E,'INFO AÇÕES'!I:I),"BRL") -> BRL | F95: Bolsa Iniciação Científica | G95: 1 | H95: 700 | I95: Banco do Brasil | J95: =H95*G95 -> 700 | K95: NÃO | L95: =MONTH(tb_investimentos[[#This Row],[DATA]]) -> 3 | M95: =YEAR(tb_investimentos[[#This Row],[DATA]]) -> 2027 | N95: =DAY(tb_investimentos[[#This Row],[DATA]]) -> 5 | O95: =SUMIF($D$5:$D$10000, D95, $J$5:$J$10000) / SUMIF($D$5:$D$10000, D95, $G$5:$G$10000) -> 770 | P95: =tb_investimentos[[#This Row],[PREÇO MÉDIO PONDERADO]]*tb_investimentos[[#This Row],[QUANTIDADE]] -> 770 | Q95: =IFERROR(_xlfn.XLOOKUP(tb_investimentos[[#This Row],[DESCRIÇÃO]],tb_acoes[Símbolo do ticker],tb_acoes[Preço]),"") | R95: =IFERROR(tb_investimentos[[#This Row],[QUANTIDADE]]*tb_investimentos[[#This Row],[PREÇO MERCADO]],"") | S95: =IFERROR(tb_investimentos[[#This Row],[VALOR TOTAL MERCADO]]-tb_investimentos[[#This Row],[VALOR TOTAL PONDERADO]],"") | T95: =IFERROR(_xlfn.XLOOKUP(tb_investimentos[[#This Row],[DESCRIÇÃO]],'INFO AÇÕES'!E:E,'INFO AÇÕES'!H:H),"") | U95: =IFERROR((tb_investimentos[[#This Row],[VALOR TOTAL MERCADO]]-tb_investimentos[[#This Row],[VALOR TOTAL PONDERADO]])/tb_investimentos[[#This Row],[VALOR TOTAL PONDERADO]],"")
... B97: Saídas | C97: 46451 | D97: Banco do Brasil | E97: =IF(tb_investimentos[[#This Row],[TIPO MOVIMENTAÇÃO]]="Aporte",_xlfn.XLOOKUP(tb_investimentos[[#This Row],[DESCRIÇÃO]],'INFO AÇÕES'!E:E,'INFO AÇÕES'!I:I),"BRL") -> BRL | F97: Cartão de Crédito | G97: 1 | H97: 500 | I97: Banco do Brasil | J97: =H97*G97 -> 500 | K97: NÃO | L97: =MONTH(tb_investimentos[[#This Row],[DATA]]) -> 3 | M97: =YEAR(tb_investimentos[[#This Row],[DATA]]) -> 2027 | N97: =DAY(tb_investimentos[[#This Row],[DATA]]) -> 5 | O97: =SUMIF($D$5:$D$10000, D97, $J$5:$J$10000) / SUMIF($D$5:$D$10000, D97, $G$5:$G$10000) -> 515.93333 | P97: =tb_investimentos[[#This Row],[PREÇO MÉDIO PONDERADO]]*tb_investimentos[[#This Row],[QUANTIDADE]] -> 515.93333 | Q97: =IFERROR(_xlfn.XLOOKUP(tb_investimentos[[#This Row],[DESCRIÇÃO]],tb_acoes[Símbolo do ticker],tb_acoes[Preço]),"") | R97: =IFERROR(tb_investimentos[[#This Row],[QUANTIDADE]]*tb_investimentos[[#This Row],[PREÇO MERCADO]],"") | S97: =IFERROR(tb_investimentos[[#This Row],[VALOR TOTAL MERCADO]]-tb_investimentos[[#This Row],[VALOR TOTAL PONDERADO]],"") | T97: =IFERROR(_xlfn.XLOOKUP(tb_investimentos[[#This Row],[DESCRIÇÃO]],'INFO AÇÕES'!E:E,'INFO AÇÕES'!H:H),"") | U97: =IFERROR((tb_investimentos[[#This Row],[VALOR TOTAL MERCADO]]-tb_investimentos[[#This Row],[VALOR TOTAL PONDERADO]])/tb_investimentos[[#This Row],[VALOR TOTAL PONDERADO]],"")
B98: Aporte | C98: 46451 | E98: =IF(tb_investimentos[[#This Row],[TIPO MOVIMENTAÇÃO]]="Aporte",_xlfn.XLOOKUP(tb_investimentos[[#This Row],[DESCRIÇÃO]],'INFO AÇÕES'!E:E,'INFO AÇÕES'!I:I),"BRL") -> 0 | F98: Ações | G98: 1 | H98: 2500 | I98: Investimentos BB | J98: =H98*G98 -> 2500 | K98: NÃO | L98: =MONTH(tb_investimentos[[#This Row],[DATA]]) -> 3 | M98: =YEAR(tb_investimentos[[#This Row],[DATA]]) -> 2027 | N98: =DAY(tb_investimentos[[#This Row],[DATA]]) -> 5 | O98: =SUMIF($D$5:$D$10000, D98, $J$5:$J$10000) / SUMIF($D$5:$D$10000, D98, $G$5:$G$10000) -> #DIV/0! | P98: =tb_investimentos[[#This Row],[PREÇO MÉDIO PONDERADO]]*tb_investimentos[[#This Row],[QUANTIDADE]] -> #DIV/0! | Q98: =IFERROR(_xlfn.XLOOKUP(tb_investimentos[[#This Row],[DESCRIÇÃO]],tb_acoes[Símbolo do ticker],tb_acoes[Preço]),"") | R98: =IFERROR(tb_investimentos[[#This Row],[QUANTIDADE]]*tb_investimentos[[#This Row],[PREÇO MERCADO]],"") | S98: =IFERROR(tb_investimentos[[#This Row],[VALOR TOTAL MERCADO]]-tb_investimentos[[#This Row],[VALOR TOTAL PONDERADO]],"") | T98: =IFERROR(_xlfn.XLOOKUP(tb_investimentos[[#This Row],[DESCRIÇÃO]],'INFO AÇÕES'!E:E,'INFO AÇÕES'!H:H),"") | U98: =IFERROR((tb_investimentos[[#This Row],[VALOR TOTAL MERCADO]]-tb_investimentos[[#This Row],[VALOR TOTAL PONDERADO]])/tb_investimentos[[#This Row],[VALOR TOTAL PONDERADO]],"")
B99: Saídas | C99: 46454 | D99: Sabesp | E99: =IF(tb_investimentos[[#This Row],[TIPO MOVIMENTAÇÃO]]="Aporte",_xlfn.XLOOKUP(tb_investimentos[[#This Row],[DESCRIÇÃO]],'INFO AÇÕES'!E:E,'INFO AÇÕES'!I:I),"BRL") -> BRL | F99: Agua | G99: 1 | H99: 25 | I99: Banco do Brasil | J99: =H99*G99 -> 25 | K99: NÃO | L99: =MONTH(tb_investimentos[[#This Row],[DATA]]) -> 3 | M99: =YEAR(tb_investimentos[[#This Row],[DATA]]) -> 2027 | N99: =DAY(tb_investimentos[[#This Row],[DATA]]) -> 8 | O99: =SUMIF($D$5:$D$10000, D99, $J$5:$J$10000) / SUMIF($D$5:$D$10000, D99, $G$5:$G$10000) -> 25 | P99: =tb_investimentos[[#This Row],[PREÇO MÉDIO PONDERADO]]*tb_investimentos[[#This Row],[QUANTIDADE]] -> 25 | Q99: =IFERROR(_xlfn.XLOOKUP(tb_investimentos[[#This Row],[DESCRIÇÃO]],tb_acoes[Símbolo do ticker],tb_acoes[Preço]),"") | R99: =IFERROR(tb_investimentos[[#This Row],[QUANTIDADE]]*tb_investimentos[[#This Row],[PREÇO MERCADO]],"") | S99: =IFERROR(tb_investimentos[[#This Row],[VALOR TOTAL MERCADO]]-tb_investimentos[[#This Row],[VALOR TOTAL PONDERADO]],"") | T99: =IFERROR(_xlfn.XLOOKUP(tb_investimentos[[#This Row],[DESCRIÇÃO]],'INFO AÇÕES'!E:E,'INFO AÇÕES'!H:H),"") | U99: =IFERROR((tb_investimentos[[#This Row],[VALOR TOTAL MERCADO]]-tb_investimentos[[#This Row],[VALOR TOTAL PONDERADO]])/tb_investimentos[[#This Row],[VALOR TOTAL PONDERADO]],"")
B100: Saídas | C100: 46456 | D100: Cia Manah | E100: =IF(tb_investimentos[[#This Row],[TIPO MOVIMENTAÇÃO]]="Aporte",_xlfn.XLOOKUP(tb_investimentos[[#This Row],[DESCRIÇÃO]],'INFO AÇÕES'!E:E,'INFO AÇÕES'!I:I),"BRL") -> BRL | F100: Ballet e Ginastica | G100: 1 | H100: 95 | I100: Banco do Brasil | J100: =H100*G100 -> 95 | K100: NÃO | L100: =MONTH(tb_investimentos[[#This Row],[DATA]]) -> 3 | M100: =YEAR(tb_investimentos[[#This Row],[DATA]]) -> 2027 | N100: =DAY(tb_investimentos[[#This Row],[DATA]]) -> 10 | O100: =SUMIF($D$5:$D$10000, D100, $J$5:$J$10000) / SUMIF($D$5:$D$10000, D100, $G$5:$G$10000) -> 95 | P100: =tb_investimentos[[#This Row],[PREÇO MÉDIO PONDERADO]]*tb_investimentos[[#This Row],[QUANTIDADE]] -> 95 | Q100: =IFERROR(_xlfn.XLOOKUP(tb_investimentos[[#This Row],[DESCRIÇÃO]],tb_acoes[Símbolo do ticker],tb_acoes[Preço]),"") | R100: =IFERROR(tb_investimentos[[#This Row],[QUANTIDADE]]*tb_investimentos[[#This Row],[PREÇO MERCADO]],"") | S100: =IFERROR(tb_investimentos[[#This Row],[VALOR TOTAL MERCADO]]-tb_investimentos[[#This Row],[VALOR TOTAL PONDERADO]],"") | T100: =IFERROR(_xlfn.XLOOKUP(tb_investimentos[[#This Row],[DESCRIÇÃO]],'INFO AÇÕES'!E:E,'INFO AÇÕES'!H:H),"") | U100: =IFERROR((tb_investimentos[[#This Row],[VALOR TOTAL MERCADO]]-tb_investimentos[[#This Row],[VALOR TOTAL PONDERADO]])/tb_investimentos[[#This Row],[VALOR TOTAL PONDERADO]],"")
B101: Saídas | C101: 46458 | D101: Youtube | E101: =IF(tb_investimentos[[#This Row],[TIPO MOVIMENTAÇÃO]]="Aporte",_xlfn.XLOOKUP(tb_investimentos[[#This Row],[DESCRIÇÃO]],'INFO AÇÕES'!E:E,'INFO AÇÕES'!I:I),"BRL") -> BRL | F101: Youtube Music | G101: 1 | H101: 16.9 | I101: Banco do Brasil | J101: =H101*G101 -> 16.9 | K101: NÃO | L101: =MONTH(tb_investimentos[[#This Row],[DATA]]) -> 3 | M101: =YEAR(tb_investimentos[[#This Row],[DATA]]) -> 2027 | N101: =DAY(tb_investimentos[[#This Row],[DATA]]) -> 12 | O101: =SUMIF($D$5:$D$10000, D101, $J$5:$J$10000) / SUMIF($D$5:$D$10000, D101, $G$5:$G$10000) -> 137.33454 | P101: =tb_investimentos[[#This Row],[PREÇO MÉDIO PONDERADO]]*tb_investimentos[[#This Row],[QUANTIDADE]] -> 137.33454 | Q101: =IFERROR(_xlfn.XLOOKUP(tb_investimentos[[#This Row],[DESCRIÇÃO]],tb_acoes[Símbolo do ticker],tb_acoes[Preço]),"") | R101: =IFERROR(tb_investimentos[[#This Row],[QUANTIDADE]]*tb_investimentos[[#This Row],[PREÇO MERCADO]],"") | S101: =IFERROR(tb_investimentos[[#This Row],[VALOR TOTAL MERCADO]]-tb_investimentos[[#This Row],[VALOR TOTAL PONDERADO]],"") | T101: =IFERROR(_xlfn.XLOOKUP(tb_investimentos[[#This Row],[DESCRIÇÃO]],'INFO AÇÕES'!E:E,'INFO AÇÕES'!H:H),"") | U101: =IFERROR((tb_investimentos[[#This Row],[VALOR TOTAL MERCADO]]-tb_investimentos[[#This Row],[VALOR TOTAL PONDERADO]])/tb_investimentos[[#This Row],[VALOR TOTAL PONDERADO]],"")
B102: Saídas | C102: 46461 | D102: Vivo | E102: =IF(tb_investimentos[[#This Row],[TIPO MOVIMENTAÇÃO]]="Aporte",_xlfn.XLOOKUP(tb_investimentos[[#This Row],[DESCRIÇÃO]],'INFO AÇÕES'!E:E,'INFO AÇÕES'!I:I),"BRL") -> BRL | F102: Movel | G102: 1 | H102: 39.9 | I102: Banco do Brasil | J102: =H102*G102 -> 39.9 | K102: NÃO | L102: =MONTH(tb_investimentos[[#This Row],[DATA]]) -> 3 | M102: =YEAR(tb_investimentos[[#This Row],[DATA]]) -> 2027 | N102: =DAY(tb_investimentos[[#This Row],[DATA]]) -> 15 | O102: =SUMIF($D$5:$D$10000, D102, $J$5:$J$10000) / SUMIF($D$5:$D$10000, D102, $G$5:$G$10000) -> 59.9 | P102: =tb_investimentos[[#This Row],[PREÇO MÉDIO PONDERADO]]*tb_investimentos[[#This Row],[QUANTIDADE]] -> 59.9 | Q102: =IFERROR(_xlfn.XLOOKUP(tb_investimentos[[#This Row],[DESCRIÇÃO]],tb_acoes[Símbolo do ticker],tb_acoes[Preço]),"") | R102: =IFERROR(tb_investimentos[[#This Row],[QUANTIDADE]]*tb_investimentos[[#This Row],[PREÇO MERCADO]],"") | S102: =IFERROR(tb_investimentos[[#This Row],[VALOR TOTAL MERCADO]]-tb_investimentos[[#This Row],[VALOR TOTAL PONDERADO]],"") | T102: =IFERROR(_xlfn.XLOOKUP(tb_investimentos[[#This Row],[DESCRIÇÃO]],'INFO AÇÕES'!E:E,'INFO AÇÕES'!H:H),"") | U102: =IFERROR((tb_investimentos[[#This Row],[VALOR TOTAL MERCADO]]-tb_investimentos[[#This Row],[VALOR TOTAL PONDERADO]])/tb_investimentos[[#This Row],[VALOR TOTAL PONDERADO]],"")
B103: Saídas | C103: 46461 | D103: Vivo | E103: =IF(tb_investimentos[[#This Row],[TIPO MOVIMENTAÇÃO]]="Aporte",_xlfn.XLOOKUP(tb_investimentos[[#This Row],[DESCRIÇÃO]],'INFO AÇÕES'!E:E,'INFO AÇÕES'!I:I),"BRL") -> BRL | F103: Fibra | G103: 1 | H103: 79.9 | I103: Banco do Brasil | J103: =H103*G103 -> 79.9 | K103: NÃO | L103: =MONTH(tb_investimentos[[#This Row],[DATA]]) -> 3 | M103: =YEAR(tb_investimentos[[#This Row],[DATA]]) -> 2027 | N103: =DAY(tb_investimentos[[#This Row],[DATA]]) -> 15 | O103: =SUMIF($D$5:$D$10000, D103, $J$5:$J$10000) / SUMIF($D$5:$D$10000, D103, $G$5:$G$10000) -> 59.9 | P103: =tb_investimentos[[#This Row],[PREÇO MÉDIO PONDERADO]]*tb_investimentos[[#This Row],[QUANTIDADE]] -> 59.9 | Q103: =IFERROR(_xlfn.XLOOKUP(tb_investimentos[[#This Row],[DESCRIÇÃO]],tb_acoes[Símbolo do ticker],tb_acoes[Preço]),"") | R103: =IFERROR(tb_investimentos[[#This Row],[QUANTIDADE]]*tb_investimentos[[#This Row],[PREÇO MERCADO]],"") | S103: =IFERROR(tb_investimentos[[#This Row],[VALOR TOTAL MERCADO]]-tb_investimentos[[#This Row],[VALOR TOTAL PONDERADO]],"") | T103: =IFERROR(_xlfn.XLOOKUP(tb_investimentos[[#This Row],[DESCRIÇÃO]],'INFO AÇÕES'!E:E,'INFO AÇÕES'!H:H),"") | U103: =IFERROR((tb_investimentos[[#This Row],[VALOR TOTAL MERCADO]]-tb_investimentos[[#This Row],[VALOR TOTAL PONDERADO]])/tb_investimentos[[#This Row],[VALOR TOTAL PONDERADO]],"")
B104: Saídas | C104: 46461 | D104: Enel | E104: =IF(tb_investimentos[[#This Row],[TIPO MOVIMENTAÇÃO]]="Aporte",_xlfn.XLOOKUP(tb_investimentos[[#This Row],[DESCRIÇÃO]],'INFO AÇÕES'!E:E,'INFO AÇÕES'!I:I),"BRL") -> BRL | F104: Energia | G104: 1 | H104: 110 | I104: Banco do Brasil | J104: =H104*G104 -> 110 | K104: NÃO | L104: =MONTH(tb_investimentos[[#This Row],[DATA]]) -> 3 | M104: =YEAR(tb_investimentos[[#This Row],[DATA]]) -> 2027 | N104: =DAY(tb_investimentos[[#This Row],[DATA]]) -> 15 | O104: =SUMIF($D$5:$D$10000, D104, $J$5:$J$10000) / SUMIF($D$5:$D$10000, D104, $G$5:$G$10000) -> 110 | P104: =tb_investimentos[[#This Row],[PREÇO MÉDIO PONDERADO]]*tb_investimentos[[#This Row],[QUANTIDADE]] -> 110 | Q104: =IFERROR(_xlfn.XLOOKUP(tb_investimentos[[#This Row],[DESCRIÇÃO]],tb_acoes[Símbolo do ticker],tb_acoes[Preço]),"") | R104: =IFERROR(tb_investimentos[[#This Row],[QUANTIDADE]]*tb_investimentos[[#This Row],[PREÇO MERCADO]],"") | S104: =IFERROR(tb_investimentos[[#This Row],[VALOR TOTAL MERCADO]]-tb_investimentos[[#This Row],[VALOR TOTAL PONDERADO]],"") | T104: =IFERROR(_xlfn.XLOOKUP(tb_investimentos[[#This Row],[DESCRIÇÃO]],'INFO AÇÕES'!E:E,'INFO AÇÕES'!H:H),"") | U104: =IFERROR((tb_investimentos[[#This Row],[VALOR TOTAL MERCADO]]-tb_investimentos[[#This Row],[VALOR TOTAL PONDERADO]])/tb_investimentos[[#This Row],[VALOR TOTAL PONDERADO]],"")
B105: Saídas | C105: 46461 | D105: Caixa Econômica Federal | E105: =IF(tb_investimentos[[#This Row],[TIPO MOVIMENTAÇÃO]]="Aporte",_xlfn.XLOOKUP(tb_investimentos[[#This Row],[DESCRIÇÃO]],'INFO AÇÕES'!E:E,'INFO AÇÕES'!I:I),"BRL") -> BRL | F105: Evolução de obras | G105: 1 | H105: 1056.5151 | I105: Banco do Brasil | J105: =H105*G105 -> 1056.5151 | K105: NÃO | L105: =MONTH(tb_investimentos[[#This Row],[DATA]]) -> 3 | M105: =YEAR(tb_investimentos[[#This Row],[DATA]]) -> 2027 | N105: =DAY(tb_investimentos[[#This Row],[DATA]]) -> 15 | O105: =SUMIF($D$5:$D$10000, D105, $J$5:$J$10000) / SUMIF($D$5:$D$10000, D105, $G$5:$G$10000) -> 1629.993 | P105: =tb_investimentos[[#This Row],[PREÇO MÉDIO PONDERADO]]*tb_investimentos[[#This Row],[QUANTIDADE]] -> 1629.993 | Q105: =IFERROR(_xlfn.XLOOKUP(tb_investimentos[[#This Row],[DESCRIÇÃO]],tb_acoes[Símbolo do ticker],tb_acoes[Preço]),"") | R105: =IFERROR(tb_investimentos[[#This Row],[QUANTIDADE]]*tb_investimentos[[#This Row],[PREÇO MERCADO]],"") | S105: =IFERROR(tb_investimentos[[#This Row],[VALOR TOTAL MERCADO]]-tb_investimentos[[#This Row],[VALOR TOTAL PONDERADO]],"") | T105: =IFERROR(_xlfn.XLOOKUP(tb_investimentos[[#This Row],[DESCRIÇÃO]],'INFO AÇÕES'!E:E,'INFO AÇÕES'!H:H),"") | U105: =IFERROR((tb_investimentos[[#This Row],[VALOR TOTAL MERCADO]]-tb_investimentos[[#This Row],[VALOR TOTAL PONDERADO]])/tb_investimentos[[#This Row],[VALOR TOTAL PONDERADO]],"")
B106: Saídas | C106: 46466 | D106: DAS/DARF | E106: =IF(tb_investimentos[[#This Row],[TIPO MOVIMENTAÇÃO]]="Aporte",_xlfn.XLOOKUP(tb_investimentos[[#This Row],[DESCRIÇÃO]],'INFO AÇÕES'!E:E,'INFO AÇÕES'!I:I),"BRL") -> BRL | F106: Impostos | G106: 1 | H106: 95 | I106: Banco do Brasil | J106: =H106*G106 -> 95 | K106: NÃO | L106: =MONTH(tb_investimentos[[#This Row],[DATA]]) -> 3 | M106: =YEAR(tb_investimentos[[#This Row],[DATA]]) -> 2027 | N106: =DAY(tb_investimentos[[#This Row],[DATA]]) -> 20 | O106: =SUMIF($D$5:$D$10000, D106, $J$5:$J$10000) / SUMIF($D$5:$D$10000, D106, $G$5:$G$10000) -> 93.857143 | P106: =tb_investimentos[[#This Row],[PREÇO MÉDIO PONDERADO]]*tb_investimentos[[#This Row],[QUANTIDADE]] -> 93.857143 | Q106: =IFERROR(_xlfn.XLOOKUP(tb_investimentos[[#This Row],[DESCRIÇÃO]],tb_acoes[Símbolo do ticker],tb_acoes[Preço]),"") | R106: =IFERROR(tb_investimentos[[#This Row],[QUANTIDADE]]*tb_investimentos[[#This Row],[PREÇO MERCADO]],"") | S106: =IFERROR(tb_investimentos[[#This Row],[VALOR TOTAL MERCADO]]-tb_investimentos[[#This Row],[VALOR TOTAL PONDERADO]],"") | T106: =IFERROR(_xlfn.XLOOKUP(tb_investimentos[[#This Row],[DESCRIÇÃO]],'INFO AÇÕES'!E:E,'INFO AÇÕES'!H:H),"") | U106: =IFERROR((tb_investimentos[[#This Row],[VALOR TOTAL MERCADO]]-tb_investimentos[[#This Row],[VALOR TOTAL PONDERADO]])/tb_investimentos[[#This Row],[VALOR TOTAL PONDERADO]],"")
B107: Saídas | C107: 46470 | D107: Aluguel | E107: =IF(tb_investimentos[[#This Row],[TIPO MOVIMENTAÇÃO]]="Aporte",_xlfn.XLOOKUP(tb_investimentos[[#This Row],[DESCRIÇÃO]],'INFO AÇÕES'!E:E,'INFO AÇÕES'!I:I),"BRL") -> BRL | F107: Moradia | G107: 1 | H107: 650 | I107: Banco do Brasil | J107: =H107*G107 -> 650 | K107: NÃO | L107: =MONTH(tb_investimentos[[#This Row],[DATA]]) -> 3 | M107: =YEAR(tb_investimentos[[#This Row],[DATA]]) -> 2027 | N107: =DAY(tb_investimentos[[#This Row],[DATA]]) -> 24 | O107: =SUMIF($D$5:$D$10000, D107, $J$5:$J$10000) / SUMIF($D$5:$D$10000, D107, $G$5:$G$10000) -> 650 | P107: =tb_investimentos[[#This Row],[PREÇO MÉDIO PONDERADO]]*tb_investimentos[[#This Row],[QUANTIDADE]] -> 650 | Q107: =IFERROR(_xlfn.XLOOKUP(tb_investimentos[[#This Row],[DESCRIÇÃO]],tb_acoes[Símbolo do ticker],tb_acoes[Preço]),"") | R107: =IFERROR(tb_investimentos[[#This Row],[QUANTIDADE]]*tb_investimentos[[#This Row],[PREÇO MERCADO]],"") | S107: =IFERROR(tb_investimentos[[#This Row],[VALOR TOTAL MERCADO]]-tb_investimentos[[#This Row],[VALOR TOTAL PONDERADO]],"") | T107: =IFERROR(_xlfn.XLOOKUP(tb_investimentos[[#This Row],[DESCRIÇÃO]],'INFO AÇÕES'!E:E,'INFO AÇÕES'!H:H),"") | U107: =IFERROR((tb_investimentos[[#This Row],[VALOR TOTAL MERCADO]]-tb_investimentos[[#This Row],[VALOR TOTAL PONDERADO]])/tb_investimentos[[#This Row],[VALOR TOTAL PONDERADO]],"")
B108: Saídas | C108: 46474 | D108: Tia Mônica | E108: =IF(tb_investimentos[[#This Row],[TIPO MOVIMENTAÇÃO]]="Aporte",_xlfn.XLOOKUP(tb_investimentos[[#This Row],[DESCRIÇÃO]],'INFO AÇÕES'!E:E,'INFO AÇÕES'!I:I),"BRL") -> BRL | F108: Cuidadora | G108: 1 | H108: 650 | I108: Banco do Brasil | J108: =H108*G108 -> 650 | K108: NÃO | L108: =MONTH(tb_investimentos[[#This Row],[DATA]]) -> 3 | M108: =YEAR(tb_investimentos[[#This Row],[DATA]]) -> 2027 | N108: =DAY(tb_investimentos[[#This Row],[DATA]]) -> 28 | O108: =SUMIF($D$5:$D$10000, D108, $J$5:$J$10000) / SUMIF($D$5:$D$10000, D108, $G$5:$G$10000) -> 650 | P108: =tb_investimentos[[#This Row],[PREÇO MÉDIO PONDERADO]]*tb_investimentos[[#This Row],[QUANTIDADE]] -> 650 | Q108: =IFERROR(_xlfn.XLOOKUP(tb_investimentos[[#This Row],[DESCRIÇÃO]],tb_acoes[Símbolo do ticker],tb_acoes[Preço]),"") | R108: =IFERROR(tb_investimentos[[#This Row],[QUANTIDADE]]*tb_investimentos[[#This Row],[PREÇO MERCADO]],"") | S108: =IFERROR(tb_investimentos[[#This Row],[VALOR TOTAL MERCADO]]-tb_investimentos[[#This Row],[VALOR TOTAL PONDERADO]],"") | T108: =IFERROR(_xlfn.XLOOKUP(tb_investimentos[[#This Row],[DESCRIÇÃO]],'INFO AÇÕES'!E:E,'INFO AÇÕES'!H:H),"") | U108: =IFERROR((tb_investimentos[[#This Row],[VALOR TOTAL MERCADO]]-tb_investimentos[[#This Row],[VALOR TOTAL PONDERADO]])/tb_investimentos[[#This Row],[VALOR TOTAL PONDERADO]],"")
B109: Entradas | C109: 46482 | D109: LoyaltyCom | E109: =IF(tb_investimentos[[#This Row],[TIPO MOVIMENTAÇÃO]]="Aporte",_xlfn.XLOOKUP(tb_investimentos[[#This Row],[DESCRIÇÃO]],'INFO AÇÕES'!E:E,'INFO AÇÕES'!I:I),"BRL") -> BRL | F109: Salário | G109: 1 | H109: 8000 | I109: Banco do Brasil | J109: =H109*G109 -> 8000 | K109: NÃO | L109: =MONTH(tb_investimentos[[#This Row],[DATA]]) -> 4 | M109: =YEAR(tb_investimentos[[#This Row],[DATA]]) -> 2027 | N109: =DAY(tb_investimentos[[#This Row],[DATA]]) -> 5 | O109: =SUMIF($D$5:$D$10000, D109, $J$5:$J$10000) / SUMIF($D$5:$D$10000, D109, $G$5:$G$10000) -> 7801.7949 | P109: =tb_investimentos[[#This Row],[PREÇO MÉDIO PONDERADO]]*tb_investimentos[[#This Row],[QUANTIDADE]] -> 7801.7949 | Q109: =IFERROR(_xlfn.XLOOKUP(tb_investimentos[[#This Row],[DESCRIÇÃO]],tb_acoes[Símbolo do ticker],tb_acoes[Preço]),"") | R109: =IFERROR(tb_investimentos[[#This Row],[QUANTIDADE]]*tb_investimentos[[#This Row],[PREÇO MERCADO]],"") | S109: =IFERROR(tb_investimentos[[#This Row],[VALOR TOTAL MERCADO]]-tb_investimentos[[#This Row],[VALOR TOTAL PONDERADO]],"") | T109: =IFERROR(_xlfn.XLOOKUP(tb_investimentos[[#This Row],[DESCRIÇÃO]],'INFO AÇÕES'!E:E,'INFO AÇÕES'!H:H),"") | U109: =IFERROR((tb_investimentos[[#This Row],[VALOR TOTAL MERCADO]]-tb_investimentos[[#This Row],[VALOR TOTAL PONDERADO]])/tb_investimentos[[#This Row],[VALOR TOTAL PONDERADO]],"")
B110: Entradas | C110: 46482 | D110: Fatec-SP | E110: =IF(tb_investimentos[[#This Row],[TIPO MOVIMENTAÇÃO]]="Aporte",_xlfn.XLOOKUP(tb_investimentos[[#This Row],[DESCRIÇÃO]],'INFO AÇÕES'!E:E,'INFO AÇÕES'!I:I),"BRL") -> BRL | F110: Bolsa Iniciação Científica | G110: 1 | H110: 700 | I110: Banco do Brasil | J110: =H110*G110 -> 700 | K110: NÃO | L110: =MONTH(tb_investimentos[[#This Row],[DATA]]) -> 4 | M110: =YEAR(tb_investimentos[[#This Row],[DATA]]) -> 2027 | N110: =DAY(tb_investimentos[[#This Row],[DATA]]) -> 5 | O110: =SUMIF($D$5:$D$10000, D110, $J$5:$J$10000) / SUMIF($D$5:$D$10000, D110, $G$5:$G$10000) -> 770 | P110: =tb_investimentos[[#This Row],[PREÇO MÉDIO PONDERADO]]*tb_investimentos[[#This Row],[QUANTIDADE]] -> 770 | Q110: =IFERROR(_xlfn.XLOOKUP(tb_investimentos[[#This Row],[DESCRIÇÃO]],tb_acoes[Símbolo do ticker],tb_acoes[Preço]),"") | R110: =IFERROR(tb_investimentos[[#This Row],[QUANTIDADE]]*tb_investimentos[[#This Row],[PREÇO MERCADO]],"") | S110: =IFERROR(tb_investimentos[[#This Row],[VALOR TOTAL MERCADO]]-tb_investimentos[[#This Row],[VALOR TOTAL PONDERADO]],"") | T110: =IFERROR(_xlfn.XLOOKUP(tb_investimentos[[#This Row],[DESCRIÇÃO]],'INFO AÇÕES'!E:E,'INFO AÇÕES'!H:H),"") | U110: =IFERROR((tb_investimentos[[#This Row],[VALOR TOTAL MERCADO]]-tb_investimentos[[#This Row],[VALOR TOTAL PONDERADO]])/tb_investimentos[[#This Row],[VALOR TOTAL PONDERADO]],"")
... B112: Saídas | C112: 46482 | D112: Banco do Brasil | E112: =IF(tb_investimentos[[#This Row],[TIPO MOVIMENTAÇÃO]]="Aporte",_xlfn.XLOOKUP(tb_investimentos[[#This Row],[DESCRIÇÃO]],'INFO AÇÕES'!E:E,'INFO AÇÕES'!I:I),"BRL") -> BRL | F112: Cartão de Crédito | G112: 1 | H112: 500 | I112: Banco do Brasil | J112: =H112*G112 -> 500 | K112: NÃO | L112: =MONTH(tb_investimentos[[#This Row],[DATA]]) -> 4 | M112: =YEAR(tb_investimentos[[#This Row],[DATA]]) -> 2027 | N112: =DAY(tb_investimentos[[#This Row],[DATA]]) -> 5 | O112: =SUMIF($D$5:$D$10000, D112, $J$5:$J$10000) / SUMIF($D$5:$D$10000, D112, $G$5:$G$10000) -> 515.93333 | P112: =tb_investimentos[[#This Row],[PREÇO MÉDIO PONDERADO]]*tb_investimentos[[#This Row],[QUANTIDADE]] -> 515.93333 | Q112: =IFERROR(_xlfn.XLOOKUP(tb_investimentos[[#This Row],[DESCRIÇÃO]],tb_acoes[Símbolo do ticker],tb_acoes[Preço]),"") | R112: =IFERROR(tb_investimentos[[#This Row],[QUANTIDADE]]*tb_investimentos[[#This Row],[PREÇO MERCADO]],"") | S112: =IFERROR(tb_investimentos[[#This Row],[VALOR TOTAL MERCADO]]-tb_investimentos[[#This Row],[VALOR TOTAL PONDERADO]],"") | T112: =IFERROR(_xlfn.XLOOKUP(tb_investimentos[[#This Row],[DESCRIÇÃO]],'INFO AÇÕES'!E:E,'INFO AÇÕES'!H:H),"") | U112: =IFERROR((tb_investimentos[[#This Row],[VALOR TOTAL MERCADO]]-tb_investimentos[[#This Row],[VALOR TOTAL PONDERADO]])/tb_investimentos[[#This Row],[VALOR TOTAL PONDERADO]],"")
B113: Aporte | C113: 46482 | E113: =IF(tb_investimentos[[#This Row],[TIPO MOVIMENTAÇÃO]]="Aporte",_xlfn.XLOOKUP(tb_investimentos[[#This Row],[DESCRIÇÃO]],'INFO AÇÕES'!E:E,'INFO AÇÕES'!I:I),"BRL") -> 0 | F113: Ações | G113: 1 | H113: 2500 | I113: Investimentos BB | J113: =H113*G113 -> 2500 | K113: NÃO | L113: =MONTH(tb_investimentos[[#This Row],[DATA]]) -> 4 | M113: =YEAR(tb_investimentos[[#This Row],[DATA]]) -> 2027 | N113: =DAY(tb_investimentos[[#This Row],[DATA]]) -> 5 | O113: =SUMIF($D$5:$D$10000, D113, $J$5:$J$10000) / SUMIF($D$5:$D$10000, D113, $G$5:$G$10000) -> #DIV/0! | P113: =tb_investimentos[[#This Row],[PREÇO MÉDIO PONDERADO]]*tb_investimentos[[#This Row],[QUANTIDADE]] -> #DIV/0! | Q113: =IFERROR(_xlfn.XLOOKUP(tb_investimentos[[#This Row],[DESCRIÇÃO]],tb_acoes[Símbolo do ticker],tb_acoes[Preço]),"") | R113: =IFERROR(tb_investimentos[[#This Row],[QUANTIDADE]]*tb_investimentos[[#This Row],[PREÇO MERCADO]],"") | S113: =IFERROR(tb_investimentos[[#This Row],[VALOR TOTAL MERCADO]]-tb_investimentos[[#This Row],[VALOR TOTAL PONDERADO]],"") | T113: =IFERROR(_xlfn.XLOOKUP(tb_investimentos[[#This Row],[DESCRIÇÃO]],'INFO AÇÕES'!E:E,'INFO AÇÕES'!H:H),"") | U113: =IFERROR((tb_investimentos[[#This Row],[VALOR TOTAL MERCADO]]-tb_investimentos[[#This Row],[VALOR TOTAL PONDERADO]])/tb_investimentos[[#This Row],[VALOR TOTAL PONDERADO]],"")
B114: Saídas | C114: 46485 | D114: Sabesp | E114: =IF(tb_investimentos[[#This Row],[TIPO MOVIMENTAÇÃO]]="Aporte",_xlfn.XLOOKUP(tb_investimentos[[#This Row],[DESCRIÇÃO]],'INFO AÇÕES'!E:E,'INFO AÇÕES'!I:I),"BRL") -> BRL | F114: Agua | G114: 1 | H114: 25 | I114: Banco do Brasil | J114: =H114*G114 -> 25 | K114: NÃO | L114: =MONTH(tb_investimentos[[#This Row],[DATA]]) -> 4 | M114: =YEAR(tb_investimentos[[#This Row],[DATA]]) -> 2027 | N114: =DAY(tb_investimentos[[#This Row],[DATA]]) -> 8 | O114: =SUMIF($D$5:$D$10000, D114, $J$5:$J$10000) / SUMIF($D$5:$D$10000, D114, $G$5:$G$10000) -> 25 | P114: =tb_investimentos[[#This Row],[PREÇO MÉDIO PONDERADO]]*tb_investimentos[[#This Row],[QUANTIDADE]] -> 25 | Q114: =IFERROR(_xlfn.XLOOKUP(tb_investimentos[[#This Row],[DESCRIÇÃO]],tb_acoes[Símbolo do ticker],tb_acoes[Preço]),"") | R114: =IFERROR(tb_investimentos[[#This Row],[QUANTIDADE]]*tb_investimentos[[#This Row],[PREÇO MERCADO]],"") | S114: =IFERROR(tb_investimentos[[#This Row],[VALOR TOTAL MERCADO]]-tb_investimentos[[#This Row],[VALOR TOTAL PONDERADO]],"") | T114: =IFERROR(_xlfn.XLOOKUP(tb_investimentos[[#This Row],[DESCRIÇÃO]],'INFO AÇÕES'!E:E,'INFO AÇÕES'!H:H),"") | U114: =IFERROR((tb_investimentos[[#This Row],[VALOR TOTAL MERCADO]]-tb_investimentos[[#This Row],[VALOR TOTAL PONDERADO]])/tb_investimentos[[#This Row],[VALOR TOTAL PONDERADO]],"")
B115: Saídas | C115: 46487 | D115: Cia Manah | E115: =IF(tb_investimentos[[#This Row],[TIPO MOVIMENTAÇÃO]]="Aporte",_xlfn.XLOOKUP(tb_investimentos[[#This Row],[DESCRIÇÃO]],'INFO AÇÕES'!E:E,'INFO AÇÕES'!I:I),"BRL") -> BRL | F115: Ballet e Ginastica | G115: 1 | H115: 95 | I115: Banco do Brasil | J115: =H115*G115 -> 95 | K115: NÃO | L115: =MONTH(tb_investimentos[[#This Row],[DATA]]) -> 4 | M115: =YEAR(tb_investimentos[[#This Row],[DATA]]) -> 2027 | N115: =DAY(tb_investimentos[[#This Row],[DATA]]) -> 10 | O115: =SUMIF($D$5:$D$10000, D115, $J$5:$J$10000) / SUMIF($D$5:$D$10000, D115, $G$5:$G$10000) -> 95 | P115: =tb_investimentos[[#This Row],[PREÇO MÉDIO PONDERADO]]*tb_investimentos[[#This Row],[QUANTIDADE]] -> 95 | Q115: =IFERROR(_xlfn.XLOOKUP(tb_investimentos[[#This Row],[DESCRIÇÃO]],tb_acoes[Símbolo do ticker],tb_acoes[Preço]),"") | R115: =IFERROR(tb_investimentos[[#This Row],[QUANTIDADE]]*tb_investimentos[[#This Row],[PREÇO MERCADO]],"") | S115: =IFERROR(tb_investimentos[[#This Row],[VALOR TOTAL MERCADO]]-tb_investimentos[[#This Row],[VALOR TOTAL PONDERADO]],"") | T115: =IFERROR(_xlfn.XLOOKUP(tb_investimentos[[#This Row],[DESCRIÇÃO]],'INFO AÇÕES'!E:E,'INFO AÇÕES'!H:H),"") | U115: =IFERROR((tb_investimentos[[#This Row],[VALOR TOTAL MERCADO]]-tb_investimentos[[#This Row],[VALOR TOTAL PONDERADO]])/tb_investimentos[[#This Row],[VALOR TOTAL PONDERADO]],"")
B116: Saídas | C116: 46489 | D116: Youtube | E116: =IF(tb_investimentos[[#This Row],[TIPO MOVIMENTAÇÃO]]="Aporte",_xlfn.XLOOKUP(tb_investimentos[[#This Row],[DESCRIÇÃO]],'INFO AÇÕES'!E:E,'INFO AÇÕES'!I:I),"BRL") -> BRL | F116: Youtube Music | G116: 1 | H116: 16.9 | I116: Banco do Brasil | J116: =H116*G116 -> 16.9 | K116: NÃO | L116: =MONTH(tb_investimentos[[#This Row],[DATA]]) -> 4 | M116: =YEAR(tb_investimentos[[#This Row],[DATA]]) -> 2027 | N116: =DAY(tb_investimentos[[#This Row],[DATA]]) -> 12 | O116: =SUMIF($D$5:$D$10000, D116, $J$5:$J$10000) / SUMIF($D$5:$D$10000, D116, $G$5:$G$10000) -> 137.33454 | P116: =tb_investimentos[[#This Row],[PREÇO MÉDIO PONDERADO]]*tb_investimentos[[#This Row],[QUANTIDADE]] -> 137.33454 | Q116: =IFERROR(_xlfn.XLOOKUP(tb_investimentos[[#This Row],[DESCRIÇÃO]],tb_acoes[Símbolo do ticker],tb_acoes[Preço]),"") | R116: =IFERROR(tb_investimentos[[#This Row],[QUANTIDADE]]*tb_investimentos[[#This Row],[PREÇO MERCADO]],"") | S116: =IFERROR(tb_investimentos[[#This Row],[VALOR TOTAL MERCADO]]-tb_investimentos[[#This Row],[VALOR TOTAL PONDERADO]],"") | T116: =IFERROR(_xlfn.XLOOKUP(tb_investimentos[[#This Row],[DESCRIÇÃO]],'INFO AÇÕES'!E:E,'INFO AÇÕES'!H:H),"") | U116: =IFERROR((tb_investimentos[[#This Row],[VALOR TOTAL MERCADO]]-tb_investimentos[[#This Row],[VALOR TOTAL PONDERADO]])/tb_investimentos[[#This Row],[VALOR TOTAL PONDERADO]],"")
B117: Saídas | C117: 46492 | D117: Vivo | E117: =IF(tb_investimentos[[#This Row],[TIPO MOVIMENTAÇÃO]]="Aporte",_xlfn.XLOOKUP(tb_investimentos[[#This Row],[DESCRIÇÃO]],'INFO AÇÕES'!E:E,'INFO AÇÕES'!I:I),"BRL") -> BRL | F117: Movel | G117: 1 | H117: 39.9 | I117: Banco do Brasil | J117: =H117*G117 -> 39.9 | K117: NÃO | L117: =MONTH(tb_investimentos[[#This Row],[DATA]]) -> 4 | M117: =YEAR(tb_investimentos[[#This Row],[DATA]]) -> 2027 | N117: =DAY(tb_investimentos[[#This Row],[DATA]]) -> 15 | O117: =SUMIF($D$5:$D$10000, D117, $J$5:$J$10000) / SUMIF($D$5:$D$10000, D117, $G$5:$G$10000) -> 59.9 | P117: =tb_investimentos[[#This Row],[PREÇO MÉDIO PONDERADO]]*tb_investimentos[[#This Row],[QUANTIDADE]] -> 59.9 | Q117: =IFERROR(_xlfn.XLOOKUP(tb_investimentos[[#This Row],[DESCRIÇÃO]],tb_acoes[Símbolo do ticker],tb_acoes[Preço]),"") | R117: =IFERROR(tb_investimentos[[#This Row],[QUANTIDADE]]*tb_investimentos[[#This Row],[PREÇO MERCADO]],"") | S117: =IFERROR(tb_investimentos[[#This Row],[VALOR TOTAL MERCADO]]-tb_investimentos[[#This Row],[VALOR TOTAL PONDERADO]],"") | T117: =IFERROR(_xlfn.XLOOKUP(tb_investimentos[[#This Row],[DESCRIÇÃO]],'INFO AÇÕES'!E:E,'INFO AÇÕES'!H:H),"") | U117: =IFERROR((tb_investimentos[[#This Row],[VALOR TOTAL MERCADO]]-tb_investimentos[[#This Row],[VALOR TOTAL PONDERADO]])/tb_investimentos[[#This Row],[VALOR TOTAL PONDERADO]],"")
B118: Saídas | C118: 46492 | D118: Vivo | E118: =IF(tb_investimentos[[#This Row],[TIPO MOVIMENTAÇÃO]]="Aporte",_xlfn.XLOOKUP(tb_investimentos[[#This Row],[DESCRIÇÃO]],'INFO AÇÕES'!E:E,'INFO AÇÕES'!I:I),"BRL") -> BRL | F118: Fibra | G118: 1 | H118: 79.9 | I118: Banco do Brasil | J118: =H118*G118 -> 79.9 | K118: NÃO | L118: =MONTH(tb_investimentos[[#This Row],[DATA]]) -> 4 | M118: =YEAR(tb_investimentos[[#This Row],[DATA]]) -> 2027 | N118: =DAY(tb_investimentos[[#This Row],[DATA]]) -> 15 | O118: =SUMIF($D$5:$D$10000, D118, $J$5:$J$10000) / SUMIF($D$5:$D$10000, D118, $G$5:$G$10000) -> 59.9 | P118: =tb_investimentos[[#This Row],[PREÇO MÉDIO PONDERADO]]*tb_investimentos[[#This Row],[QUANTIDADE]] -> 59.9 | Q118: =IFERROR(_xlfn.XLOOKUP(tb_investimentos[[#This Row],[DESCRIÇÃO]],tb_acoes[Símbolo do ticker],tb_acoes[Preço]),"") | R118: =IFERROR(tb_investimentos[[#This Row],[QUANTIDADE]]*tb_investimentos[[#This Row],[PREÇO MERCADO]],"") | S118: =IFERROR(tb_investimentos[[#This Row],[VALOR TOTAL MERCADO]]-tb_investimentos[[#This Row],[VALOR TOTAL PONDERADO]],"") | T118: =IFERROR(_xlfn.XLOOKUP(tb_investimentos[[#This Row],[DESCRIÇÃO]],'INFO AÇÕES'!E:E,'INFO AÇÕES'!H:H),"") | U118: =IFERROR((tb_investimentos[[#This Row],[VALOR TOTAL MERCADO]]-tb_investimentos[[#This Row],[VALOR TOTAL PONDERADO]])/tb_investimentos[[#This Row],[VALOR TOTAL PONDERADO]],"")
B119: Saídas | C119: 46492 | D119: Enel | E119: =IF(tb_investimentos[[#This Row],[TIPO MOVIMENTAÇÃO]]="Aporte",_xlfn.XLOOKUP(tb_investimentos[[#This Row],[DESCRIÇÃO]],'INFO AÇÕES'!E:E,'INFO AÇÕES'!I:I),"BRL") -> BRL | F119: Energia | G119: 1 | H119: 110 | I119: Banco do Brasil | J119: =H119*G119 -> 110 | K119: NÃO | L119: =MONTH(tb_investimentos[[#This Row],[DATA]]) -> 4 | M119: =YEAR(tb_investimentos[[#This Row],[DATA]]) -> 2027 | N119: =DAY(tb_investimentos[[#This Row],[DATA]]) -> 15 | O119: =SUMIF($D$5:$D$10000, D119, $J$5:$J$10000) / SUMIF($D$5:$D$10000, D119, $G$5:$G$10000) -> 110 | P119: =tb_investimentos[[#This Row],[PREÇO MÉDIO PONDERADO]]*tb_investimentos[[#This Row],[QUANTIDADE]] -> 110 | Q119: =IFERROR(_xlfn.XLOOKUP(tb_investimentos[[#This Row],[DESCRIÇÃO]],tb_acoes[Símbolo do ticker],tb_acoes[Preço]),"") | R119: =IFERROR(tb_investimentos[[#This Row],[QUANTIDADE]]*tb_investimentos[[#This Row],[PREÇO MERCADO]],"") | S119: =IFERROR(tb_investimentos[[#This Row],[VALOR TOTAL MERCADO]]-tb_investimentos[[#This Row],[VALOR TOTAL PONDERADO]],"") | T119: =IFERROR(_xlfn.XLOOKUP(tb_investimentos[[#This Row],[DESCRIÇÃO]],'INFO AÇÕES'!E:E,'INFO AÇÕES'!H:H),"") | U119: =IFERROR((tb_investimentos[[#This Row],[VALOR TOTAL MERCADO]]-tb_investimentos[[#This Row],[VALOR TOTAL PONDERADO]])/tb_investimentos[[#This Row],[VALOR TOTAL PONDERADO]],"")
B120: Saídas | C120: 46492 | D120: Caixa Econômica Federal | E120: =IF(tb_investimentos[[#This Row],[TIPO MOVIMENTAÇÃO]]="Aporte",_xlfn.XLOOKUP(tb_investimentos[[#This Row],[DESCRIÇÃO]],'INFO AÇÕES'!E:E,'INFO AÇÕES'!I:I),"BRL") -> BRL | F120: Evolução de obras | G120: 1 | H120: 1119.5248 | I120: Banco do Brasil | J120: =H120*G120 -> 1119.5248 | K120: NÃO | L120: =MONTH(tb_investimentos[[#This Row],[DATA]]) -> 4 | M120: =YEAR(tb_investimentos[[#This Row],[DATA]]) -> 2027 | N120: =DAY(tb_investimentos[[#This Row],[DATA]]) -> 15 | O120: =SUMIF($D$5:$D$10000, D120, $J$5:$J$10000) / SUMIF($D$5:$D$10000, D120, $G$5:$G$10000) -> 1629.993 | P120: =tb_investimentos[[#This Row],[PREÇO MÉDIO PONDERADO]]*tb_investimentos[[#This Row],[QUANTIDADE]] -> 1629.993 | Q120: =IFERROR(_xlfn.XLOOKUP(tb_investimentos[[#This Row],[DESCRIÇÃO]],tb_acoes[Símbolo do ticker],tb_acoes[Preço]),"") | R120: =IFERROR(tb_investimentos[[#This Row],[QUANTIDADE]]*tb_investimentos[[#This Row],[PREÇO MERCADO]],"") | S120: =IFERROR(tb_investimentos[[#This Row],[VALOR TOTAL MERCADO]]-tb_investimentos[[#This Row],[VALOR TOTAL PONDERADO]],"") | T120: =IFERROR(_xlfn.XLOOKUP(tb_investimentos[[#This Row],[DESCRIÇÃO]],'INFO AÇÕES'!E:E,'INFO AÇÕES'!H:H),"") | U120: =IFERROR((tb_investimentos[[#This Row],[VALOR TOTAL MERCADO]]-tb_investimentos[[#This Row],[VALOR TOTAL PONDERADO]])/tb_investimentos[[#This Row],[VALOR TOTAL PONDERADO]],"")
B121: Saídas | C121: 46497 | D121: DAS/DARF | E121: =IF(tb_investimentos[[#This Row],[TIPO MOVIMENTAÇÃO]]="Aporte",_xlfn.XLOOKUP(tb_investimentos[[#This Row],[DESCRIÇÃO]],'INFO AÇÕES'!E:E,'INFO AÇÕES'!I:I),"BRL") -> BRL | F121: Impostos | G121: 1 | H121: 95 | I121: Banco do Brasil | J121: =H121*G121 -> 95 | K121: NÃO | L121: =MONTH(tb_investimentos[[#This Row],[DATA]]) -> 4 | M121: =YEAR(tb_investimentos[[#This Row],[DATA]]) -> 2027 | N121: =DAY(tb_investimentos[[#This Row],[DATA]]) -> 20 | O121: =SUMIF($D$5:$D$10000, D121, $J$5:$J$10000) / SUMIF($D$5:$D$10000, D121, $G$5:$G$10000) -> 93.857143 | P121: =tb_investimentos[[#This Row],[PREÇO MÉDIO PONDERADO]]*tb_investimentos[[#This Row],[QUANTIDADE]] -> 93.857143 | Q121: =IFERROR(_xlfn.XLOOKUP(tb_investimentos[[#This Row],[DESCRIÇÃO]],tb_acoes[Símbolo do ticker],tb_acoes[Preço]),"") | R121: =IFERROR(tb_investimentos[[#This Row],[QUANTIDADE]]*tb_investimentos[[#This Row],[PREÇO MERCADO]],"") | S121: =IFERROR(tb_investimentos[[#This Row],[VALOR TOTAL MERCADO]]-tb_investimentos[[#This Row],[VALOR TOTAL PONDERADO]],"") | T121: =IFERROR(_xlfn.XLOOKUP(tb_investimentos[[#This Row],[DESCRIÇÃO]],'INFO AÇÕES'!E:E,'INFO AÇÕES'!H:H),"") | U121: =IFERROR((tb_investimentos[[#This Row],[VALOR TOTAL MERCADO]]-tb_investimentos[[#This Row],[VALOR TOTAL PONDERADO]])/tb_investimentos[[#This Row],[VALOR TOTAL PONDERADO]],"")
B122: Saídas | C122: 46501 | D122: Aluguel | E122: =IF(tb_investimentos[[#This Row],[TIPO MOVIMENTAÇÃO]]="Aporte",_xlfn.XLOOKUP(tb_investimentos[[#This Row],[DESCRIÇÃO]],'INFO AÇÕES'!E:E,'INFO AÇÕES'!I:I),"BRL") -> BRL | F122: Moradia | G122: 1 | H122: 650 | I122: Banco do Brasil | J122: =H122*G122 -> 650 | K122: NÃO | L122: =MONTH(tb_investimentos[[#This Row],[DATA]]) -> 4 | M122: =YEAR(tb_investimentos[[#This Row],[DATA]]) -> 2027 | N122: =DAY(tb_investimentos[[#This Row],[DATA]]) -> 24 | O122: =SUMIF($D$5:$D$10000, D122, $J$5:$J$10000) / SUMIF($D$5:$D$10000, D122, $G$5:$G$10000) -> 650 | P122: =tb_investimentos[[#This Row],[PREÇO MÉDIO PONDERADO]]*tb_investimentos[[#This Row],[QUANTIDADE]] -> 650 | Q122: =IFERROR(_xlfn.XLOOKUP(tb_investimentos[[#This Row],[DESCRIÇÃO]],tb_acoes[Símbolo do ticker],tb_acoes[Preço]),"") | R122: =IFERROR(tb_investimentos[[#This Row],[QUANTIDADE]]*tb_investimentos[[#This Row],[PREÇO MERCADO]],"") | S122: =IFERROR(tb_investimentos[[#This Row],[VALOR TOTAL MERCADO]]-tb_investimentos[[#This Row],[VALOR TOTAL PONDERADO]],"") | T122: =IFERROR(_xlfn.XLOOKUP(tb_investimentos[[#This Row],[DESCRIÇÃO]],'INFO AÇÕES'!E:E,'INFO AÇÕES'!H:H),"") | U122: =IFERROR((tb_investimentos[[#This Row],[VALOR TOTAL MERCADO]]-tb_investimentos[[#This Row],[VALOR TOTAL PONDERADO]])/tb_investimentos[[#This Row],[VALOR TOTAL PONDERADO]],"")
B123: Saídas | C123: 46505 | D123: Tia Mônica | E123: =IF(tb_investimentos[[#This Row],[TIPO MOVIMENTAÇÃO]]="Aporte",_xlfn.XLOOKUP(tb_investimentos[[#This Row],[DESCRIÇÃO]],'INFO AÇÕES'!E:E,'INFO AÇÕES'!I:I),"BRL") -> BRL | F123: Cuidadora | G123: 1 | H123: 650 | I123: Banco do Brasil | J123: =H123*G123 -> 650 | K123: NÃO | L123: =MONTH(tb_investimentos[[#This Row],[DATA]]) -> 4 | M123: =YEAR(tb_investimentos[[#This Row],[DATA]]) -> 2027 | N123: =DAY(tb_investimentos[[#This Row],[DATA]]) -> 28 | O123: =SUMIF($D$5:$D$10000, D123, $J$5:$J$10000) / SUMIF($D$5:$D$10000, D123, $G$5:$G$10000) -> 650 | P123: =tb_investimentos[[#This Row],[PREÇO MÉDIO PONDERADO]]*tb_investimentos[[#This Row],[QUANTIDADE]] -> 650 | Q123: =IFERROR(_xlfn.XLOOKUP(tb_investimentos[[#This Row],[DESCRIÇÃO]],tb_acoes[Símbolo do ticker],tb_acoes[Preço]),"") | R123: =IFERROR(tb_investimentos[[#This Row],[QUANTIDADE]]*tb_investimentos[[#This Row],[PREÇO MERCADO]],"") | S123: =IFERROR(tb_investimentos[[#This Row],[VALOR TOTAL MERCADO]]-tb_investimentos[[#This Row],[VALOR TOTAL PONDERADO]],"") | T123: =IFERROR(_xlfn.XLOOKUP(tb_investimentos[[#This Row],[DESCRIÇÃO]],'INFO AÇÕES'!E:E,'INFO AÇÕES'!H:H),"") | U123: =IFERROR((tb_investimentos[[#This Row],[VALOR TOTAL MERCADO]]-tb_investimentos[[#This Row],[VALOR TOTAL PONDERADO]])/tb_investimentos[[#This Row],[VALOR TOTAL PONDERADO]],"")
B124: Entradas | C124: 46512 | D124: LoyaltyCom | E124: =IF(tb_investimentos[[#This Row],[TIPO MOVIMENTAÇÃO]]="Aporte",_xlfn.XLOOKUP(tb_investimentos[[#This Row],[DESCRIÇÃO]],'INFO AÇÕES'!E:E,'INFO AÇÕES'!I:I),"BRL") -> BRL | F124: Salário | G124: 1 | H124: 8000 | I124: Banco do Brasil | J124: =H124*G124 -> 8000 | K124: NÃO | L124: =MONTH(tb_investimentos[[#This Row],[DATA]]) -> 5 | M124: =YEAR(tb_investimentos[[#This Row],[DATA]]) -> 2027 | N124: =DAY(tb_investimentos[[#This Row],[DATA]]) -> 5 | O124: =SUMIF($D$5:$D$10000, D124, $J$5:$J$10000) / SUMIF($D$5:$D$10000, D124, $G$5:$G$10000) -> 7801.7949 | P124: =tb_investimentos[[#This Row],[PREÇO MÉDIO PONDERADO]]*tb_investimentos[[#This Row],[QUANTIDADE]] -> 7801.7949 | Q124: =IFERROR(_xlfn.XLOOKUP(tb_investimentos[[#This Row],[DESCRIÇÃO]],tb_acoes[Símbolo do ticker],tb_acoes[Preço]),"") | R124: =IFERROR(tb_investimentos[[#This Row],[QUANTIDADE]]*tb_investimentos[[#This Row],[PREÇO MERCADO]],"") | S124: =IFERROR(tb_investimentos[[#This Row],[VALOR TOTAL MERCADO]]-tb_investimentos[[#This Row],[VALOR TOTAL PONDERADO]],"") | T124: =IFERROR(_xlfn.XLOOKUP(tb_investimentos[[#This Row],[DESCRIÇÃO]],'INFO AÇÕES'!E:E,'INFO AÇÕES'!H:H),"") | U124: =IFERROR((tb_investimentos[[#This Row],[VALOR TOTAL MERCADO]]-tb_investimentos[[#This Row],[VALOR TOTAL PONDERADO]])/tb_investimentos[[#This Row],[VALOR TOTAL PONDERADO]],"")
B125: Entradas | C125: 46512 | D125: Fatec-SP | E125: =IF(tb_investimentos[[#This Row],[TIPO MOVIMENTAÇÃO]]="Aporte",_xlfn.XLOOKUP(tb_investimentos[[#This Row],[DESCRIÇÃO]],'INFO AÇÕES'!E:E,'INFO AÇÕES'!I:I),"BRL") -> BRL | F125: Bolsa Iniciação Científica | G125: 1 | H125: 700 | I125: Banco do Brasil | J125: =H125*G125 -> 700 | K125: NÃO | L125: =MONTH(tb_investimentos[[#This Row],[DATA]]) -> 5 | M125: =YEAR(tb_investimentos[[#This Row],[DATA]]) -> 2027 | N125: =DAY(tb_investimentos[[#This Row],[DATA]]) -> 5 | O125: =SUMIF($D$5:$D$10000, D125, $J$5:$J$10000) / SUMIF($D$5:$D$10000, D125, $G$5:$G$10000) -> 770 | P125: =tb_investimentos[[#This Row],[PREÇO MÉDIO PONDERADO]]*tb_investimentos[[#This Row],[QUANTIDADE]] -> 770 | Q125: =IFERROR(_xlfn.XLOOKUP(tb_investimentos[[#This Row],[DESCRIÇÃO]],tb_acoes[Símbolo do ticker],tb_acoes[Preço]),"") | R125: =IFERROR(tb_investimentos[[#This Row],[QUANTIDADE]]*tb_investimentos[[#This Row],[PREÇO MERCADO]],"") | S125: =IFERROR(tb_investimentos[[#This Row],[VALOR TOTAL MERCADO]]-tb_investimentos[[#This Row],[VALOR TOTAL PONDERADO]],"") | T125: =IFERROR(_xlfn.XLOOKUP(tb_investimentos[[#This Row],[DESCRIÇÃO]],'INFO AÇÕES'!E:E,'INFO AÇÕES'!H:H),"") | U125: =IFERROR((tb_investimentos[[#This Row],[VALOR TOTAL MERCADO]]-tb_investimentos[[#This Row],[VALOR TOTAL PONDERADO]])/tb_investimentos[[#This Row],[VALOR TOTAL PONDERADO]],"")
... B127: Saídas | C127: 46512 | D127: Banco do Brasil | E127: =IF(tb_investimentos[[#This Row],[TIPO MOVIMENTAÇÃO]]="Aporte",_xlfn.XLOOKUP(tb_investimentos[[#This Row],[DESCRIÇÃO]],'INFO AÇÕES'!E:E,'INFO AÇÕES'!I:I),"BRL") -> BRL | F127: Cartão de Crédito | G127: 1 | H127: 500 | I127: Banco do Brasil | J127: =H127*G127 -> 500 | K127: NÃO | L127: =MONTH(tb_investimentos[[#This Row],[DATA]]) -> 5 | M127: =YEAR(tb_investimentos[[#This Row],[DATA]]) -> 2027 | N127: =DAY(tb_investimentos[[#This Row],[DATA]]) -> 5 | O127: =SUMIF($D$5:$D$10000, D127, $J$5:$J$10000) / SUMIF($D$5:$D$10000, D127, $G$5:$G$10000) -> 515.93333 | P127: =tb_investimentos[[#This Row],[PREÇO MÉDIO PONDERADO]]*tb_investimentos[[#This Row],[QUANTIDADE]] -> 515.93333 | Q127: =IFERROR(_xlfn.XLOOKUP(tb_investimentos[[#This Row],[DESCRIÇÃO]],tb_acoes[Símbolo do ticker],tb_acoes[Preço]),"") | R127: =IFERROR(tb_investimentos[[#This Row],[QUANTIDADE]]*tb_investimentos[[#This Row],[PREÇO MERCADO]],"") | S127: =IFERROR(tb_investimentos[[#This Row],[VALOR TOTAL MERCADO]]-tb_investimentos[[#This Row],[VALOR TOTAL PONDERADO]],"") | T127: =IFERROR(_xlfn.XLOOKUP(tb_investimentos[[#This Row],[DESCRIÇÃO]],'INFO AÇÕES'!E:E,'INFO AÇÕES'!H:H),"") | U127: =IFERROR((tb_investimentos[[#This Row],[VALOR TOTAL MERCADO]]-tb_investimentos[[#This Row],[VALOR TOTAL PONDERADO]])/tb_investimentos[[#This Row],[VALOR TOTAL PONDERADO]],"")
...

Sheet Previsão Investimento
M2: Previsto | N2: Realizado | O2: Diferença
L3: % Rendimento Médio | M3: 0.007 | N3: =AVERAGE(O9:O186) -> #DIV/0! | O3: =N3-M3 -> #DIV/0!
L4: Juros Total | M4: =SUMIFS($K$9:$K$186,$P$9:$P$186,"OK") -> 0 | N4: =SUM(L9:L186) -> 0 | O4: =N4-M4 -> 0
L5: Investimento Total | M5: =SUMIFS($G$9:$G$186,$P$9:$P$186,"OK") -> #REF! | N5: =SUM(H9:H186) -> 799.8 | O5: =N5-M5 -> #REF!
L6: Ganho/Perda Capital | N6: =#REF! -> #REF! | O6: =N6-N5 -> #REF!
D8: MÊS | E8: ANO | F8: Meses | G8: PREVISTO Investimento | H8: REALIZADO Investimento | I8: PREVISTO Investimento Acumulado | J8: REALIZADO Investimento Acumulado | K8: PREVISTO Juros | L8: REALIZADO Juros | M8: PREVISTO Juros Acumulado | N8: REALIZADO Juros Acumulado | O8: REALIZADO % Rendimento | P8: STATUS
B9: =DATE(E9,D9,DAY(TODAY())) -> 46322 | C9: =TODAY() -> 46322 | D9: =MONTH(F9) -> 10 | E9: =YEAR(F9) -> 2026 | F9: 46296 | G9: =SUMIFS(#REF!,#REF!,D9,#REF!,E9,#REF!,"SIM")-SUMIFS(#REF!,#REF!,D9,#REF!,E9,#REF!,"SIM",#REF!,"EXTERIOR") -> #REF! | H9: =IF(SUMIFS(tb_investimentos[VALOR TOTAL],tb_investimentos[Ano],E9,tb_investimentos[Mês],D9,tb_investimentos[FEITO?],"SIM",tb_investimentos[TIPO MOVIMENTAÇÃO],"Aporte")=0,"",SUMIFS(tb_investimentos[VALOR TOTAL],tb_investimentos[Ano],E9,tb_investimentos[Mês],D9,tb_investimentos[FEITO?],"SIM",tb_investimentos[TIPO MOVIMENTAÇÃO],"Aporte")) -> 799.8 | I9: =G9 -> #REF! | J9: =H9 -> 799.8 | P9: =IF(B9>C9,"","OK") -> OK | Q9: =P9 -> OK
B10: =DATE(E10,D10,DAY(TODAY())) -> 46353 | C10: =TODAY() -> 46322 | D10: =MONTH(F10) -> 11 | E10: =YEAR(F10) -> 2026 | F10: 46327 | G10: =SUMIFS(#REF!,#REF!,D10,#REF!,E10,#REF!,"SIM")-SUMIFS(#REF!,#REF!,D10,#REF!,E10,#REF!,"SIM",#REF!,"EXTERIOR") -> #REF! | H10: =IF(SUMIFS(tb_investimentos[VALOR TOTAL],tb_investimentos[Ano],E10,tb_investimentos[Mês],D10,tb_investimentos[FEITO?],"SIM",tb_investimentos[TIPO MOVIMENTAÇÃO],"Aporte")=0,"",SUMIFS(tb_investimentos[VALOR TOTAL],tb_investimentos[Ano],E10,tb_investimentos[Mês],D10,tb_investimentos[FEITO?],"SIM",tb_investimentos[TIPO MOVIMENTAÇÃO],"Aporte")) | I10: =G10+I9 -> #REF! | J10: =IF(B10>C10,"",IF(B10>C10,0,SUMIFS(#REF!,#REF!,"<"&DATE(E11,D11,1),#REF!,"sim",#REF!,"<>"&"EXTERIOR"))) | K10: =J9*$M$3 -> 5.5986 | L10: =IF(B10>C10,"",SUMIFS(#REF!,#REF!,D10,#REF!,E10,#REF!,"INVESTIMENTO",#REF!,"SIM")) | M10: =K10+M9 -> 5.5986 | N10: =IFERROR(IF(L10=0,0,L10+N9),"") | O10: =IFERROR(IF(L10=0,"",L10/J9),"") | P10: =IF(B10>C10,"","OK")
B11: =DATE(E11,D11,DAY(TODAY())) -> 46383 | C11: =TODAY() -> 46322 | D11: =MONTH(F11) -> 12 | E11: =YEAR(F11) -> 2026 | F11: 46357 | G11: =SUMIFS(#REF!,#REF!,D11,#REF!,E11,#REF!,"SIM")-SUMIFS(#REF!,#REF!,D11,#REF!,E11,#REF!,"SIM",#REF!,"EXTERIOR") -> #REF! | H11: =IF(SUMIFS(tb_investimentos[VALOR TOTAL],tb_investimentos[Ano],E11,tb_investimentos[Mês],D11,tb_investimentos[FEITO?],"SIM",tb_investimentos[TIPO MOVIMENTAÇÃO],"Aporte")=0,"",SUMIFS(tb_investimentos[VALOR TOTAL],tb_investimentos[Ano],E11,tb_investimentos[Mês],D11,tb_investimentos[FEITO?],"SIM",tb_investimentos[TIPO MOVIMENTAÇÃO],"Aporte")) | I11: =G11+I10 -> #REF! | J11: =IF(B11>C11,"",IF(B11>C11,0,SUMIFS(#REF!,#REF!,"<"&DATE(E12,D12,1),#REF!,"sim",#REF!,"<>"&"EXTERIOR"))) | K11: =J10*$M$3 -> #VALUE! | L11: =IF(B11>C11,"",SUMIFS(#REF!,#REF!,D11,#REF!,E11,#REF!,"INVESTIMENTO",#REF!,"SIM")) | M11: =K11+M10 -> #VALUE! | N11: =IFERROR(IF(L11=0,0,L11+N10),"") | O11: =IFERROR(IF(L11=0,"",L11/J10),"") | P11: =IF(B11>C11,"","OK")
B12: =DATE(E12,D12,DAY(TODAY())) -> 46414 | C12: =TODAY() -> 46322 | D12: =MONTH(F12) -> 1 | E12: =YEAR(F12) -> 2027 | F12: 46388 | G12: =SUMIFS(#REF!,#REF!,D12,#REF!,E12,#REF!,"SIM")-SUMIFS(#REF!,#REF!,D12,#REF!,E12,#REF!,"SIM",#REF!,"EXTERIOR") -> #REF! | H12: =IF(SUMIFS(tb_investimentos[VALOR TOTAL],tb_investimentos[Ano],E12,tb_investimentos[Mês],D12,tb_investimentos[FEITO?],"SIM",tb_investimentos[TIPO MOVIMENTAÇÃO],"Aporte")=0,"",SUMIFS(tb_investimentos[VALOR TOTAL],tb_investimentos[Ano],E12,tb_investimentos[Mês],D12,tb_investimentos[FEITO?],"SIM",tb_investimentos[TIPO MOVIMENTAÇÃO],"Aporte")) | I12: =G12+I11 -> #REF! | J12: =IF(B12>C12,"",IF(B12>C12,0,SUMIFS(#REF!,#REF!,"<"&DATE(E13,D13,1),#REF!,"sim",#REF!,"<>"&"EXTERIOR"))) | K12: =J11*$M$3 -> #VALUE! | L12: =IF(B12>C12,"",SUMIFS(#REF!,#REF!,D12,#REF!,E12,#REF!,"INVESTIMENTO",#REF!,"SIM")) | M12: =K12+M11 -> #VALUE! | N12: =IFERROR(IF(L12=0,0,L12+N11),"") | O12: =IFERROR(IF(L12=0,"",L12/J11),"") | P12: =IF(B12>C12,"","OK")
B13: =DATE(E13,D13,DAY(TODAY())) -> 46445 | C13: =TODAY() -> 46322 | D13: =MONTH(F13) -> 2 | E13: =YEAR(F13) -> 2027 | F13: 46419 | G13: 3000 | H13: =IF(SUMIFS(tb_investimentos[VALOR TOTAL],tb_investimentos[Ano],E13,tb_investimentos[Mês],D13,tb_investimentos[FEITO?],"SIM",tb_investimentos[TIPO MOVIMENTAÇÃO],"Aporte")=0,"",SUMIFS(tb_investimentos[VALOR TOTAL],tb_investimentos[Ano],E13,tb_investimentos[Mês],D13,tb_investimentos[FEITO?],"SIM",tb_investimentos[TIPO MOVIMENTAÇÃO],"Aporte")) | I13: =G13+I12 -> #REF! | J13: =IF(B13>C13,"",IF(B13>C13,0,SUMIFS(#REF!,#REF!,"<"&DATE(E14,D14,1),#REF!,"sim",#REF!,"<>"&"EXTERIOR"))) | K13: =I12*$M$3 -> #REF! | L13: =IF(B13>C13,"",SUMIFS(#REF!,#REF!,D13,#REF!,E13,#REF!,"INVESTIMENTO",#REF!,"SIM")) | M13: =K13+M12 -> #REF! | N13: =IFERROR(IF(L13=0,0,L13+N12),"") | O13: =IFERROR(IF(L13=0,"",L13/J12),"") | P13: =IF(B13>C13,"","OK")
B14: =DATE(E14,D14,DAY(TODAY())) -> 46473 | C14: =TODAY() -> 46322 | D14: =MONTH(F14) -> 3 | E14: =YEAR(F14) -> 2027 | F14: 46447 | G14: =3000+K14 -> #REF! | H14: =IF(SUMIFS(tb_investimentos[VALOR TOTAL],tb_investimentos[Ano],E14,tb_investimentos[Mês],D14,tb_investimentos[FEITO?],"SIM",tb_investimentos[TIPO MOVIMENTAÇÃO],"Aporte")=0,"",SUMIFS(tb_investimentos[VALOR TOTAL],tb_investimentos[Ano],E14,tb_investimentos[Mês],D14,tb_investimentos[FEITO?],"SIM",tb_investimentos[TIPO MOVIMENTAÇÃO],"Aporte")) | I14: =G14+I13 -> #REF! | J14: =IF(B14>C14,"",IF(B14>C14,0,SUMIFS(#REF!,#REF!,"<"&DATE(E15,D15,1),#REF!,"sim",#REF!,"<>"&"EXTERIOR"))) | K14: =I13*$M$3 -> #REF! | L14: =IF(B14>C14,"",SUMIFS(#REF!,#REF!,D14,#REF!,E14,#REF!,"INVESTIMENTO",#REF!,"SIM")) | M14: =K14+M13 -> #REF! | N14: =IFERROR(IF(L14=0,0,L14+N13),"") | O14: =IFERROR(IF(L14=0,"",L14/J13),"") | P14: =IF(B14>C14,"","OK")
B15: =DATE(E15,D15,DAY(TODAY())) -> 46504 | C15: =TODAY() -> 46322 | D15: =MONTH(F15) -> 4 | E15: =YEAR(F15) -> 2027 | F15: 46478 | G15: =3000+K15 -> #REF! | H15: =IF(SUMIFS(tb_investimentos[VALOR TOTAL],tb_investimentos[Ano],E15,tb_investimentos[Mês],D15,tb_investimentos[FEITO?],"SIM",tb_investimentos[TIPO MOVIMENTAÇÃO],"Aporte")=0,"",SUMIFS(tb_investimentos[VALOR TOTAL],tb_investimentos[Ano],E15,tb_investimentos[Mês],D15,tb_investimentos[FEITO?],"SIM",tb_investimentos[TIPO MOVIMENTAÇÃO],"Aporte")) | I15: =G15+I14 -> #REF! | J15: =IF(B15>C15,"",IF(B15>C15,0,SUMIFS(#REF!,#REF!,"<"&DATE(E16,D16,1),#REF!,"sim",#REF!,"<>"&"EXTERIOR"))) | K15: =I14*$M$3 -> #REF! | L15: =IF(B15>C15,"",SUMIFS(#REF!,#REF!,D15,#REF!,E15,#REF!,"INVESTIMENTO",#REF!,"SIM")) | M15: =K15+M14 -> #REF! | N15: =IFERROR(IF(L15=0,0,L15+N14),"") | O15: =IFERROR(IF(L15=0,"",L15/J14),"") | P15: =IF(B15>C15,"","OK")
B16: =DATE(E16,D16,DAY(TODAY())) -> 46534 | C16: =TODAY() -> 46322 | D16: =MONTH(F16) -> 5 | E16: =YEAR(F16) -> 2027 | F16: 46508 | G16: =3000+K16 -> #REF! | H16: =IF(SUMIFS(tb_investimentos[VALOR TOTAL],tb_investimentos[Ano],E16,tb_investimentos[Mês],D16,tb_investimentos[FEITO?],"SIM",tb_investimentos[TIPO MOVIMENTAÇÃO],"Aporte")=0,"",SUMIFS(tb_investimentos[VALOR TOTAL],tb_investimentos[Ano],E16,tb_investimentos[Mês],D16,tb_investimentos[FEITO?],"SIM",tb_investimentos[TIPO MOVIMENTAÇÃO],"Aporte")) | I16: =G16+I15 -> #REF! | J16: =IF(B16>C16,"",IF(B16>C16,0,SUMIFS(#REF!,#REF!,"<"&DATE(E17,D17,1),#REF!,"sim",#REF!,"<>"&"EXTERIOR"))) | K16: =I15*$M$3 -> #REF! | L16: =IF(B16>C16,"",SUMIFS(#REF!,#REF!,D16,#REF!,E16,#REF!,"INVESTIMENTO",#REF!,"SIM")) | M16: =K16+M15 -> #REF! | N16: =IFERROR(IF(L16=0,0,L16+N15),"") | O16: =IFERROR(IF(L16=0,"",L16/J15),"") | P16: =IF(B16>C16,"","OK")
B17: =DATE(E17,D17,DAY(TODAY())) -> 46565 | C17: =TODAY() -> 46322 | D17: =MONTH(F17) -> 6 | E17: =YEAR(F17) -> 2027 | F17: 46539 | G17: =3000+K17 -> #REF! | H17: =IF(B17>C17,"",SUMIFS(#REF!,#REF!,D17,#REF!,E17,#REF!,"SIM")-SUMIFS(#REF!,#REF!,D17,#REF!,E17,#REF!,"SIM",#REF!,"EXTERIOR")) | I17: =G17+I16 -> #REF! | J17: =IF(B17>C17,"",IF(B17>C17,0,SUMIFS(#REF!,#REF!,"<"&DATE(E18,D18,1),#REF!,"sim",#REF!,"<>"&"EXTERIOR"))) | K17: =I16*$M$3 -> #REF! | L17: =IF(B17>C17,"",SUMIFS(#REF!,#REF!,D17,#REF!,E17,#REF!,"INVESTIMENTO",#REF!,"SIM")) | M17: =K17+M16 -> #REF! | N17: =IFERROR(IF(L17=0,0,L17+N16),"") | O17: =IFERROR(IF(L17=0,"",L17/J16),"") | P17: =IF(B17>C17,"","OK")
B18: =DATE(E18,D18,DAY(TODAY())) -> 46595 | C18: =TODAY() -> 46322 | D18: =MONTH(F18) -> 7 | E18: =YEAR(F18) -> 2027 | F18: 46569 | G18: =3000+K18 -> #REF! | H18: =IF(B18>C18,"",SUMIFS(#REF!,#REF!,D18,#REF!,E18,#REF!,"SIM")-SUMIFS(#REF!,#REF!,D18,#REF!,E18,#REF!,"SIM",#REF!,"EXTERIOR")) | I18: =G18+I17 -> #REF! | J18: =IF(B18>C18,"",IF(B18>C18,0,SUMIFS(#REF!,#REF!,"<"&DATE(E19,D19,1),#REF!,"sim",#REF!,"<>"&"EXTERIOR"))) | K18: =I17*$M$3 -> #REF! | L18: =IF(B18>C18,"",SUMIFS(#REF!,#REF!,D18,#REF!,E18,#REF!,"INVESTIMENTO",#REF!,"SIM")) | M18: =K18+M17 -> #REF! | N18: =IFERROR(IF(L18=0,0,L18+N17),"") | O18: =IFERROR(IF(L18=0,"",L18/J17),"") | P18: =IF(B18>C18,"","OK")
B19: =DATE(E19,D19,DAY(TODAY())) -> 46626 | C19: =TODAY() -> 46322 | D19: =MONTH(F19) -> 8 | E19: =YEAR(F19) -> 2027 | F19: 46600 | G19: =3000+K19 -> #REF! | H19: =IF(B19>C19,"",SUMIFS(#REF!,#REF!,D19,#REF!,E19,#REF!,"SIM")-SUMIFS(#REF!,#REF!,D19,#REF!,E19,#REF!,"SIM",#REF!,"EXTERIOR")) | I19: =G19+I18 -> #REF! | J19: =IF(B19>C19,"",IF(B19>C19,0,SUMIFS(#REF!,#REF!,"<"&DATE(E20,D20,1),#REF!,"sim",#REF!,"<>"&"EXTERIOR"))) | K19: =I18*$M$3 -> #REF! | L19: =IF(B19>C19,"",SUMIFS(#REF!,#REF!,D19,#REF!,E19,#REF!,"INVESTIMENTO",#REF!,"SIM")) | M19: =K19+M18 -> #REF! | N19: =IFERROR(IF(L19=0,0,L19+N18),"") | O19: =IFERROR(IF(L19=0,"",L19/J18),"") | P19: =IF(B19>C19,"","OK")
B20: =DATE(E20,D20,DAY(TODAY())) -> 46657 | C20: =TODAY() -> 46322 | D20: =MONTH(F20) -> 9 | E20: =YEAR(F20) -> 2027 | F20: 46631 | G20: =3000+K20 -> #REF! | H20: =IF(B20>C20,"",SUMIFS(#REF!,#REF!,D20,#REF!,E20,#REF!,"SIM")-SUMIFS(#REF!,#REF!,D20,#REF!,E20,#REF!,"SIM",#REF!,"EXTERIOR")) | I20: =G20+I19 -> #REF! | J20: =IF(B20>C20,"",IF(B20>C20,0,SUMIFS(#REF!,#REF!,"<"&DATE(E21,D21,1),#REF!,"sim",#REF!,"<>"&"EXTERIOR"))) | K20: =I19*$M$3 -> #REF! | L20: =IF(B20>C20,"",SUMIFS(#REF!,#REF!,D20,#REF!,E20,#REF!,"INVESTIMENTO",#REF!,"SIM")) | M20: =K20+M19 -> #REF! | N20: =IFERROR(IF(L20=0,0,L20+N19),"") | O20: =IFERROR(IF(L20=0,"",L20/J19),"") | P20: =IF(B20>C20,"","OK")
B21: =DATE(E21,D21,DAY(TODAY())) -> 46687 | C21: =TODAY() -> 46322 | D21: =MONTH(F21) -> 10 | E21: =YEAR(F21) -> 2027 | F21: 46661 | G21: =3000+K21 -> #REF! | H21: =IF(B21>C21,"",SUMIFS(#REF!,#REF!,D21,#REF!,E21,#REF!,"SIM")-SUMIFS(#REF!,#REF!,D21,#REF!,E21,#REF!,"SIM",#REF!,"EXTERIOR")) | I21: =G21+I20 -> #REF! | J21: =IF(B21>C21,"",IF(B21>C21,0,SUMIFS(#REF!,#REF!,"<"&DATE(E22,D22,1),#REF!,"sim",#REF!,"<>"&"EXTERIOR"))) | K21: =I20*$M$3 -> #REF! | L21: =IF(B21>C21,"",SUMIFS(#REF!,#REF!,D21,#REF!,E21,#REF!,"INVESTIMENTO",#REF!,"SIM")) | M21: =K21+M20 -> #REF! | N21: =IFERROR(IF(L21=0,0,L21+N20),"") | O21: =IFERROR(IF(L21=0,"",L21/J20),"") | P21: =IF(B21>C21,"","OK")
B22: =DATE(E22,D22,DAY(TODAY())) -> 46718 | C22: =TODAY() -> 46322 | D22: =MONTH(F22) -> 11 | E22: =YEAR(F22) -> 2027 | F22: 46692 | G22: =3000+K22 -> #REF! | H22: =IF(B22>C22,"",SUMIFS(#REF!,#REF!,D22,#REF!,E22,#REF!,"SIM")-SUMIFS(#REF!,#REF!,D22,#REF!,E22,#REF!,"SIM",#REF!,"EXTERIOR")) | I22: =G22+I21 -> #REF! | J22: =IF(B22>C22,"",IF(B22>C22,0,SUMIFS(#REF!,#REF!,"<"&DATE(E23,D23,1),#REF!,"sim",#REF!,"<>"&"EXTERIOR"))) | K22: =I21*$M$3 -> #REF! | L22: =IF(B22>C22,"",SUMIFS(#REF!,#REF!,D22,#REF!,E22,#REF!,"INVESTIMENTO",#REF!,"SIM")) | M22: =K22+M21 -> #REF! | N22: =IFERROR(IF(L22=0,0,L22+N21),"") | O22: =IFERROR(IF(L22=0,"",L22/J21),"") | P22: =IF(B22>C22,"","OK")
B23: =DATE(E23,D23,DAY(TODAY())) -> 46748 | C23: =TODAY() -> 46322 | D23: =MONTH(F23) -> 12 | E23: =YEAR(F23) -> 2027 | F23: 46722 | G23: =3000+K23 -> #REF! | H23: =IF(B23>C23,"",SUMIFS(#REF!,#REF!,D23,#REF!,E23,#REF!,"SIM")-SUMIFS(#REF!,#REF!,D23,#REF!,E23,#REF!,"SIM",#REF!,"EXTERIOR")) | I23: =G23+I22 -> #REF! | J23: =IF(B23>C23,"",IF(B23>C23,0,SUMIFS(#REF!,#REF!,"<"&DATE(E24,D24,1),#REF!,"sim",#REF!,"<>"&"EXTERIOR"))) | K23: =I22*$M$3 -> #REF! | L23: =IF(B23>C23,"",SUMIFS(#REF!,#REF!,D23,#REF!,E23,#REF!,"INVESTIMENTO",#REF!,"SIM")) | M23: =K23+M22 -> #REF! | N23: =IFERROR(IF(L23=0,0,L23+N22),"") | O23: =IFERROR(IF(L23=0,"",L23/J22),"") | P23: =IF(B23>C23,"","OK")
B24: =DATE(E24,D24,DAY(TODAY())) -> 46779 | C24: =TODAY() -> 46322 | D24: =MONTH(F24) -> 1 | E24: =YEAR(F24) -> 2028 | F24: 46753 | G24: =3000+K24 -> #REF! | H24: =IF(B24>C24,"",SUMIFS(#REF!,#REF!,D24,#REF!,E24,#REF!,"SIM")-SUMIFS(#REF!,#REF!,D24,#REF!,E24,#REF!,"SIM",#REF!,"EXTERIOR")) | I24: =G24+I23 -> #REF! | J24: =IF(B24>C24,"",IF(B24>C24,0,SUMIFS(#REF!,#REF!,"<"&DATE(E25,D25,1),#REF!,"sim",#REF!,"<>"&"EXTERIOR"))) | K24: =I23*$M$3 -> #REF! | L24: =IF(B24>C24,"",SUMIFS(#REF!,#REF!,D24,#REF!,E24,#REF!,"INVESTIMENTO",#REF!,"SIM")) | M24: =K24+M23 -> #REF! | N24: =IFERROR(IF(L24=0,0,L24+N23),"") | O24: =IFERROR(IF(L24=0,"",L24/J23),"") | P24: =IF(B24>C24,"","OK")
B25: =DATE(E25,D25,DAY(TODAY())) -> 46810 | C25: =TODAY() -> 46322 | D25: =MONTH(F25) -> 2 | E25: =YEAR(F25) -> 2028 | F25: 46784 | G25: =3000+K25 -> #REF! | H25: =IF(B25>C25,"",SUMIFS(#REF!,#REF!,D25,#REF!,E25,#REF!,"SIM")-SUMIFS(#REF!,#REF!,D25,#REF!,E25,#REF!,"SIM",#REF!,"EXTERIOR")) | I25: =G25+I24 -> #REF! | J25: =IF(B25>C25,"",IF(B25>C25,0,SUMIFS(#REF!,#REF!,"<"&DATE(E26,D26,1),#REF!,"sim",#REF!,"<>"&"EXTERIOR"))) | K25: =I24*$M$3 -> #REF! | L25: =IF(B25>C25,"",SUMIFS(#REF!,#REF!,D25,#REF!,E25,#REF!,"INVESTIMENTO",#REF!,"SIM")) | M25: =K25+M24 -> #REF! | N25: =IFERROR(IF(L25=0,0,L25+N24),"") | O25: =IFERROR(IF(L25=0,"",L25/J24),"") | P25: =IF(B25>C25,"","OK")
B26: =DATE(E26,D26,DAY(TODAY())) -> 46839 | C26: =TODAY() -> 46322 | D26: =MONTH(F26) -> 3 | E26: =YEAR(F26) -> 2028 | F26: 46813 | G26: =3000+K26 -> #REF! | H26: =IF(B26>C26,"",SUMIFS(#REF!,#REF!,D26,#REF!,E26,#REF!,"SIM")-SUMIFS(#REF!,#REF!,D26,#REF!,E26,#REF!,"SIM",#REF!,"EXTERIOR")) | I26: =G26+I25 -> #REF! | J26: =IF(B26>C26,"",IF(B26>C26,0,SUMIFS(#REF!,#REF!,"<"&DATE(E27,D27,1),#REF!,"sim",#REF!,"<>"&"EXTERIOR"))) | K26: =I25*$M$3 -> #REF! | L26: =IF(B26>C26,"",SUMIFS(#REF!,#REF!,D26,#REF!,E26,#REF!,"INVESTIMENTO",#REF!,"SIM")) | M26: =K26+M25 -> #REF! | N26: =IFERROR(IF(L26=0,0,L26+N25),"") | O26: =IFERROR(IF(L26=0,"",L26/J25),"") | P26: =IF(B26>C26,"","OK")
B27: =DATE(E27,D27,DAY(TODAY())) -> 46870 | C27: =TODAY() -> 46322 | D27: =MONTH(F27) -> 4 | E27: =YEAR(F27) -> 2028 | F27: 46844 | G27: =3000+K27 -> #REF! | H27: =IF(B27>C27,"",SUMIFS(#REF!,#REF!,D27,#REF!,E27,#REF!,"SIM")-SUMIFS(#REF!,#REF!,D27,#REF!,E27,#REF!,"SIM",#REF!,"EXTERIOR")) | I27: =G27+I26 -> #REF! | J27: =IF(B27>C27,"",IF(B27>C27,0,SUMIFS(#REF!,#REF!,"<"&DATE(E28,D28,1),#REF!,"sim",#REF!,"<>"&"EXTERIOR"))) | K27: =I26*$M$3 -> #REF! | L27: =IF(B27>C27,"",SUMIFS(#REF!,#REF!,D27,#REF!,E27,#REF!,"INVESTIMENTO",#REF!,"SIM")) | M27: =K27+M26 -> #REF! | N27: =IFERROR(IF(L27=0,0,L27+N26),"") | O27: =IFERROR(IF(L27=0,"",L27/J26),"") | P27: =IF(B27>C27,"","OK")
B28: =DATE(E28,D28,DAY(TODAY())) -> 46900 | C28: =TODAY() -> 46322 | D28: =MONTH(F28) -> 5 | E28: =YEAR(F28) -> 2028 | F28: 46874 | G28: =3000+K28 -> #REF! | H28: =IF(B28>C28,"",SUMIFS(#REF!,#REF!,D28,#REF!,E28,#REF!,"SIM")-SUMIFS(#REF!,#REF!,D28,#REF!,E28,#REF!,"SIM",#REF!,"EXTERIOR")) | I28: =G28+I27 -> #REF! | J28: =IF(B28>C28,"",IF(B28>C28,0,SUMIFS(#REF!,#REF!,"<"&DATE(E29,D29,1),#REF!,"sim",#REF!,"<>"&"EXTERIOR"))) | K28: =I27*$M$3 -> #REF! | L28: =IF(B28>C28,"",SUMIFS(#REF!,#REF!,D28,#REF!,E28,#REF!,"INVESTIMENTO",#REF!,"SIM")) | M28: =K28+M27 -> #REF! | N28: =IFERROR(IF(L28=0,0,L28+N27),"") | O28: =IFERROR(IF(L28=0,"",L28/J27),"") | P28: =IF(B28>C28,"","OK")
... B186: =DATE(E186,D186,DAY(TODAY())) -> 51709 | C186: =TODAY() -> 46322 | D186: =MONTH(F186) -> 7 | E186: =YEAR(F186) -> 2041 | F186: 51683 | G186: =3000+K186 -> #REF! | H186: =IF(B186>C186,"",SUMIFS(#REF!,#REF!,D186,#REF!,E186,#REF!,"SIM")-SUMIFS(#REF!,#REF!,D186,#REF!,E186,#REF!,"SIM",#REF!,"EXTERIOR")) | I186: =G186+I185 -> #REF! | J186: =IF(B186>C186,"",IF(B186>C186,0,SUMIFS(#REF!,#REF!,"<"&DATE(E187,D187,1),#REF!,"sim",#REF!,"<>"&"EXTERIOR"))) | K186: =I185*$M$3 -> #REF! | L186: =IF(B186>C186,"",SUMIFS(#REF!,#REF!,D186,#REF!,E186,#REF!,"INVESTIMENTO",#REF!,"SIM")) | M186: =K186+M185 -> #REF! | N186: =IFERROR(IF(L186=0,0,L186+N185),"") | O186: =IFERROR(IF(L186=0,"",L186/J185),"") | P186: =IF(B186>C186,"","OK")
